Workbook
Name Class_IMC: 'Cleaned_data (Eng)'!$D$1
Name Class_IMC: 'Données nettoyées (Fr)'!$D$1

Sheet Sheet1
A1: D | B1: Gender | C1: BirthComor | D1: BMI measure | E1: BMI | F1: Vacstat | G1: Date 1 | H1: Date 2 | I1: Age | J1: Class | K1: Infected prior to vaccination | L1: Quantivac at 28 days | M1: Q 28 Result | N1: ODQ28Days | O1: NCPat28 days | P1: N28Results | Q1: Quantivacat3 months | R1: Q3 Result | S1: ODQ4months | T1: NCPat3months | U1: N3Result | V1: Quantivacat7months | W1: Q7Result | X1: ODQ7months | Y1: NCPat7months | Z1: N7Result | AA1: Time | AB1: Status | AC1: TruncatedTiter
A2: US-050 | B2: Female | C2: NA | D2: 22.8 | E2: Overweight | F2: Non Vaccinated | G2: =#N/A -> #N/A | H2: =#N/A -> #N/A | I2: 12 | J2: S1 | K2: N | L2: 0.1679 | M2: N | N2: 0.031 | O2: 0.7099 | P2: N | Q2: >120 | R2: R | S2: 0.958 | T2: 6.4746 | U2: R | V2: >120 | W2: R | X2: 0.589 | Y2: 3.3545 | Z2: R | AA2: 210 | AB2: 0
A3: US-509 | B3: M | C3: N | D3: 17 | E3: Normal Weight | F3: Non Vaccinated | G3: =#N/A -> #N/A | H3: =#N/A -> #N/A | I3: 12 | J3: S1 | K3: N | L3: 0.3747 | M3: N | N3: 0.035 | O3: 1.6594 | P3: R | Q3: >120 | R3: R | S3: 0.482 | T3: 6.2601 | U3: R | V3: >120 | W3: R | X3: 2.847 | Y3: 2.3946 | Z3: R | AA3: 210 | AB3: 0
A4: US-063 | B4: Female | C4: N | D4: 14.4 | E4: Underweight | F4: Non Vaccinated | G4: =#N/A -> #N/A | H4: =#N/A -> #N/A | I4: 12 | J4: S1 | K4: N | L4: 0.1022 | M4: N | N4: 0.037 | O4: 0.5253 | P4: N | Q4: >120 | R4: R | S4: 0.857 | T4: 0.2737 | U4: N | V4: >120 | W4: R | X4: 0.499 | Y4: 0.1885 | Z4: N | AA4: 210 | AB4: 0
A5: US-188 | B5: M | C5: NA | D5: 21.4 | E5: Normal Weight | F5: Non Vaccinated | G5: =#N/A -> #N/A | H5: =#N/A -> #N/A | I5: 15 | J5: S4 | K5: N | L5: 0.2861 | M5: N | N5: 0.038 | O5: 0.298 | P5: N | Q5: ***** | R5: * | S5: 0.737 | T5: 2.0179 | U5: R | V5: >120 | W5: R | X5: 0.43 | Y5: 0.6488 | Z5: N | AA5: 210 | AB5: 0
A6: US-286 | B6: M | C6: NA | D6: 33.2 | E6: Obese | F6: Non Vaccinated | G6: =#N/A -> #N/A | H6: =#N/A -> #N/A | I6: 15 | J6: S4 | K6: N | L6: 0.3317 | M6: N | N6: 0.038 | O6: 0.528 | P6: N | Q6: >120 | R6: R | S6: 3.392 | T6: 0.3179 | U6: N | V6: >120 | W6: R | X6: 3.2 | Y6: 0.1482 | Z6: N | AA6: 210 | AB6: 0
A7: US-116 | B7: Female | C7: Y | D7: 25.5 | E7: Overweight | F7: Non Vaccinated | G7: =#N/A -> #N/A | H7: =#N/A -> #N/A | I7: 14 | J7: S4 | K7: N | L7: 0.2117 | M7: N | N7: 0.04 | O7: 0.1868 | P7: N | Q7: 0.2649 | R7: N | S7: 0.05 | T7: 0.083 | U7: N | V7: 0.0426 | W7: N | X7: 0.031 | Y7: 0.1496 | Z7: N
A8: US-544 | B8: Female | C8: N | D8: 17.6 | E8: Normal Weight | F8: Non Vaccinated | G8: =#N/A -> #N/A | H8: =#N/A -> #N/A | I8: 12 | J8: S1 | K8: N | L8: 0.1797 | M8: N | N8: 0.041 | O8: 1.2327 | P8: R | Q8: >120 | R8: R | S8: 1.84 | T8: 0.5941 | U8: N | V8: >120 | W8: R | X8: 1.691 | Y8: 6.0625 | Z8: R | AA8: 210 | AB8: 0
A9: US-551 | B9: M | C9: NA | D9: 22.1 | E9: Overweight | F9: Non Vaccinated | G9: =#N/A -> #N/A | H9: =#N/A -> #N/A | I9: 12 | J9: S1 | K9: N | L9: 0.2709 | M9: N | N9: 0.045 | O9: 1.1834 | P9: R | Q9: >120 | R9: R | S9: 0.321 | T9: 6.1808 | U9: R | V9: ***** | W9: * | X9: 2.068 | Y9: 1.9138/1.8862 | Z9: R | AA9: 210 | AB9: 0
A10: US-231 | B10: M | C10: Y | D10: 26.3 | E10: Overweight | F10: Vaccinated | G10: 44453 | H10: 44476 | I10: 15 | J10: S4 | K10: R | L10: 4.4375 | M10: N | N10: 0.045 | O10: 1.1459 | P10: N | Q10: >120 | R10: R | S10: 3.329 | T10: 4.2489 | U10: R | V10: ***** | W10: * | X10: 2.835 | Y10: 1.7662/1.6430 | Z10: R | AA10: 210 | AB10: 0
A11: US-547 | B11: M | C11: NA | D11: 21.4 | E11: Overweight | F11: Non Vaccinated | G11: =#N/A -> #N/A | H11: =#N/A -> #N/A | I11: 12 | J11: S1 | K11: N | L11: 0.2937 | M11: N | N11: 0.046 | O11: 1.9888 | P11: R | Q11: ***** | R11: * | S11: 2.559 | T11: 7.1226 | U11: R | V11: >120 | W11: R | X11: 1.132 | Y11: 4.0134 | Z11: R | AA11: 210 | AB11: 0
A12: US-530 | B12: M | C12: N | D12: 20.1 | E12: Normal Weight | F12: Non Vaccinated | G12: =#N/A -> #N/A | H12: =#N/A -> #N/A | I12: 15 | J12: S4 | K12: N | L12: 0.665 | M12: N | N12: 0.048 | O12: 1.1387 | P12: R | Q12: ***** | R12: * | S12: 0.033 | T12: 0.9011 | U12: N | V12: >120 | W12: R | X12: 1.945 | Y12: 0.6033 | Z12: N | AA12: 210 | AB12: 0
A13: US-149 | B13: M | C13: N | D13: 18.6 | E13: Normal Weight | F13: Non Vaccinated | G13: =#N/A -> #N/A | H13: =#N/A -> #N/A | I13: 12 | J13: S1 | K13: N | L13: 0.365 | M13: N | N13: 0.052 | O13: 0.0831/0.0814 | P13: N | Q13: >120 | R13: R | S13: 3.376 | T13: 0.1192 | U13: N | V13: >120 | W13: R | X13: 2.346 | Y13: 2.2869 | Z13: R | AA13: 210 | AB13: 0
A14: US-433 | B14: Female | C14: Y | D14: 30.8 | E14: Obese | F14: Non Vaccinated | G14: =#N/A -> #N/A | H14: =#N/A -> #N/A | I14: 15 | J14: S4 | K14: N | L14: 0.7767 | M14: N | N14: 0.053 | O14: 0.537 | P14: N | Q14: >120 | R14: R | S14: 1.131 | T14: 7.0446 | U14: N | V14: >120 | W14: R | X14: 0.732 | Y14: 1.6983 | Z14: R | AA14: 210 | AB14: 0
A15: US-258 | B15: M | C15: N | D15: 17.8 | E15: Normal Weight | F15: Non Vaccinated | G15: =#N/A -> #N/A | H15: =#N/A -> #N/A | I15: 12 | J15: S1 | K15: N | L15: 0.6755 | M15: N | N15: 0.056 | O15: 0.1332 | P15: N | Q15: ***** | R15: * | S15: 0.905 | T15: 2.6568 | U15: R | V15: ***** | W15: * | X15: 3.5 | Y15: 2.3841 | Z15: R | AA15: 210 | AB15: 0
A16: US-124 | B16: Female | C16: N | D16: 16.8 | E16: Normal Weight | F16: Non Vaccinated | G16: =#N/A -> #N/A | H16: =#N/A -> #N/A | I16: 15 | J16: S4 | K16: N | L16: 0.3431 | M16: N | N16: 0.057 | O16: 0.3231 | P16: N | Q16: >120 | R16: R | S16: 0.041 | T16: 5.6358 | U16: R | V16: >120 | W16: R | X16: 0.036 | Y16: 3.0553 | Z16: R | AA16: 210 | AB16: 0
A17: US-429 | B17: Female | C17: NA | D17: 16.6 | E17: Normal Weight | F17: Non Vaccinated | G17: =#N/A -> #N/A | H17: =#N/A -> #N/A | I17: 15 | J17: S4 | K17: N | L17: 1 | M17: N | N17: 0.063 | O17: 0.736 | P17: N | Q17: >120 | R17: R | S17: 0.868 | T17: 0.3661 | U17: N | V17: >120 | W17: R | X17: 0.389 | Y17: 3.9966 | Z17: R | AA17: 210 | AB17: 0
A18: US-150 | B18: Female | C18: N | D18: 19.3 | E18: Normal Weight | F18: Non Vaccinated | G18: =#N/A -> #N/A | H18: =#N/A -> #N/A | I18: 12 | J18: S1 | K18: N | L18: 0.4307 | M18: N | N18: 0.064 | O18: 0.4397/0.4511 | P18: N | Q18: >120 | R18: R | S18: 0.128 | T18: 0.3466 | U18: N | V18: >120 | W18: R | X18: 0.146 | Y18: 4.1619 | Z18: R | AA18: 210 | AB18: 0
A19: US-493 | B19: Female | C19: NA | D19: 21.2 | E19: Normal Weight | F19: Non Vaccinated | G19: =#N/A -> #N/A | H19: =#N/A -> #N/A | I19: 12 | J19: S1 | K19: N | L19: 1.0447 | M19: N | N19: 0.065 | O19: 2.6629 | P19: R | Q19: >120 | R19: R | S19: 0.26 | T19: 5.6682 | U19: R | V19: >120 | W19: R | X19: 0.196 | Y19: 3.5558 | Z19: R | AA19: 210 | AB19: 0
A20: US-255 | B20: M | C20: NA | D20: 21.9 | E20: Overweight | F20: Non Vaccinated | G20: =#N/A -> #N/A | H20: =#N/A -> #N/A | I20: 12 | J20: S1 | K20: N | L20: 0.8702 | M20: N | N20: 0.065 | O20: 0.0699 | P20: N | Q20: 17.0308 | R20: R | S20: 0.606 | T20: 0.9958 | U20: N | V20: ***** | W20: * | X20: 0.506 | Y20: 0.524 | Z20: N | AA20: 92 | AB20: 1
A21: US-134 | B21: Female | C21: N | D21: 25.9 | E21: Overweight | F21: Non Vaccinated | G21: =#N/A -> #N/A | H21: =#N/A -> #N/A | I21: 15 | J21: S4 | K21: R | L21: 0.5182 | M21: N | N21: 0.065 | O21: 0.2593 | P21: N | Q21: >120 | R21: R | S21: 0.384 | T21: 0.1082 | U21: N | V21: ***** | W21: * | X21: 1.256 | Y21: 3.0861 | Z21: R | AA21: 210 | AB21: 0
A22: US-137 | B22: Female | C22: NA | D22: 17.1 | E22: Normal Weight | F22: Non Vaccinated | G22: =#N/A -> #N/A | H22: =#N/A -> #N/A | I22: 14 | J22: S4 | K22: N | L22: 0.6058 | M22: N | N22: 0.067 | O22: 0.3978 | P22: N | Q22: >120 | R22: R | S22: 0.403 | T22: 0.0861 | U22: N | V22: ***** | W22: * | X22: 0.479 | Y22: 1.9324 | Z22: R | AA22: 210 | AB22: 0
A23: US-229 | B23: Female | C23: N | D23: 34.2 | E23: Obese | F23: Non Vaccinated | G23: =#N/A -> #N/A | H23: =#N/A -> #N/A | I23: 11 | J23: S1 | K23: N | L23: 1.0216 | M23: N | N23: 0.072 | O23: 0.1416 | P23: N | Q23: ***** | R23: * | S23: 0.745 | T23: 1.7825 | U23: R | V23: ***** | W23: * | X23: 2.678 | Y23: 6.219 | Z23: R | AA23: 210 | AB23: 0
A24: US-573 | B24: Female | C24: N | D24: 22.3 | E24: Overweight | F24: Non Vaccinated | G24: =#N/A -> #N/A | H24: =#N/A -> #N/A | I24: 12 | J24: S1 | K24: N | L24: 0.9089 | M24: N | N24: 0.073 | O24: 1.6025 | P24: R | Q24: >120 | R24: R | S24: 0.051 | T24: 0.6138 | U24: N | V24: >120 | W24: R | X24: 0.073 | Y24: 0.25 | Z24: N | AA24: 210 | AB24: 0
A25: US-048 | B25: M | C25: N | D25: 28.6 | E25: Obese | F25: Non Vaccinated | G25: =#N/A -> #N/A | H25: =#N/A -> #N/A | I25: 15 | J25: S4 | K25: N | L25: 1.1533 | M25: N | N25: 0.074 | O25: 0.4571 | P25: N | Q25: ***** | R25: * | S25: 0.077 | T25: 1.479 | U25: R | V25: ***** | W25: * | X25: 1.246 | Y25: 1.2029 | Z25: R | AA25: 210 | AB25: 0
A26: US-066 | B26: Female | C26: N | D26: 17.2 | E26: Normal Weight | F26: Non Vaccinated | G26: =#N/A -> #N/A | H26: =#N/A -> #N/A | I26: 12 | J26: S1 | K26: N | L26: 1.1533 | M26: N | N26: 0.089 | O26: 0.2923 | P26: N | Q26: ***** | R26: * | S26: 0.684 | T26: 3.0044 | U26: R | V26: ***** | W26: * | X26: 0.365 | Y26: 1.3504 | Z26: R | AA26: 210 | AB26: 0
A27: US-169 | B27: Female | C27: N | D27: 27.2 | E27: Overweight | F27: Non Vaccinated | G27: =#N/A -> #N/A | H27: =#N/A -> #N/A | I27: 15 | J27: S4 | K27: R | L27: 1.3894 | M27: N | N27: 0.089 | O27: 0.0586 | P27: N | Q27: >120 | R27: R | S27: 3.5 | T27: 5.0045 | U27: R | V27: 60.0531 | W27: R | X27: 2.813 | Y27: 1.8802 | Z27: R
A28: US-512 | B28: M | C28: NA | D28: 16.4 | E28: Normal Weight | F28: Non Vaccinated | G28: =#N/A -> #N/A | H28: =#N/A -> #N/A | I28: 12 | J28: S1 | K28: R | L28: 1.8263 | M28: N | N28: 0.1 | O28: 3.059 | P28: R | Q28: 45.4201 | R28: R | S28: 0.207 | T28: 1.6463 | U28: R | V28: 97.9592 | W28: R | X28: 0.218 | Y28: 5.7516 | Z28: R
A29: US-004 | B29: M | C29: N | D29: 16.8 | E29: Normal Weight | F29: Non Vaccinated | G29: =#N/A -> #N/A | H29: =#N/A -> #N/A | I29: 12 | J29: S1 | K29: N | L29: 1.1752 | M29: N | N29: 0.101 | O29: 0.9143 | P29: N | Q29: ***** | R29: * | S29: 1.45 | T29: 0.5828 | U29: N | V29: >120 | W29: R | X29: 0.972 | Y29: 0.416 | Z29: N | AA29: 210 | AB29: 0
A30: US-042 | B30: Female | C30: NA | D30: 19.5 | E30: Normal Weight | F30: Non Vaccinated | G30: =#N/A -> #N/A | H30: =#N/A -> #N/A | I30: 15 | J30: S4 | K30: N | L30: 1.5474 | M30: N | N30: 0.152 | O30: 0.3495 | P30: N | Q30: ***** | R30: * | S30: 0.114 | T30: 2.0442 | U30: R | V30: ***** | W30: * | X30: 0.142 | Y30: 5.2398 | Z30: R | AA30: 210 | AB30: 0
A31: US-100 | B31: Female | C31: Y | D31: 37.7 | E31: Obese | F31: Non Vaccinated | G31: =#N/A -> #N/A | H31: =#N/A -> #N/A | I31: 15 | J31: S4 | K31: R | L31: 3.6058 | M31: N | N31: 0.2 | O31: 0.4725 | P31: N | Q31: >120 | R31: R | S31: 2.5 | T31: 0.4194 | U31: N | V31: ***** | W31: * | X31: 1.843 | Y31: 1.2684 | Z31: R | AA31: 210 | AB31: 0
A32: US-484 | B32: Female | C32: Y | D32: 20.5 | E32: Normal Weight | F32: Non Vaccinated | G32: =#N/A -> #N/A | H32: =#N/A -> #N/A | I32: 12 | J32: S1 | K32: N | L32: 4.1935 | M32: N | N32: 0.206 | O32: 1.3844 | P32: R | Q32: >120 | R32: R | S32: 0.068 | T32: 1.2466 | U32: R | V32: >120 | W32: R | X32: 0.067 | Y32: 5.7789 | Z32: R | AA32: 210 | AB32: 0
A33: US-453 | B33: Female | C33: N | D33: 18.8 | E33: Normal Weight | F33: Non Vaccinated | G33: =#N/A -> #N/A | H33: =#N/A -> #N/A | I33: 14 | J33: S4 | K33: N | L33: 4.7742 | M33: N | N33: 0.232 | O33: 1.8154 | P33: R | Q33: 48.7591 | R33: R | S33: 3.421 | T33: 1.5938 | U33: R | V33: 37.8616 | W33: R | X33: 3.397 | Y33: 0.8293 | Z33: N
A34: US-082 | B34: M | C34: N | D34: 18.4 | E34: Normal Weight | F34: Non Vaccinated | G34: =#N/A -> #N/A | H34: =#N/A -> #N/A | I34: 15 | J34: S4 | K34: N | L34: 6.0146 | M34: N | N34: 0.292 | O34: 0.2923 | P34: N | Q34: 22.6736 | R34: R | S34: 0.382 | T34: 2.8168 | U34: R | V34: 14.0227 | W34: R | X34: 1.631 | Y34: 1.1209 | Z34: R
A35: US-543 | B35: Female | C35: N | D35: 17.2 | E35: Normal Weight | F35: Non Vaccinated | G35: =#N/A -> #N/A | H35: =#N/A -> #N/A | I35: 12 | J35: S1 | K35: N | L35: 7.0608 | M35: N | N35: 0.343 | O35: 3.0045 | P35: R | Q35: ***** | R35: * | S35: 0.256 | T35: 1.8034 | U35: R | V35: ***** | W35: * | X35: 2.683 | Y35: 6.846 | Z35: R | AA35: 210 | AB35: 0
A36: US-118 | B36: Female | C36: Y | D36: 18.1 | E36: Normal Weight | F36: Non Vaccinated | G36: =#N/A -> #N/A | H36: =#N/A -> #N/A | I36: 15 | J36: S4 | K36: R | L36: 7.7226 | M36: N | N36: 0.36 | O36: 0.6769 | P36: N | Q36: 7.5745 | R36: N | S36: 0.38 | T36: 0.4415 | U36: N | V36: >120 | W36: R | X36: 3.023 | Y36: 6.5984 | Z36: R
A37: US-526 | B37: M | C37: NA | D37: 21.7 | E37: Normal Weight | F37: Non Vaccinated | G37: =#N/A -> #N/A | H37: =#N/A -> #N/A | I37: 15 | J37: S4 | K37: R | L37: 8.9727 | M37: ? | N37: 0.42 | O37: 1.2052 | P37: R | Q37: >120 | R37: R | S37: 2.78 | T37: 5.0761 | U37: R | V37: >120 | W37: R | X37: 1.221 | Y37: 2.4363 | Z37: R | AA37: 210 | AB37: 0
A38: US-440 | B38: Female | C38: N | D38: 18 | E38: Normal Weight | F38: Non Vaccinated | G38: =#N/A -> #N/A | H38: =#N/A -> #N/A | I38: 15 | J38: S4 | K38: R | L38: 9.5533 | M38: ? | N38: 0.446 | O38: 0.0909 | P38: N | Q38: >120 | R38: R | S38: 0.251 | T38: 1.308 | U38: N | V38: 34.5493 | W38: R | X38: 1.774 | Y38: 0.7414 | Z38: N
A39: US-024 | B39: M | C39: N | D39: 19.8 | E39: Normal Weight | F39: Non Vaccinated | G39: =#N/A -> #N/A | H39: =#N/A -> #N/A | I39: 12 | J39: S1 | K39: N | L39: 9.9124 | M39: ? | N39: 0.47 | O39: 0.8635/0.7942 | P39: N | Q39: >120 | R39: R | S39: 2.322 | T39: 2.8295 | U39: R | V39: >120 | W39: R | X39: 1.453 | Y39: 0.5678 | Z39: N | AA39: 210 | AB39: 0
A40: US-101 | B40: M | C40: N | D40: 21.5 | E40: Normal Weight | F40: Non Vaccinated | G40: =#N/A -> #N/A | H40: =#N/A -> #N/A | I40: 14 | J40: S4 | K40: R | L40: 9.6496 | M40: ? | N40: 0.486 | O40: 0.3275 | P40: N | Q40: >120 | R40: R | S40: 3.374 | T40: 0.1649 | U40: N | V40: ***** | W40: * | X40: 1.898 | Y40: 1.334 | Z40: R | AA40: 210 | AB40: 0
A41: US-223 | B41: Female | C41: N | D41: 20.7 | E41: Normal Weight | F41: Non Vaccinated | G41: =#N/A -> #N/A | H41: =#N/A -> #N/A | I41: 12 | J41: S1 | K41: N | L41: 10.7494 | M41: ? | N41: 0.516 | O41: 0.1142/0.1797 | P41: N | Q41: >120 | R41: R | S41: 2.828 | T41: 0.1256 | U41: N | V41: 107.1762 | W41: R | X41: 1.705 | Y41: 0.093 | Z41: N | AA41: 182 | AB41: 1
A42: US-287 | B42: Female | C42: NA | D42: 22.2 | E42: Overweight | F42: Non Vaccinated | G42: =#N/A -> #N/A | H42: =#N/A -> #N/A | I42: 12 | J42: S1 | K42: N | L42: 0.7104 | M42: N | N42: 0.55 | O42: 0.7293 | P42: N | Q42: >120 | R42: R | S42: 0.053 | T42: 0.4442 | U42: N | V42: >120 | W42: R | X42: 0.044 | Y42: 0.2276 | Z42: N | AA42: 210 | AB42: 0
A43: US-019 | B43: Female | C43: Y | D43: 18.8 | E43: Normal Weight | F43: Non Vaccinated | G43: =#N/A -> #N/A | H43: =#N/A -> #N/A | I43: 12 | J43: S1 | K43: N | L43: 13.4584 | M43: R | N43: 0.576 | O43: 1.0515 | P43: N | Q43: >120 | R43: R | S43: 0.57 | T43: 6.0571 | U43: R | V43: >120 | W43: R | X43: 2.605 | Y43: 3.067 | Z43: R | AA43: 210 | AB43: 0
A44: US-184 | B44: M | C44: N | D44: 18.2 | E44: Normal Weight | F44: Non Vaccinated | G44: =#N/A -> #N/A | H44: =#N/A -> #N/A | I44: 15 | J44: S4 | K44: R | L44: 15.814 | M44: R | N44: 0.712 | O44: 0.4642 | P44: N | Q44: ***** | R44: * | S44: 3.462 | T44: 0.5493 | U44: N | V44: >120 | W44: R | X44: 2.835 | Y44: 6.2376 | Z44: R | AA44: 210 | AB44: 0
A45: US-535 | B45: M | C45: N | D45: 15.9 | E45: Normal Weight | F45: Non Vaccinated | G45: =#N/A -> #N/A | H45: =#N/A -> #N/A | I45: 12 | J45: S1 | K45: R | L45: 16.2814 | M45: R | N45: 0.716 | O45: 4.4161 | P45: R | Q45: >120 | R45: R | S45: 2.689 | T45: 5.9366 | U45: R | V45: >120 | W45: R | X45: 3.155 | Y45: 3.7701 | Z45: R
A46: US-165 | B46: M | C46: NA | D46: 16.5 | E46: Normal Weight | F46: Non Vaccinated | G46: =#N/A -> #N/A | H46: =#N/A -> #N/A | I46: 12 | J46: S1 | K46: R | L46: 17.7519 | M46: R | N46: 0.787 | O46: 0.6091 | P46: N | Q46: >120 | R46: R | S46: 3.5 | T46: 0.3722 | U46: N | V46: >120 | W46: R | X46: 2.118 | Y46: 5.7107 | Z46: N | AA46: 210 | AB46: 0
A47: US-518 | B47: M | C47: NA | D47: 21 | E47: Normal Weight | F47: Non Vaccinated | G47: =#N/A -> #N/A | H47: =#N/A -> #N/A | I47: 15 | J47: S4 | K47: N | L47: 18.7186 | M47: R | N47: 0.813 | O47: 4.1943 | P47: R | Q47: >120 | R47: R | S47: 2.793 | T47: 5.7368 | U47: R | V47: ***** | W47: * | X47: 1.61 | Y47: 2.7349 | Z47: R | AA47: 210 | AB47: 0
A48: US-221 | B48: M | C48: N | D48: 19.2 | E48: Normal Weight | F48: Non Vaccinated | G48: =#N/A -> #N/A | H48: =#N/A -> #N/A | I48: 12 | J48: S1 | K48: R | L48: 20.1524 | M48: R | N48: 0.878 | O48: 0.6107 | P48: N | Q48: >120 | R48: R | S48: 0.0738 | T48: 6.2152 | U48: R | V48: ***** | W48: * | X48: 2.979 | Y48: 4.9855 | Z48: R | AA48: 210 | AB48: 0
A49: US-035 | B49: Female | C49: N | D49: 20.8 | E49: Normal Weight | F49: Non Vaccinated | G49: =#N/A -> #N/A | H49: =#N/A -> #N/A | I49: 15 | J49: S4 | K49: R | L49: 24.3443 | M49: R | N49: 0.934 | O49: 0.2176/0.2527 | P49: N | Q49: ***** | R49: * | S49: 2.417 | T49: 4.2185 | U49: R | V49: >120 | W49: R | X49: 1.218 | Y49: 1.3463/1.3074 | Z49: R | AA49: 210 | AB49: 0
A50: US-087 | B50: M | C50: N | D50: 21.6 | E50: Normal Weight | F50: Non Vaccinated | G50: =#N/A -> #N/A | H50: =#N/A -> #N/A | I50: 14 | J50: S4 | K50: R | L50: 26.8306 | M50: R | N50: 1.04 | O50: 0.3538 | P50: N | Q50: 19.3798 | R50: R | S50: 2.908 | T50: 3.7196 | U50: R | V50: 11.4731 | W50: R | X50: 2.248 | Y50: 1.3607 | Z50: R
A51: US-253 | B51: M | C51: NA | D51: 24.2 | E51: Overweight | F51: Non Vaccinated | G51: =#N/A -> #N/A | H51: =#N/A -> #N/A | I51: 12 | J51: S1 | K51: R | L51: 31.6952 | M51: R | N51: 1.181 | O51: 0.0973 | P51: N | Q51: ***** | R51: * | S51: 3.361 | T51: 3.6427 | U51: R | V51: >120 | W51: R | X51: 2.808 | Y51: 1.95 | Z51: R | AA51: 210 | AB51: 0
A52: US-220 | B52: M | C52: NA | D52: 15.5 | E52: Normal Weight | F52: Non Vaccinated | G52: =#N/A -> #N/A | H52: =#N/A -> #N/A | I52: 11 | J52: S1 | K52: R | L52: 32.1524 | M52: R | N52: 1.193 | O52: 0.1726 | P52: N | Q52: ***** | R52: * | S52: 1.092 | T52: 3.5628 | U52: R | V52: ***** | W52: * | X52: 3.452 | Y52: 1.2562 | Z52: R | AA52: 210 | AB52: 0
A53: US-273 | B53: Female | C53: N | D53: 15.9 | E53: Normal Weight | F53: Non Vaccinated | G53: =#N/A -> #N/A | H53: =#N/A -> #N/A | I53: 12 | J53: S1 | K53: R | L53: 28.6196 | M53: R | N53: 1.196 | O53: 0.0633 | P53: N | Q53: >120 | R53: R | S53: 3.334 | T53: 1.8589 | U53: R | V53: >120 | W53: R | X53: 2.075 | Y53: 0.6472 | Z53: N | AA53: 210 | AB53: 0
A54: US-191 | B54: Female | C54: Y | D54: 18.2 | E54: Normal Weight | F54: Non Vaccinated | G54: =#N/A -> #N/A | H54: =#N/A -> #N/A | I54: 15 | J54: S4 | K54: R | L54: 33.2952 | M54: R | N54: 1.223 | O54: 0.0651 | P54: N | Q54: ***** | R54: * | S54: 2.981 | T54: 0.9686 | U54: N | V54: ***** | W54: * | X54: 2.469 | Y54: 3.6942 | Z54: R | AA54: 210 | AB54: 0
A55: US-054 | B55: Female | C55: NA | D55: 17.2 | E55: Normal Weight | F55: Non Vaccinated | G55: =#N/A -> #N/A | H55: =#N/A -> #N/A | I55: 12 | J55: S1 | K55: N | L55: 33.1421 | M55: R | N55: 1.283 | O55: 0.5604 | P55: N | Q55: ***** | R55: * | S55: 3.29 | T55: 6.7726 | U55: R | V55: >120 | W55: R | X55: 2.581 | Y55: 3.6414 | Z55: R | AA55: 210 | AB55: 0
A56: US-532 | B56: M | C56: N | D56: 24.2 | E56: Overweight | F56: Non Vaccinated | G56: =#N/A -> #N/A | H56: =#N/A -> #N/A | I56: 12 | J56: S1 | K56: N | L56: 37.97 | M56: R | N56: 1.404 | O56: 1.3154 | P56: R | Q56: >120 | R56: R | S56: 0.934 | T56: 5.5284 | U56: R | V56: >120 | W56: R | X56: 3.379 | Y56: 1.6347 | Z56: R | AA56: 210 | AB56: 0
A57: US-005 | B57: Female | C57: Y | D57: 16.3 | E57: Normal Weight | F57: Non Vaccinated | G57: =#N/A -> #N/A | H57: =#N/A -> #N/A | I57: 12 | J57: S1 | K57: N | L57: 41.0127 | M57: R | N57: 1.466 | O57: 0.8 | P57: N | Q57: >120 | R57: R | S57: 1.63 | T57: 0.6159 | U57: N | V57: >120 | W57: R | X57: 1.211 | Y57: 0.2254 | Z57: N | AA57: 210 | AB57: 0
A58: US-135 | B58: M | C58: N | D58: 17.4 | E58: Normal Weight | F58: Vaccinated | G58: 44453 | H58: 44476 | I58: 15 | J58: S4 | K58: N | L58: 39.2077 | M58: R | N58: 1.558 | O58: 0.2462 | P58: N | Q58: 8.0638 | R58: ? | S58: 3.5 | T58: 1.0508 | U58: N | V58: 10.9065 | W58: ? | X58: 2.836 | Y58: 0.7643 | Z58: N
A59: US-457 | B59: Female | C59: N | D59: 18 | E59: Normal Weight | F59: Non Vaccinated | G59: =#N/A -> #N/A | H59: =#N/A -> #N/A | I59: 12 | J59: S1 | K59: N | L59: 49.32 | M59: R | N59: 1.674 | O59: 1.5604 | P59: R | Q59: ***** | R59: * | S59: 0.971 | T59: 2.0464 | U59: R | V59: >120 | W59: R | X59: 0.741 | Y59: 1.6107 | Z59: R | AA59: 210 | AB59: 0
A60: US-182 | B60: M | C60: N | D60: 17.4 | E60: Normal Weight | F60: Non Vaccinated | G60: =#N/A -> #N/A | H60: =#N/A -> #N/A | I60: 15 | J60: S4 | K60: N | L60: 54.3849 | M60: R | N60: 1.741 | O60: 0.0961 | P60: N | Q60: >120 | R60: R | S60: 1.249 | T60: 0.6233 | U60: N | V60: >120 | W60: R | X60: 1.093 | Y60: 0.564 | Z60: N | AA60: 210 | AB60: 0
A61: US-280 | B61: Female | C61: N | D61: 35.5 | E61: Obese | F61: Non Vaccinated | G61: =#N/A -> #N/A | H61: =#N/A -> #N/A | I61: 14 | J61: S4 | K61: N | L61: 51.5217 | M61: R | N61: 1.779 | O61: 0.4295 | P61: N | Q61: >120 | R61: R | S61: 3.102 | T61: 0.3642 | U61: N | V61: ***** | W61: * | X61: 2.807 | Y61: 3.3653 | Z61: R | AA61: 210 | AB61: 0
A62: US-292 | B62: Female | C62: N | D62: 25.5 | E62: Overweight | F62: Non Vaccinated | G62: =#N/A -> #N/A | H62: =#N/A -> #N/A | I62: 12 | J62: S1 | K62: R | L62: 64.5652 | M62: R | N62: 2.019 | O62: 0.1477 | P62: N | Q62: ***** | R62: * | S62: 1.466 | T62: 0.5032 | U62: N | V62: >120 | W62: R | X62: 2.407 | Y62: 0.6263 | Z62: N | AA62: 210 | AB62: 0
A63: US-257 | B63: Female | C63: NA | D63: 18.9 | E63: Normal Weight | F63: Non Vaccinated | G63: =#N/A -> #N/A | H63: =#N/A -> #N/A | I63: 12 | J63: S1 | K63: N | L63: 66.1199 | M63: R | N63: 2.02 | O63: 0.2817 | P63: N | Q63: ***** | R63: * | S63: 3.5 | T63: 0.32 | U63: N | V63: >120 | W63: R | X63: 3.5 | Y63: 0.2547 | Z63: N | AA63: 210 | AB63: 0
A64: US-161 | B64: Female | C64: Y | D64: 17.8 | E64: Normal Weight | F64: Non Vaccinated | G64: =#N/A -> #N/A | H64: =#N/A -> #N/A | I64: 11 | J64: S1 | K64: R | L64: 68.7697 | M64: R | N64: 2.083 | O64: 0.158 | P64: N | Q64: ***** | R64: * | S64: 1.405 | T64: 1.5673 | U64: R | V64: 11.8004 | W64: R | X64: 1.043 | Y64: 0.8616 | Z64: N | AA64: 182 | AB64: 1
A65: US-178 | B65: Female | C65: Y | D65: 20.2 | E65: Normal Weight | F65: Non Vaccinated | G65: =#N/A -> #N/A | H65: =#N/A -> #N/A | I65: 15 | J65: S4 | K65: R | L65: 102.3404 | M65: R | N65: 2.455 | O65: 0.0977 | P65: N | Q65: >120 | R65: R | S65: 3.062 | T65: 3.935 | U65: R | V65: >120 | W65: R | X65: 3.5 | Y65: 2.1302 | Z65: R | AA65: 210 | AB65: 0
A66: US-528 | B66: Female | C66: N | D66: 17.9 | E66: Normal Weight | F66: Vaccinated | G66: 44453 | H66: 44476 | I66: 15 | J66: S4 | K66: R | L66: 95.0324 | M66: R | N66: 2.536 | O66: 1.6353/1.6913 | P66: R | Q66: >120 | R66: R | S66: 2.899 | T66: 5.6421 | U66: R | V66: >120 | W66: R | X66: 2.284 | Y66: 2.3967 | Z66: R | AA66: 210 | AB66: 0
A67: US-475 | B67: M | C67: Y | D67: 30.5 | E67: Obese | F67: Vaccinated | G67: 44453 | H67: 44477 | I67: 12 | J67: S1 | K67: N | L67: 101.8575 | M67: R | N67: 2.615 | O67: 2.2622 | P67: R | Q67: 38.1944 | R67: R | S67: 3.5 | T67: 1.5475 | U67: R | V67: 28.2991 | W67: R | X67: 3.417 | Y67: 0.9112/0.8884 | Z67: N
A68: US-216 | B68: Female | C68: NA | D68: 16.2 | E68: Normal Weight | F68: Non Vaccinated | G68: =#N/A -> #N/A | H68: =#N/A -> #N/A | I68: 12 | J68: S1 | K68: N | L68: >120 | M68: R | N68: 2.69 | O68: 0.0635 | P68: N | Q68: ***** | R68: * | S68: 3.378 | T68: 1.8251 | U68: R | V68: >120 | W68: R | X68: 3.017 | Y68: 0.626 | Z68: N | AA68: 210 | AB68: 0
A69: US-416 | B69: Female | C69: NA | D69: 22.9 | E69: Normal Weight | F69: Vaccinated | G69: 44454 | H69: 44476 | I69: 15 | J69: S4 | K69: N | L69: ***** | M69: * | N69: 2.779 | O69: 0.1857 | P69: N | Q69: >120 | R69: R | S69: 3.493 | T69: 1.6384 | U69: R | V69: >120 | W69: R | X69: 3.046 | Y69: 0.9586 | Z69: N | AA69: 210 | AB69: 0
A70: US-545 | B70: Female | C70: NA | D70: 26.3 | E70: Obese | F70: Vaccinated | G70: 44453 | H70: 44476 | I70: 12 | J70: S1 | K70: N | L70: >120 | M70: R | N70: 2.939 | O70: 1.4672 | P70: R | Q70: >120 | R70: R | S70: 2.971 | T70: 6.7209 | U70: R | V70: >120 | W70: R | X70: 3.5 | Y70: 3.904 | Z70: R | AA70: 210 | AB70: 0
A71: US-211 | B71: M | C71: N | D71: 23.7 | E71: Overweight | F71: Vaccinated | G71: 44453 | H71: 44477 | I71: 12 | J71: S1 | K71: R | L71: >120 | M71: R | N71: 2.96 | O71: 0.114 | P71: N | Q71: ***** | R71: * | S71: 3.5 | T71: 2.2197 | U71: R | V71: >120 | W71: R | X71: 3.5 | Y71: 0.7872 | Z71: N | AA71: 210 | AB71: 0
A72: US-212 | B72: M | C72: Y | D72: 16.2 | E72: Normal Weight | F72: Vaccinated | G72: 44453 | H72: 44480 | I72: 12 | J72: S1 | K72: N | L72: >120 | M72: R | N72: 3.056 | O72: 0.0863 | P72: N | Q72: >120 | R72: R | S72: 3.5 | T72: 0.1457 | U72: N | V72: ***** | W72: * | X72: 2.971 | Y72: 1.4897 | Z72: R | AA72: 210 | AB72: 0
A73: US-386 | B73: Female | C73: N | D73: 42.2 | E73: Obese | F73: Non Vaccinated | G73: =#N/A -> #N/A | H73: =#N/A -> #N/A | I73: 15 | J73: S4 | K73: N | L73: 3.7178 | M73: N | N73: 3.059 | O73: 0.7673 | P73: N | Q73: >120 | R73: R | S73: 2.352 | T73: 0.3552 | U73: N | V73: >120 | W73: R | X73: 3.157 | Y73: 5.8482 | Z73: R | AA73: 210 | AB73: 0
A74: US-317 | B74: Female | C74: NA | D74: 21.8 | E74: Normal Weight | F74: Vaccinated | G74: 44453 | H74: 44476 | I74: 14 | J74: S4 | K74: N | L74: >120 | M74: R | N74: 3.059 | O74: 0.2886 | P74: N | Q74: >120 | R74: R | S74: 3.5 | T74: 3.7188 | U74: R | V74: >120 | W74: R | X74: 3.411 | Y74: 5.7098 | Z74: R
A75: US-187 | B75: M | C75: NA | D75: 19.2 | E75: Normal Weight | F75: Vaccinated | G75: 44453 | H75: 44482 | I75: 15 | J75: S4 | K75: N | L75: >120 | M75: R | N75: 3.059 | O75: 0.0603 | P75: N | Q75: ***** | R75: * | S75: 3.5 | T75: 1.4978 | U75: R | V75: ***** | W75: * | X75: 3.5 | Y75: 0.8864 | Z75: N | AA75: 210 | AB75: 0
A76: US-248 | B76: Female | C76: NA | D76: 24.8 | E76: Overweight | F76: Vaccinated | G76: 44453 | H76: 44477 | I76: 12 | J76: S1 | K76: N | L76: >120 | M76: R | N76: 3.087 | O76: 0.0764 | P76: N | Q76: >120 | R76: R | S76: 3.253 | T76: 0.0821 | U76: N | V76: >120 | W76: R | X76: 3.5 | Y76: 1.4175 | Z76: R | AA76: 210 | AB76: 0
A77: US-148 | B77: M | C77: NA | D77: 22 | E77: Overweight | F77: Vaccinated | G77: 44453 | H77: 44482 | I77: 12 | J77: S1 | K77: N | L77: >120 | M77: R | N77: 3.089 | O77: 0.2606/0.2541 | P77: N | Q77: >120 | R77: R | S77: 3.164 | T77: 2.1325 | U77: R | V77: >120 | W77: R | X77: 2.677 | Y77: 0.8422 | Z77: N | AA77: 210 | AB77: 0
A78: US-449 | B78: M | C78: N | D78: 23.6 | E78: Normal Weight | F78: Vaccinated | G78: 44454 | H78: 44476 | I78: 15 | J78: S4 | K78: N | L78: >120 | M78: R | N78: 3.089 | O78: 0.093 | P78: N | Q78: >120 | R78: R | S78: 3.5 | T78: 1.7388 | U78: R | V78: >120 | W78: R | X78: 3.322 | Y78: 0.969 | Z78: N | AA78: 210 | AB78: 0
A79: US-426 | B79: Female | C79: NA | D79: 19.7 | E79: Normal Weight | F79: Vaccinated | G79: 44453 | H79: 44476 | I79: 14 | J79: S4 | K79: N | L79: >120 | M79: R | N79: 3.113 | O79: 0.4832 | P79: N | Q79: >120 | R79: R | S79: 3.5 | T79: 0.3147 | U79: N | V79: >120 | W79: R | X79: 3.006 | Y79: 5.7569 | Z79: R | AA79: 210 | AB79: 0
A80: US-470 | B80: Female | C80: N | D80: 13 | E80: Underweight | F80: Vaccinated | G80: 44453 | H80: 44477 | I80: 11 | J80: S1 | K80: R | L80: >120 | M80: R | N80: 3.114 | O80: 1.6923 | P80: R | Q80: >120 | R80: R | S80: 3.255 | T80: 1.1943 | U80: R | V80: >120 | W80: R | X80: 3.238 | Y80: 0.8053 | Z80: N | AA80: 210 | AB80: 0
A81: US-404 | B81: M | C81: Y | D81: 21.2 | E81: Normal Weight | F81: Vaccinated | G81: 44454 | H81: 44476 | I81: 15 | J81: S4 | K81: N | L81: >120 | M81: R | N81: 3.127 | O81: 0.7047 | P81: N | Q81: >120 | R81: R | S81: 3.063 | T81: 1.7098 | U81: R | V81: >120/>120 | W81: R | X81: 2.387 | Y81: 1.0086 | Z81: N | AA81: 210 | AB81: 0
A82: US-238 | B82: Female | C82: N | D82: 28.4 | E82: Obese | F82: Vaccinated | G82: 44453 | H82: 44477 | I82: 14 | J82: S4 | K82: N | L82: >120 | M82: R | N82: 3.14 | O82: 0.1878 | P82: N | Q82: >120 | R82: R | S82: 3.242 | T82: 0.1749 | U82: N | V82: ***** | W82: * | X82: 3.099 | Y82: 0.952 | Z82: N | AA82: 210 | AB82: 0
A83: US-158 | B83: M | C83: N | D83: 18.4 | E83: Normal Weight | F83: Vaccinated | G83: 44453 | H83: 44477 | I83: 12 | J83: S1 | K83: R | L83: >120 | M83: R | N83: 3.141 | O83: 0.1759 | P83: N | Q83: ***** | R83: * | S83: 3.5 | T83: 1.936 | U83: R | V83: >120 | W83: R | X83: 3.409 | Y83: 1.1157 | Z83: R
A84: US-267 | B84: Female | C84: NA | D84: 15.5 | E84: Normal Weight | F84: Vaccinated | G84: 44453 | H84: 44477 | I84: 12 | J84: S1 | K84: N | L84: ***** | M84: * | N84: 3.146 | O84: 0.2555 | P84: N | Q84: ***** | R84: * | S84: 3.5 | T84: 5.4358 | U84: R | V84: >120 | W84: R | X84: 3.5 | Y84: 1.904 | Z84: R | AA84: 210 | AB84: 0
A85: US-481 | B85: Female | C85: N | D85: 15.7 | E85: Normal Weight | F85: Vaccinated | G85: 44453 | H85: 44477 | I85: 11 | J85: S1 | K85: N | L85: >120 | M85: R | N85: 3.157 | O85: 2.759 | P85: R | Q85: >120 | R85: R | S85: 3.307 | T85: 2.6413/2.5695 | U85: R | V85: ***** | W85: * | X85: 3.09 | Y85: 5.8595 | Z85: R
A86: US-205 | B86: Female | C86: NA | D86: 31.4 | E86: Obese | F86: Vaccinated | G86: 44453 | H86: 44477 | I86: 12 | J86: S1 | K86: R | L86: >120 | M86: R | N86: 3.165 | O86: 0.0456 | P86: N | Q86: >120 | R86: R | S86: 3.5 | T86: 0.074 | U86: N | V86: >120 | W86: R | X86: 3.351 | Y86: 0.2169 | Z86: N | AA86: 210 | AB86: 0
A87: US-504 | B87: Female | C87: N | D87: 21.7 | E87: Normal Weight | F87: Vaccinated | G87: 44453 | H87: 44477 | I87: 12 | J87: S1 | K87: R | L87: >120 | M87: R | N87: 3.183 | O87: 1.5546 | P87: R | Q87: >120 | R87: R | S87: 3.196 | T87: 0.6457 | U87: N | V87: ***** | W87: * | X87: 2.599 | Y87: 4.7829 | Z87: R | AA87: 210 | AB87: 0
A88: US-097 | B88: Female | C88: NA | D88: 20.3 | E88: Normal Weight | F88: Vaccinated | G88: 44453 | H88: 44476 | I88: 15 | J88: S4 | K88: R | L88: >120 | M88: R | N88: 3.195 | O88: 0.4637 | P88: N | Q88: 14.9096 | R88: R | S88: 3.5 | T88: 2.5342 | U88: R | V88: 8.0372 | W88: ? | X88: 2.994 | Y88: 0.918 | Z88: N
A89: US-459 | B89: Female | C89: N | D89: 15.1 | E89: Normal Weight | F89: Vaccinated | G89: 44453 | H89: 44477 | I89: 12 | J89: S1 | K89: N | L89: >120 | M89: R | N89: 3.205 | O89: 1.1582 | P89: R | Q89: 84.8451 | R89: R | S89: 3.5 | T89: 5.1192 | U89: R | V89: 48.724 | W89: R | X89: 3.031 | Y89: 2.1414 | Z89: R
A90: US-127 | B90: M | C90: N | D90: 20.5 | E90: Normal Weight | F90: Vaccinated | G90: 44453 | H90: 44476 | I90: 14 | J90: S4 | K90: N | L90: >120 | M90: R | N90: 3.217 | O90: 0.6066 | P90: N | Q90: >120 | R90: R | S90: 3.128 | T90: 0.3642 | U90: N | V90: >120 | W90: R | X90: 3.376 | Y90: 4.709 | Z90: R | AA90: 210 | AB90: 0
A91: US-075 | B91: M | C91: NA | D91: 25.6 | E91: Obese | F91: Vaccinated | G91: 44453 | H91: 44477 | I91: 12 | J91: S1 | K91: N | L91: >120 | M91: R | N91: 3.223 | O91: 0.5407 | P91: N | Q91: 1.1277 | R91: N | S91: 3.118 | T91: 0.1965 | U91: N | V91: 37.6285 | W91: R | X91: 3.023 | Y91: 3.3176 | Z91: R
A92: US-006 | B92: Female | C92: NA | D92: 14.7 | E92: Underweight | F92: Vaccinated | G92: 44466 | H92: 44487 | I92: 11 | J92: S1 | K92: N | L92: >120 | M92: R | N92: 3.265 | O92: 1.033 | P92: N | Q92: >120 | R92: R | S92: 3.064 | T92: 5.7061 | U92: R | V92: 71.3687 | W92: R | X92: 3.5 | Y92: 1.3155 | Z92: R
A93: US-575 | B93: M | C93: NA | D93: 23.7 | E93: Normal Weight | F93: Vaccinated | G93: 44454 | H93: 44476 | I93: 15 | J93: S4 | K93: N | L93: >120 | M93: R | N93: 3.31 | O93: 1.5856 | P93: R | Q93: ***** | R93: * | S93: 3.335 | T93: 5.6496 | U93: R | V93: >120 | W93: R | X93: 3.5 | Y93: 1.4552 | Z93: R | AA93: 210 | AB93: 0
A94: US-549 | B94: M | C94: N | D94: 14.6 | E94: Underweight | F94: Vaccinated | G94: 44453 | H94: 44476 | I94: 12 | J94: S1 | K94: N | L94: >120 | M94: R | N94: 3.355 | O94: 1.302 | P94: R | Q94: >120 | R94: R | S94: 3.5 | T94: 0.5714/0.5580 | U94: N | V94: >120 | W94: R | X94: 3.026 | Y94: 0.4241 | Z94: N | AA94: 210 | AB94: 0
A95: US-215 | B95: M | C95: Y | D95: 16.6 | E95: Normal Weight | F95: Vaccinated | G95: 44453 | H95: 44477 | I95: 12 | J95: S1 | K95: R | L95: >120 | M95: R | N95: 3.376 | O95: 0.0831 | P95: N | Q95: 14.121 | R95: R | S95: 3.154 | T95: 3.1323 | U95: R | V95: 11.3462 | W95: R | X95: 2.941 | Y95: 1.0847 | Z95: N
A96: US-189 | B96: M | C96: Y | D96: 20.3 | E96: Normal Weight | F96: Vaccinated | G96: 44453 | H96: 44476 | I96: 14 | J96: S4 | K96: N | L96: >120 | M96: R | N96: 3.398 | O96: 0.1059 | P96: N | Q96: ***** | R96: * | S96: 3.081 | T96: 2.9462 | U96: R | V96: >120 | W96: R | X96: 3.5 | Y96: 0.8967 | Z96: N | AA96: 210 | AB96: 0
A97: US-260 | B97: Female | C97: NA | D97: 19.6 | E97: Normal Weight | F97: Vaccinated | G97: 44453 | H97: 44477 | I97: 12 | J97: S1 | K97: N | L97: >120 | M97: R | N97: 3.405 | O97: 0.0808 | P97: N | Q97: >120 | R97: R | S97: 3.5 | T97: 0.0884 | U97: N | V97: >120 | W97: R | X97: 3.5 | Y97: 0.0731 | Z97: N | AA97: 210 | AB97: 0
A98: US-285 | B98: Female | C98: NA | D98: 29.1 | E98: Obese | F98: Vaccinated | G98: 44453 | H98: 44477 | I98: 15 | J98: S4 | K98: N | L98: >120 | M98: R | N98: 3.416 | O98: 0.5839 | P98: N | Q98: >120 | R98: R | S98: 3.5 | T98: 2.0737 | U98: R | V98: >120 | W98: R | X98: 3.5 | Y98: 1.2923 | Z98: R | AA98: 210 | AB98: 0
A99: US-138 | B99: M | C99: Y | D99: 23.7 | E99: Overweight | F99: Vaccinated | G99: 44453 | H99: 44476 | I99: 15 | J99: S4 | K99: N | L99: >120 | M99: R | N99: 3.428 | O99: 0.5495 | P99: N | Q99: >120 | R99: R | S99: 2.979 | T99: 0.2384 | U99: N | V99: >120 | W99: R | X99: 3.5 | Y99: 1.4795 | Z99: R | AA99: 210 | AB99: 0
A100: US-195 | B100: M | C100: Y | D100: 17.8 | E100: Normal Weight | F100: Vaccinated | G100: 44453 | H100: 44477 | I100: 12 | J100: S1 | K100: N | L100: >120 | M100: R | N100: 3.43 | O100: 0.202 | P100: N | Q100: 18.1268 | R100: R | S100: 3.171 | T100: 2.148 | U100: R | V100: >120 | W100: R | X100: 2.924 | Y100: 5.9628 | Z100: R
...

Sheet Inspection
A1: Items
A2: Nombre de colonnes | B2: =COLUMNS(Sheet1!A1:AC1) -> 29
A3: Nombre de lignes | B3: =ROWS(Sheet1!A2:A295) -> 294
A5: Variables | B5: Type | C5: Modalités rencontrées | D5: Cellules vides | E5: Valeurs manquantes
A6: D | B6: Standard (Texte) | C6: =COUNTA(_xlfn.UNIQUE(Sheet1!A2:A295)) -> 294 | D6: =COUNTBLANK(Sheet1!A2:A295) -> 0 | E6: =COUNTIF(Sheet1!A2:A295,"#N/A")+COUNTIF(Sheet1!A2:A295,"NA") -> 0
A7: Gender | B7: Standard (Catégorielle) | C7: =_xlfn.TEXTJOIN(", ",TRUE,_xlfn.UNIQUE(Sheet1!B2:B295)) -> Female, M | D7: =COUNTBLANK(Sheet1!B2:B295) -> 0 | E7: =COUNTIF(Sheet1!B2:B295,"#N/A")+COUNTIF(Sheet1!B2:B295,"NA") -> 0
A8: BirthComor | B8: Standard (Catégorielle) | C8: =_xlfn.TEXTJOIN(", ",TRUE,_xlfn.UNIQUE(Sheet1!C2:C295)) -> NA, N, Y | D8: =COUNTBLANK(Sheet1!C2:C295) -> 0 | E8: =COUNTIF(Sheet1!C2:C295,"#N/A")+COUNTIF(Sheet1!C2:C295,"NA") -> 107
A9: BMI measure | B9: Nombre (Numérique) | C9: =COUNTA(_xlfn.UNIQUE(Sheet1!D2:D295)) -> 149 | D9: =COUNTBLANK(Sheet1!D2:D295) -> 0 | E9: =COUNTIF(Sheet1!D2:D295,"#N/A")+COUNTIF(Sheet1!D2:D295,"NA") -> 0
A10: BMI | B10: Standard (Catégorielle) | C10: =_xlfn.TEXTJOIN(", ", TRUE, _xlfn.UNIQUE(Sheet1!E2:E295)) -> Overweight, Normal Weight, Underweight, Obese | D10: =COUNTBLANK(Sheet1!E2:E295) -> 0 | E10: =COUNTIF(Sheet1!E2:E295,"#N/A")+COUNTIF(Sheet1!E2:E295,"NA") -> 0
A11: Vacstat | B11: Standard (Texte) | C11: =_xlfn.TEXTJOIN(", ", TRUE, _xlfn.UNIQUE(Sheet1!F2:F295)) -> Non Vaccinated, Vaccinated | D11: =COUNTBLANK(Sheet1!F2:F295) -> 0 | E11: =COUNTIF(Sheet1!F2:F295,"#N/A")+COUNTIF(Sheet1!F2:F295,"NA") -> 0
A12: Date 1 | B12: Date | C12: =COUNTA(_xlfn.UNIQUE(Sheet1!G2:G295)) -> 9 | D12: =COUNTBLANK(Sheet1!G2:G295) -> 0 | E12: =COUNTIF(Sheet1!G2:G295,"#N/A")+COUNTIF(Sheet1!G2:G295,"NA") -> 66
A13: Date 2 | B13: Date | C13: =COUNTA(_xlfn.UNIQUE(Sheet1!H2:H295)) -> 12 | D13: =COUNTBLANK(Sheet1!H2:H295) -> 0 | E13: =COUNTIF(Sheet1!H2:H295,"#N/A")+COUNTIF(Sheet1!H2:H295,"NA") -> 66
A14: Age | B14: Nombre (Numérique) | C14: =COUNTA(_xlfn.UNIQUE(Sheet1!I2:I295)) -> 6 | D14: =COUNTBLANK(Sheet1!I2:I295) -> 0 | E14: =COUNTIF(Sheet1!I2:I295,"#N/A")+COUNTIF(Sheet1!I2:I295,"NA") -> 0
A15: Class | B15: Standard (Catégorielle) | C15: =_xlfn.TEXTJOIN(", ", TRUE, _xlfn.UNIQUE(Sheet1!J2:J295)) -> S1, S4 | D15: =COUNTBLANK(Sheet1!J2:J295) -> 0 | E15: =COUNTIF(Sheet1!J2:J295,"#N/A")+COUNTIF(Sheet1!J2:J295,"NA") -> 0
A16: Infected prior to vaccination | B16: Standard (Catégorielle) | C16: =_xlfn.TEXTJOIN(", ", TRUE, _xlfn.UNIQUE(Sheet1!K2:K295)) -> N, R | D16: =COUNTBLANK(Sheet1!K2:K295) -> 0 | E16: =COUNTIF(Sheet1!K2:K295,"#N/A")+COUNTIF(Sheet1!K2:K295,"NA") -> 0
A17: Quantivac at 28 days | B17: Nombre (Numérique) | C17: =COUNTA(_xlfn.UNIQUE(Sheet1!G2:G295)) -> 9 | D17: =COUNTBLANK(Sheet1!L2:L295) -> 0 | E17: =COUNTIF(Sheet1!L2:L295,"#N/A")+COUNTIF(Sheet1!L2:L295,"NA")+COUNTIF(Sheet1!L2:L295,"*****") -> 226
A18: Q 28 Result | B18: Standard (Catégorielle) | C18: =_xlfn.TEXTJOIN(", ", TRUE, _xlfn.UNIQUE(Sheet1!M2:M295)) -> N, ?, R, * | D18: =COUNTBLANK(Sheet1!M2:M295) -> 0 | E18: =COUNTIF(Sheet1!M2:M295,"#N/A")+COUNTIF(Sheet1!M2:M295,"NA")+COUNTIF(Sheet1!L2:L295,"*")+COUNTIF(Sheet1!M2:M295,"?") -> 520
A19: ODQ28Days | B19: Nombre (Numérique) | C19: =COUNTA(_xlfn.UNIQUE(Sheet1!N2:N295)) -> 101 | D19: =COUNTBLANK(Sheet1!N2:N295) -> 0 | E19: =COUNTIF(Sheet1!N2:N295,"#N/A")+COUNTIF(Sheet1!N2:N295,"NA")+COUNTIF(Sheet1!N2:N295,"*")+COUNTIF(Sheet1!N2:N295,"?") -> 0
A20: NCPat28 days | B20: Nombre (Numérique) | C20: =COUNTA(_xlfn.UNIQUE(Sheet1!O2:O295)) -> 270 | D20: =COUNTBLANK(Sheet1!O2:O295) -> 0
A21: N28Results | B21: Standard (Catégorielle) | C21: =_xlfn.TEXTJOIN(", ", TRUE, _xlfn.UNIQUE(Sheet1!P2:P295)) -> N, R | D21: =COUNTBLANK(Sheet1!P2:P295) -> 0
A22: Quantivacat3 months | B22: Nombre (Numérique) | C22: =COUNTA(_xlfn.UNIQUE(Sheet1!Q2:Q295)) -> 49 | D22: =COUNTBLANK(Sheet1!Q2:Q295) -> 0 | E22: =COUNTIF(Sheet1!Q2:Q295,"#N/A")+COUNTIF(Sheet1!Q2:Q295,"NA")+COUNTIF(Sheet1!Q2:Q295,"*")+COUNTIF(Sheet1!Q2:Q295,"?")+COUNTIF(Sheet1!Q2:Q295,"*****") -> 494
A23: Q3 Result | B23: Standard (Catégorielle) | C23: =_xlfn.TEXTJOIN(", ", TRUE, _xlfn.UNIQUE(Sheet1!R2:R295)) -> R, *, N, ? | D23: =COUNTBLANK(Sheet1!R2:R295) -> 0 | E23: =COUNTIF(Sheet1!Q2:Q295,"*")+COUNTIF(Sheet1!Q2:Q295,"?") -> 247
A24: ODQ4months | B24: Nombre (Numérique) | C24: =COUNTA(_xlfn.UNIQUE(Sheet1!Q2:Q295)) -> 49 | D24: =COUNTBLANK(Sheet1!S2:S295) -> 0
A25: NCPat3months | B25: Nombre (Numérique) | C25: =COUNTA(_xlfn.UNIQUE(Sheet1!S2:S295)) -> 182 | D25: =COUNTBLANK(Sheet1!S2:S295) -> 0
A26: N3Result | B26: Standard (Catégorielle) | C26: =_xlfn.TEXTJOIN(", ", TRUE, _xlfn.UNIQUE(Sheet1!U2:U295)) -> R, N | D26: =COUNTBLANK(Sheet1!U2:U295) -> 0
A27: Quantivacat7months | B27: Nombre (Numérique) | C27: =COUNTA(_xlfn.UNIQUE(Sheet1!V2:V295)) -> 62 | D27: =COUNTBLANK(Sheet1!V2:V295) -> 0
A28: Q7Result | B28: Standard (Catégorielle) | C28: =_xlfn.TEXTJOIN(", ", TRUE, _xlfn.UNIQUE(Sheet1!W2:W295)) -> R, N, *, ? | D28: =COUNTBLANK(Sheet1!W2:W295) -> 0 | E28: =COUNTIF(Sheet1!W2:W295,"*")+COUNTIF(Sheet1!W2:W295,"?") -> 588
A29: ODQ7months | B29: Nombre (Numérique) | C29: =COUNTA(_xlfn.UNIQUE(Sheet1!X2:X295)) -> 209 | D29: =COUNTBLANK(Sheet1!X2:X295) -> 0
A30: NCPat7months | B30: Nombre (Numérique) | C30: =COUNTA(_xlfn.UNIQUE(Sheet1!Y2:Y295)) -> 290 | D30: =COUNTBLANK(Sheet1!Y2:Y295) -> 0
A31: N7Result | B31: Standard (Catégorielle) | C31: =_xlfn.TEXTJOIN(", ", TRUE, _xlfn.UNIQUE(Sheet1!Z2:Z295)) -> R, N | D31: =COUNTBLANK(Sheet1!Z2:Z295) -> 0
A32: Time | B32: Standard (Catégorielle) | C32: =_xlfn.TEXTJOIN(", ", TRUE, _xlfn.UNIQUE(Sheet1!AA2:AA295)) -> 210, 92, 182 | D32: =COUNTBLANK(Sheet1!AA2:AA295) -> 71
A33: Status | B33: Standard (Catégorielle) | C33: =_xlfn.TEXTJOIN(", ", TRUE, _xlfn.UNIQUE(Sheet1!AB2:AB295)) -> 0, 1 | D33: =COUNTBLANK(Sheet1!AB2:AB295) -> 71
A34: TruncatedTiter | B34: Nombre (Numérique) | C34: =COUNTA(_xlfn.UNIQUE(Sheet1!AC2:AC295)) -> 1 | D34: =COUNTBLANK(Sheet1!AC2:AC295) -> 294

Sheet Dictionnaire
A1: Dictionnaire révisé
A3: Méthode de reconstruction
A4: Hypothèses basées sur
A5: (1) L'analyse directe des valeurs,
A6: (2) Le vocabulaire standard de la sérologie vaccinale,
A7: (3) Le contexte de l'étude (adolescents scolarisés, suivi à 28j/3mois/7mois)"
A8: (4) Recherche de logique par croisement de variables
A11: Nom initial | B11: Nom proposé (FR) | C11: Nom proposé (EN) | D11: Type | E11: Signification (FR) | F11: Signification (EN) | G11: Certitude | H11: Problème identifié
A12: D | B12: ID_sujet | C12: Subject_ID | D12: Catégorique (Nominale) | E12: Identifiant unique du sujet avec préfixe "US-" | F12: Unique subject identifier with "US-" prefix | G12: Probable | H12: Signification de "US-" non confirmée
A13: Gender | B13: Sexe | C13: Sex | D13: Catégorique (Nominale) | E13: Sexe du sujet | F13: Subject's sex | G13: Certain | H13: Aucun
A14: BirthComor | B14: Comorbidite_naissance | C14: Birth_comorbidity | D14: Catégorique (Nominale) | E14: Présence de comorbidité à la naissance (Yes/No/NA) | F14: Presence of birth comorbidity (Yes/No/NA) | G14: Probable | H14: Nature exacte non précisée ; "NA" stocké comme texte
A15: BMI measure | B15: Valeur_IMC | C15: BMI_value | D15: Numérique (Décimal) | E15: Valeur numérique de l'IMC | F15: Numeric BMI value | G15: Certain | H15: Aucun
A16: BMI | B16: Classe_IMC | C16: BMI_class | D16: Catégorique (Ordinale) | E16: Catégorie de poids | F16: Weight category | G16: Certain | H16: Aucun
A17: Vacstat | B17: Statut_vaccinal | C17: Vaccination_status | D17: Catégorique (Nominale) | E17: Statut vaccinal | F17: Vaccination status | G17: Certain | H17: Aucun
A18: Date 1 | B18: Date_dose1 | C18: Dose1_date | D18: Date | E18: Date de la 1ère dose de vaccin | F18: Date of 1st vaccine dose | G18: Probable | H18: Manquants codés "#N/A" en texte
A19: Date 2 | B19: Date_dose2 | C19: Dose2_date | D19: Date | E19: Date de la 2ème dose (~3-4 sem. après) | F19: Date of 2nd dose (~3-4 weeks later) | G19: Probable | H19: Idem
A20: Age | B20: Age | C20: Age | D20: Numérique (Entier) | E20: Âge en années | F20: Age in years | G20: Certain | H20: Format "Standard"
A21: Class | B21: Classe_scolaire | C21: School_grade | D21: Catégorique (Nominale) | E21: Niveau scolaire | F21: School grade level | G21: Probable | H21: Seulement 2 modalités (S1, S4)
A22: Infected prior to vaccination | B22: Infection_anterieure | C22: Prior_infection | D22: Catégorique (Nominale) | E22: Statut sérologique avant vaccination | F22: Serological status prior to vaccination | G22: Probable | H22: "R" déduit, non documenté
... A52: TruncatedTiter | B52: Titre_tronque_dérivée | C52: Truncated_titer_derived | D52: Numérique (Continu) | E52: Titre au seuil de censure (120), rattaché au temps de suivi le plus proche | F52: Titer at censoring threshold (120), nearest follow-up time | G52: Reconstruit | H52: Colonne vide à l'origine ; construite selon règle documentée

Sheet Journal de Nettoyage
A1: N° | B1: Date | C1: Etapes | D1: Variable(s) | E1: Action réalisée | F1: Justification | G1: Livrables | H1: Observations
A2: 1 | B2: 46234 | C2: Chargement et inspection de la base | D2: Toutes les variables | E2: Inspection visuelle de la base de données, Prise de connaissances des différentes variables et leurs modalités
A3: 2 | B3: 46234 | C3: Sommaire de la base de données | D3: Toutes les variables | E3: Inspection générale de la base (Nombre de lignes et de colonnes, variables, cellules vides, valeurs manquantes)
A4: 3 | B4: 46234 | C4: Documentation | D4: Toutes les variables | E4: Construction d'un dictionnaire de données à partir de recherche sur internet et des clarifications avec l'IA | F4: Absence de documentation officielle
A5: 4 | B5: 46249 | C5: Nettoyage : Renommage des colonnes | D5: Toutes les variables | E5: Renommage des colonnes suivant le dictionnaire révisé | G5: Base de données nettoyée
A6: 5 | B6: 46249 | C6: Nettoyage : Valeurs manquantes | D6: Comorbidite_naissance, Date_Dose1, Date_Dose2 | E6: Remplacement de 107 cellules "NA" (texte) par cellules vides | F6: 100% des manquants codés en texte "NA", Aucune vraie cellule vide dans la colonne d'origine | G6: NA → (vide) | H6: Note : les "#N/A" dans Date_dose1/Date_dose2 ne sont pas du texte mais de vraies valeurs d'erreur Excel (probablement issues d'une formule =NA() ou RECHERCHEV dans le fichier source) — Rechercher/Remplacer en mode texte ne les détecte pas ; utilisation de F5 > Cellules > Erreurs à la place.
A7: 6 | B7: 46250 | C7: Nettoyage : Valeurs dupliquées | D7: CapaciteNeutralisation_(28j, 3mois, 7mois) et Titre_AC_7mois | E7: Séparation des cellules à double mesure ("xy") en 2 colonnes distinctes (_mesure1, _mesure2) via Convertir Texte en colonnes) | F7: Absence de documentation sur la nature de la 2e valeur ; choix de conserver l'information brute sans perte plutôt que de calculer une moyenne arbitraire | H7: Anomalie détectée : l'outil "Texte en colonnes" a mal interprété le séparateur décimal (confusion point virgule, paramètres régionaux français) lors de la séparation des cellules "xy" — valeurs comme "1.6594" transformées en "16594". Corrigé en spécifiant manuellement les séparateurs via le bouton "Avancé" de l'assistant. Lacolonne Titre_AC_7mois n'a pas posé de problèeme de séparateur
A8: 7 | B8: 46250 | C8: Nettoyage : Censure/codes spéciaux | D8: Titre_AC_28j, Titre_AC_3mois, Titre_AC_7mois_mesure1, Titre_AC_7mois_mesure2 | E8: Séparation de chaque colonne en 2 : "_valeur" (numérique pur) et "_statut" (Normal/Censure_haute/Echec_technique/Manquant), via SIERREUR(CNUM(...)) et test GAUCHE()/ESTVIDE(). Nous avons ">120" → valeur vide + statut "Censure_haute" ; "*****" → valeur vide + statut "Echec_technique" ; cellule vraiment vide → valeur vide + statut en cellule vide | F8: Colonnes d'origine mélangeaient valeurs numériques réelles et codes texte (">120", "*****") ; conserver l'info qualitative plutôt que de la supprimer ou d'inventer une valeur | H8: Ajout d'un test ESTVIDE() en priorité dans les formules, car les vraies cellules vides étaient mal interprétées (donnaient 0 en valeur et "Normal" en statut par défaut). CNUM() renvoie 0 sur une cellule vide au lieu d'une erreur ; nécessaire pour distinguer "vraiment manquant" de "censure"/"échec technique" ; Cellule vide : "0.00000"/"Normal" → "" / cellule vide
A9: 8 | B9: 46250 | C9: Nettoyage : Recodage catégoriel des codes spéciaux "*" et "?" | D9: Resultat_qual_28j/3mois/7mois vs Titre_AC correspondant | E9: Vérification de la cohérence entre résultat qualitatif et valeur quantitative associée ; Recodage de "*" en "Non testé" et "," en "Incertain" | F9: Validation croisée et Logique confirmée aux 3 temps : "*"↔"*****" (test non réalisé), "N"↔numérique, "R"↔(numérique ou ">120"), "?"↔numérique | 2 cas anomalies détectés ("R" associé à "*****") sur 294×3 ≈ 880 paires observées | H9: Piège rencontré : "*" et "?" sont interprétés comme caractères joker par Rechercher/Remplacer dans Excel — nécessité d'échapper avec "~*" et "~?" pour cibler les symboles littéraux.
A10: 9 | B10: 46250 | C10: Correction label | D10: Titre_AC_28j/_3mois/_7mois_mesure1/_mesure2 (statut) | E10: Remplacement global "Echec_technique" → "Non_teste" (337 cellules), puis exception manuelle sur US-111 (Titre_AC_3mois) remise en "Echec_technique" | F10: Validation croisée montrant que la quasi-totalité des cas étaient systématiques (test non réalisé) et non des pannes ; US-111 isolé et contredit le pattern
A11: 10 | B11: 46250 | C11: Correction saisie | D11: CapaciteNeutralisation_28j_mesure2 | E11: Correction de "2817" en "0.2817" (point décimal manquant, valeur aberrante comparée à mesure1=0.2817 et à la plage habituelle de la variable) ; "2817" → "0.2817" | H11: Détecté lors du scan final de vérification des caractères spéciaux résiduels
A12: 11 | B12: 46254 | C12: Standardisation catégorielle | D12: Sexe, Comorbidite_naissance, Infection_anterieure, Resultat_neutralisation_28j/3mois/7mois, Classe_IMC, Statut_vaccinal | E12: Recodage des 8 dernières colonnes catégorielles vers des libellés explicites en français (codes courts F/M/Y/N/R décodés + traduction des modalités restées en anglais) ; Ex: "F"→"Femme" ; "Overweight"→"Surpoids" ; "Vaccinated"→"Vacciné" | F12: Pour une cohérence terminologique complète du fichier | H12: Vérification exhaustive des 29 colonnes confirmant que ces 8 étaient les seules concernées (Classe_scolaire exclue, codes scolaires propres à l'étude, non traduisibles)
A13: 12 | B13: 46254 | C13: Vérification types de données | D13: Toutes les colonnes | E13: Contrôle systématique du type de chaque colonne (alignement, Ctrl+1) : colonnes numériques (Valeur_IMC, Age, Densite_optique_..., Titre_AC_..._valeur, CapaciteNeutralisation_..., Temps_suivi_jours) et colonnes dates (Date_dose1/2) vérifiées correctes ; Correction du format mixte "Standard/Nombre" sur Titre_AC_7mois_mesure_2 ; uniformisation du format des en-têtes (ligne 1) en "Standard" sur l'ensemble du fichier | H13: 2 constats sans impact réel, documentés pour mémoire : (1) en-têtes parfois au même format "Nombre" que leurs valeurs — sans effet, un en-tête reste du texte quel que soit le format appliqué ; (2) formats Standard sur Age/Temps_suivi_jours — sans impact sur les calculs. Seule vraie correction : format mixte Standard/Nombre uniformisé sur Titre_AC_7mois_mesure_2, et harmonisation des en-têtes en "Standard" ; Contrôle nécessaire après les transformations des étapes 2-4 (formules, séparations, recodages) pour s'assurer qu'aucune valeur numérique n'était restée déguisée en texte
A14: 13 | B14: 46254 | C14: Standardisation de la mise en forme | D14: Ensemble du fichier | E14: Suppression de toute la mise en forme héritée (couleurs, gras, polices, bordures manquantes) et réapplication d'un style uniforme (bordures complètes, en-têtes en gras, police unique, tableau structuré) | F14: Investigation menée avant suppression : (1) surlignage jaune sur ODQ28Days/ODQ4months coïncidant exactement avec les 2 colonnes déjà signalées comme problématiques au dictionnaire ; signal probable des auteurs originaux, confiance renforcée sur ces variables ; (2) surlignage bleu sur 2 lignes isolées (US-004, US-019) ; hypothèse de contradiction Q Result/N Results testée et rejetée : origine non déterminée, probable audit manuel des auteurs ; (3) désaccord Q Result/N Results noté comme caractéristique biologique du dataset (deux méthodes sérologiques différentes), non corrigé ; (4) cellule rouge isolée (US-116) et triangles verts Excel (BMI/Vacstat, faux-positifs standards) sans pattern confirmé. Mise en forme jugée sans valeur analytique exploitable au-delà de ces observations, supprimée après investigation
A15: 14 | B15: 46254 | C15: Construction variable dérivée | D15: Titre_tronque | E15: Colonne reconstruite (vide à l'origine) : valeur=120 si le statut de censure au temps correspondant à Temps_suivi_jours est "Censure_haute", vide sinon | F15: Absence de documentation officielle ; règle basée sur la correspondance Time/point de mesure le plus proche (92j→3mois, 182j/210j→7mois, faute de colonne dédiée à 182j) ; convention standard en analyse de survie pour encoder une censure connue
A16: 15 | B16: 46254 | C16: Indicateurs de validation | D16: Ensemble du dataset nettoyé | E16: Calcul de 6 indicateurs de vérification post-nettoyage sur feuille dédiée "Indicateurs" : (1) intégrité — 294 lignes, 294 ID uniques ; (2) répartition Censure_haute par temps (43/156/174 à 28j/3mois/7mois), conforme au croisement établi en étape 4 ; (3) progression du titre d'anticorps moyen (cas "Normal" uniquement) : 18.98 → 29.72 → 44.49, cohérente avec la logique biologique attendue (montée post-vaccinale) ; (4) cohérence chronologique Dose_Date1/Dose_Date2 (0 inversion) ; (5) plage d'âge plausible (11-16 ans) ; (6) cohérence de la variable dérivée Titre_tronque avec Statut_evenement (0 incohérence) | F16: Objectif double : produire des indicateurs de synthèse ET valider que le nettoyage des étapes 1-5 n'a pas laissé d'erreur cachée | H16: Une anomalie a été détectée par l'indicateur 3 (moyenne à 7 mois initialement à 431 321.99, hors de toute plage plausible) : facteur ×10000 résiduel sur Titre_AC_7mois_mesure_1_valeurs (bug de séparateur décimal non corrigé aux étapes précédentes, ex. US-512 : 979592→97.9592), corrigé par division ciblée des valeurs >1000

Sheet Données nettoyées (Fr)
A1: ID_sujet | B1: Sexe | C1: Comorbidite_naissance | D1: Valeur_IMC | E1: Class_IMC | F1: Statut_vaccinal | G1: Dose_Date1 | H1: Dose_Date2 | I1: Age | J1: Classe_scolaire | K1: Infection_antérieure | L1: Titre_AC_28j_statut | M1: Titre_AC_28j | N1: Titre_AC_28j_valeurs | O1: Resultat_qual_28j | P1: DensiteOptique_28j | Q1: CapaciteNeutralisation_28j_mesure1 | R1: CapaciteNeutralisation_28j_mesure2 | S1: Resultat_neutralisation_28j | T1: Titre_AC_3mois_statut | U1: Titre_AC_3mois | V1: Titre_AC_3mois_valeurs | W1: Resultat_qual_3mois | X1: DensiteOptique_3mois | Y1: CapaciteNeutralisation_3mois_mesure1 | Z1: CapaciteNeutralisation_3mois_mesure2 | AA1: Resultat_neutralisation_3mois | AB1: Titre_AC_7mois_mesure_1_statut | AC1: Titre_AC_7mois_mesure_1 | AD1: Titre_AC_7mois_mesure_1_valeurs | AE1: Titre_AC_7mois_mesure_2_statut | AF1: Titre_AC_7mois_mesure_2 | AG1: Titre_AC_7mois_mesure_2_valeurs | AH1: Resultat_qual_7mois | AI1: DensiteOptique_7mois | AJ1: CapaciteNeutralisation_7mois_mesure1 | AK1: CapaciteNeutralisation_7mois_mesure2 | AL1: Resultat_neutralisation_7mois | AM1: Temps_suivi_jours | AN1: Statut_evenement | AO1: Titre_tronque_dérivée
A2: US-050 | B2: Femme | D2: 22.8 | E2: Surpoids | F2: Non vacciné | I2: 12 | J2: S1 | K2: Négatif | L2: =IF(LEFT(M2,1)=">","Censure haute",IF(M2="*****","Non testé","Normal")) -> Normal | M2: 0.1679 | N2: =IFERROR(VALUE(M2),"") -> 0.1679 | O2: Négatif | P2: 0.031 | Q2: 0.7099 | S2: Négatif | T2: =IF(LEFT(U2,1)=">","Censure haute",IF(U2="*****","Echec technique","Normal")) -> Censure haute | U2: >120 | V2: =IFERROR(VALUE(U2),"") | W2: Réactif | X2: 0.958 | Y2: 6.4746 | AA2: Réactif | AB2: =IF(LEFT(AC2,1)=">","Censure haute",IF(AC2="*****","Non testé","Normal")) -> Censure haute | AC2: >120 | AE2: =IF(ISBLANK(AF2),"",IF(LEFT(AF2,1)=">","Censure haute",IF(AF2="*****","Non testé","Normal"))) | AG2: =IF(ISBLANK(AF2),"",IFERROR(VALUE(AF2),"")) | AH2: Réactif | AI2: 0.589 | AJ2: 3.3545 | AL2: Réactif | AM2: 210 | AN2: 0 | AO2: =IF(ISBLANK(AM2),"",IF(AM2=92,IF(T2="Censure haute",120,""),IF(AB2="Censure haute",120,""))) -> 120
A3: US-509 | B3: Homme | C3: Non | D3: 17 | E3: Poids normal | F3: Non vacciné | I3: 12 | J3: S1 | K3: Négatif | L3: =IF(LEFT(M3,1)=">","Censure haute",IF(M3="*****","Non testé","Normal")) -> Normal | M3: 0.3747 | N3: =IFERROR(VALUE(M3),"") -> 0.3747 | O3: Négatif | P3: 0.035 | Q3: 1.6594 | S3: Réactif | T3: =IF(LEFT(U3,1)=">","Censure haute",IF(U3="*****","Echec technique","Normal")) -> Censure haute | U3: >120 | V3: =IFERROR(VALUE(U3),"") | W3: Réactif | X3: 0.482 | Y3: 6.2601 | AA3: Réactif | AB3: =IF(LEFT(AC3,1)=">","Censure haute",IF(AC3="*****","Non testé","Normal")) -> Censure haute | AC3: >120 | AE3: =IF(ISBLANK(AF3),"",IF(LEFT(AF3,1)=">","Censure haute",IF(AF3="*****","Non testé","Normal"))) | AG3: =IF(ISBLANK(AF3),"",IFERROR(VALUE(AF3),"")) | AH3: Réactif | AI3: 2.847 | AJ3: 2.3946 | AL3: Réactif | AM3: 210 | AN3: 0 | AO3: =IF(ISBLANK(AM3),"",IF(AM3=92,IF(T3="Censure haute",120,""),IF(AB3="Censure haute",120,""))) -> 120
A4: US-063 | B4: Femme | C4: Non | D4: 14.4 | E4: Insuffisance pondérale | F4: Non vacciné | I4: 12 | J4: S1 | K4: Négatif | L4: =IF(LEFT(M4,1)=">","Censure haute",IF(M4="*****","Non testé","Normal")) -> Normal | M4: 0.1022 | N4: =IFERROR(VALUE(M4),"") -> 0.1022 | O4: Négatif | P4: 0.037 | Q4: 0.5253 | S4: Négatif | T4: =IF(LEFT(U4,1)=">","Censure haute",IF(U4="*****","Echec technique","Normal")) -> Censure haute | U4: >120 | V4: =IFERROR(VALUE(U4),"") | W4: Réactif | X4: 0.857 | Y4: 0.2737 | AA4: Négatif | AB4: =IF(LEFT(AC4,1)=">","Censure haute",IF(AC4="*****","Non testé","Normal")) -> Censure haute | AC4: >120 | AE4: =IF(ISBLANK(AF4),"",IF(LEFT(AF4,1)=">","Censure haute",IF(AF4="*****","Non testé","Normal"))) | AG4: =IF(ISBLANK(AF4),"",IFERROR(VALUE(AF4),"")) | AH4: Réactif | AI4: 0.499 | AJ4: 0.1885 | AL4: Négatif | AM4: 210 | AN4: 0 | AO4: =IF(ISBLANK(AM4),"",IF(AM4=92,IF(T4="Censure haute",120,""),IF(AB4="Censure haute",120,""))) -> 120
A5: US-188 | B5: Homme | D5: 21.4 | E5: Poids normal | F5: Non vacciné | I5: 15 | J5: S4 | K5: Négatif | L5: =IF(LEFT(M5,1)=">","Censure haute",IF(M5="*****","Non testé","Normal")) -> Normal | M5: 0.2861 | N5: =IFERROR(VALUE(M5),"") -> 0.2861 | O5: Négatif | P5: 0.038 | Q5: 0.298 | S5: Négatif | T5: =IF(LEFT(U5,1)=">","Censure haute",IF(U5="*****","Echec technique","Normal")) -> Echec technique | U5: ***** | V5: =IFERROR(VALUE(U5),"") | W5: Non testé | X5: 0.737 | Y5: 2.0179 | AA5: Réactif | AB5: =IF(LEFT(AC5,1)=">","Censure haute",IF(AC5="*****","Non testé","Normal")) -> Censure haute | AC5: >120 | AE5: =IF(ISBLANK(AF5),"",IF(LEFT(AF5,1)=">","Censure haute",IF(AF5="*****","Non testé","Normal"))) | AG5: =IF(ISBLANK(AF5),"",IFERROR(VALUE(AF5),"")) | AH5: Réactif | AI5: 0.43 | AJ5: 0.6488 | AL5: Négatif | AM5: 210 | AN5: 0 | AO5: =IF(ISBLANK(AM5),"",IF(AM5=92,IF(T5="Censure haute",120,""),IF(AB5="Censure haute",120,""))) -> 120
A6: US-286 | B6: Homme | D6: 33.2 | E6: Obésité | F6: Non vacciné | I6: 15 | J6: S4 | K6: Négatif | L6: =IF(LEFT(M6,1)=">","Censure haute",IF(M6="*****","Non testé","Normal")) -> Normal | M6: 0.3317 | N6: =IFERROR(VALUE(M6),"") -> 0.3317 | O6: Négatif | P6: 0.038 | Q6: 0.528 | S6: Négatif | T6: =IF(LEFT(U6,1)=">","Censure haute",IF(U6="*****","Echec technique","Normal")) -> Censure haute | U6: >120 | V6: =IFERROR(VALUE(U6),"") | W6: Réactif | X6: 3.392 | Y6: 0.3179 | AA6: Négatif | AB6: =IF(LEFT(AC6,1)=">","Censure haute",IF(AC6="*****","Non testé","Normal")) -> Censure haute | AC6: >120 | AE6: =IF(ISBLANK(AF6),"",IF(LEFT(AF6,1)=">","Censure haute",IF(AF6="*****","Non testé","Normal"))) | AG6: =IF(ISBLANK(AF6),"",IFERROR(VALUE(AF6),"")) | AH6: Réactif | AI6: 3.2 | AJ6: 0.1482 | AL6: Négatif | AM6: 210 | AN6: 0 | AO6: =IF(ISBLANK(AM6),"",IF(AM6=92,IF(T6="Censure haute",120,""),IF(AB6="Censure haute",120,""))) -> 120
A7: US-116 | B7: Femme | C7: Oui | D7: 25.5 | E7: Surpoids | F7: Non vacciné | I7: 14 | J7: S4 | K7: Négatif | L7: =IF(LEFT(M7,1)=">","Censure haute",IF(M7="*****","Non testé","Normal")) -> Normal | M7: 0.2117 | N7: =IFERROR(VALUE(M7),"") -> 0.2117 | O7: Négatif | P7: 0.04 | Q7: 0.1868 | S7: Négatif | T7: =IF(LEFT(U7,1)=">","Censure haute",IF(U7="*****","Echec technique","Normal")) -> Normal | U7: 0.2649 | V7: =IFERROR(VALUE(U7),"") -> 0.2649 | W7: Négatif | X7: 0.05 | Y7: 0.083 | AA7: Négatif | AB7: =IF(LEFT(AC7,1)=">","Censure haute",IF(AC7="*****","Non testé","Normal")) -> Normal | AC7: 0.0426 | AD7: 0.0426 | AE7: =IF(ISBLANK(AF7),"",IF(LEFT(AF7,1)=">","Censure haute",IF(AF7="*****","Non testé","Normal"))) | AG7: =IF(ISBLANK(AF7),"",IFERROR(VALUE(AF7),"")) | AH7: Négatif | AI7: 0.031 | AJ7: 0.1496 | AL7: Négatif | AO7: =IF(ISBLANK(AM7),"",IF(AM7=92,IF(T7="Censure haute",120,""),IF(AB7="Censure haute",120,"")))
A8: US-544 | B8: Femme | C8: Non | D8: 17.6 | E8: Poids normal | F8: Non vacciné | I8: 12 | J8: S1 | K8: Négatif | L8: =IF(LEFT(M8,1)=">","Censure haute",IF(M8="*****","Non testé","Normal")) -> Normal | M8: 0.1797 | N8: =IFERROR(VALUE(M8),"") -> 0.1797 | O8: Négatif | P8: 0.041 | Q8: 1.2327 | S8: Réactif | T8: =IF(LEFT(U8,1)=">","Censure haute",IF(U8="*****","Echec technique","Normal")) -> Censure haute | U8: >120 | V8: =IFERROR(VALUE(U8),"") | W8: Réactif | X8: 1.84 | Y8: 0.5941 | AA8: Négatif | AB8: =IF(LEFT(AC8,1)=">","Censure haute",IF(AC8="*****","Non testé","Normal")) -> Censure haute | AC8: >120 | AE8: =IF(ISBLANK(AF8),"",IF(LEFT(AF8,1)=">","Censure haute",IF(AF8="*****","Non testé","Normal"))) | AG8: =IF(ISBLANK(AF8),"",IFERROR(VALUE(AF8),"")) | AH8: Réactif | AI8: 1.691 | AJ8: 6.0625 | AL8: Réactif | AM8: 210 | AN8: 0 | AO8: =IF(ISBLANK(AM8),"",IF(AM8=92,IF(T8="Censure haute",120,""),IF(AB8="Censure haute",120,""))) -> 120
A9: US-551 | B9: Homme | D9: 22.1 | E9: Surpoids | F9: Non vacciné | I9: 12 | J9: S1 | K9: Négatif | L9: =IF(LEFT(M9,1)=">","Censure haute",IF(M9="*****","Non testé","Normal")) -> Normal | M9: 0.2709 | N9: =IFERROR(VALUE(M9),"") -> 0.2709 | O9: Négatif | P9: 0.045 | Q9: 1.1834 | S9: Réactif | T9: =IF(LEFT(U9,1)=">","Censure haute",IF(U9="*****","Echec technique","Normal")) -> Censure haute | U9: >120 | V9: =IFERROR(VALUE(U9),"") | W9: Réactif | X9: 0.321 | Y9: 6.1808 | AA9: Réactif | AB9: =IF(LEFT(AC9,1)=">","Censure haute",IF(AC9="*****","Non testé","Normal")) -> Non testé | AC9: ***** | AE9: =IF(ISBLANK(AF9),"",IF(LEFT(AF9,1)=">","Censure haute",IF(AF9="*****","Non testé","Normal"))) | AG9: =IF(ISBLANK(AF9),"",IFERROR(VALUE(AF9),"")) | AH9: Non testé | AI9: 2.068 | AJ9: 1.9138 | AK9: 1.8862 | AL9: Réactif | AM9: 210 | AN9: 0 | AO9: =IF(ISBLANK(AM9),"",IF(AM9=92,IF(T9="Censure haute",120,""),IF(AB9="Censure haute",120,"")))
A10: US-231 | B10: Homme | C10: Oui | D10: 26.3 | E10: Surpoids | F10: Vacciné | G10: 44453 | H10: 44476 | I10: 15 | J10: S4 | K10: Réactif | L10: =IF(LEFT(M10,1)=">","Censure haute",IF(M10="*****","Non testé","Normal")) -> Normal | M10: 4.4375 | N10: =IFERROR(VALUE(M10),"") -> 4.4375 | O10: Négatif | P10: 0.045 | Q10: 1.1459 | S10: Négatif | T10: =IF(LEFT(U10,1)=">","Censure haute",IF(U10="*****","Echec technique","Normal")) -> Censure haute | U10: >120 | V10: =IFERROR(VALUE(U10),"") | W10: Réactif | X10: 3.329 | Y10: 4.2489 | AA10: Réactif | AB10: =IF(LEFT(AC10,1)=">","Censure haute",IF(AC10="*****","Non testé","Normal")) -> Non testé | AC10: ***** | AE10: =IF(ISBLANK(AF10),"",IF(LEFT(AF10,1)=">","Censure haute",IF(AF10="*****","Non testé","Normal"))) | AG10: =IF(ISBLANK(AF10),"",IFERROR(VALUE(AF10),"")) | AH10: Non testé | AI10: 2.835 | AJ10: 1.7662 | AK10: 1.643 | AL10: Réactif | AM10: 210 | AN10: 0 | AO10: =IF(ISBLANK(AM10),"",IF(AM10=92,IF(T10="Censure haute",120,""),IF(AB10="Censure haute",120,"")))
A11: US-547 | B11: Homme | D11: 21.4 | E11: Surpoids | F11: Non vacciné | I11: 12 | J11: S1 | K11: Négatif | L11: =IF(LEFT(M11,1)=">","Censure haute",IF(M11="*****","Non testé","Normal")) -> Normal | M11: 0.2937 | N11: =IFERROR(VALUE(M11),"") -> 0.2937 | O11: Négatif | P11: 0.046 | Q11: 1.9888 | S11: Réactif | T11: =IF(LEFT(U11,1)=">","Censure haute",IF(U11="*****","Echec technique","Normal")) -> Echec technique | U11: ***** | V11: =IFERROR(VALUE(U11),"") | W11: Non testé | X11: 2.559 | Y11: 7.1226 | AA11: Réactif | AB11: =IF(LEFT(AC11,1)=">","Censure haute",IF(AC11="*****","Non testé","Normal")) -> Censure haute | AC11: >120 | AE11: =IF(ISBLANK(AF11),"",IF(LEFT(AF11,1)=">","Censure haute",IF(AF11="*****","Non testé","Normal"))) | AG11: =IF(ISBLANK(AF11),"",IFERROR(VALUE(AF11),"")) | AH11: Réactif | AI11: 1.132 | AJ11: 4.0134 | AL11: Réactif | AM11: 210 | AN11: 0 | AO11: =IF(ISBLANK(AM11),"",IF(AM11=92,IF(T11="Censure haute",120,""),IF(AB11="Censure haute",120,""))) -> 120
A12: US-530 | B12: Homme | C12: Non | D12: 20.1 | E12: Poids normal | F12: Non vacciné | I12: 15 | J12: S4 | K12: Négatif | L12: =IF(LEFT(M12,1)=">","Censure haute",IF(M12="*****","Non testé","Normal")) -> Normal | M12: 0.665 | N12: =IFERROR(VALUE(M12),"") -> 0.665 | O12: Négatif | P12: 0.048 | Q12: 1.1387 | S12: Réactif | T12: =IF(LEFT(U12,1)=">","Censure haute",IF(U12="*****","Echec technique","Normal")) -> Echec technique | U12: ***** | V12: =IFERROR(VALUE(U12),"") | W12: Non testé | X12: 0.033 | Y12: 0.9011 | AA12: Négatif | AB12: =IF(LEFT(AC12,1)=">","Censure haute",IF(AC12="*****","Non testé","Normal")) -> Censure haute | AC12: >120 | AE12: =IF(ISBLANK(AF12),"",IF(LEFT(AF12,1)=">","Censure haute",IF(AF12="*****","Non testé","Normal"))) | AG12: =IF(ISBLANK(AF12),"",IFERROR(VALUE(AF12),"")) | AH12: Réactif | AI12: 1.945 | AJ12: 0.6033 | AL12: Négatif | AM12: 210 | AN12: 0 | AO12: =IF(ISBLANK(AM12),"",IF(AM12=92,IF(T12="Censure haute",120,""),IF(AB12="Censure haute",120,""))) -> 120
A13: US-149 | B13: Homme | C13: Non | D13: 18.6 | E13: Poids normal | F13: Non vacciné | I13: 12 | J13: S1 | K13: Négatif | L13: =IF(LEFT(M13,1)=">","Censure haute",IF(M13="*****","Non testé","Normal")) -> Normal | M13: 0.365 | N13: =IFERROR(VALUE(M13),"") -> 0.365 | O13: Négatif | P13: 0.052 | Q13: 0.0831 | R13: 0.0814 | S13: Négatif | T13: =IF(LEFT(U13,1)=">","Censure haute",IF(U13="*****","Echec technique","Normal")) -> Censure haute | U13: >120 | V13: =IFERROR(VALUE(U13),"") | W13: Réactif | X13: 3.376 | Y13: 0.1192 | AA13: Négatif | AB13: =IF(LEFT(AC13,1)=">","Censure haute",IF(AC13="*****","Non testé","Normal")) -> Censure haute | AC13: >120 | AE13: =IF(ISBLANK(AF13),"",IF(LEFT(AF13,1)=">","Censure haute",IF(AF13="*****","Non testé","Normal"))) | AG13: =IF(ISBLANK(AF13),"",IFERROR(VALUE(AF13),"")) | AH13: Réactif | AI13: 2.346 | AJ13: 2.2869 | AL13: Réactif | AM13: 210 | AN13: 0 | AO13: =IF(ISBLANK(AM13),"",IF(AM13=92,IF(T13="Censure haute",120,""),IF(AB13="Censure haute",120,""))) -> 120
A14: US-433 | B14: Femme | C14: Oui | D14: 30.8 | E14: Obésité | F14: Non vacciné | I14: 15 | J14: S4 | K14: Négatif | L14: =IF(LEFT(M14,1)=">","Censure haute",IF(M14="*****","Non testé","Normal")) -> Normal | M14: 0.7767 | N14: =IFERROR(VALUE(M14),"") -> 0.7767 | O14: Négatif | P14: 0.053 | Q14: 0.537 | S14: Négatif | T14: =IF(LEFT(U14,1)=">","Censure haute",IF(U14="*****","Echec technique","Normal")) -> Censure haute | U14: >120 | V14: =IFERROR(VALUE(U14),"") | W14: Réactif | X14: 1.131 | Y14: 7.0446 | AA14: Négatif | AB14: =IF(LEFT(AC14,1)=">","Censure haute",IF(AC14="*****","Non testé","Normal")) -> Censure haute | AC14: >120 | AE14: =IF(ISBLANK(AF14),"",IF(LEFT(AF14,1)=">","Censure haute",IF(AF14="*****","Non testé","Normal"))) | AG14: =IF(ISBLANK(AF14),"",IFERROR(VALUE(AF14),"")) | AH14: Réactif | AI14: 0.732 | AJ14: 1.6983 | AL14: Réactif | AM14: 210 | AN14: 0 | AO14: =IF(ISBLANK(AM14),"",IF(AM14=92,IF(T14="Censure haute",120,""),IF(AB14="Censure haute",120,""))) -> 120
A15: US-258 | B15: Homme | C15: Non | D15: 17.8 | E15: Poids normal | F15: Non vacciné | I15: 12 | J15: S1 | K15: Négatif | L15: =IF(LEFT(M15,1)=">","Censure haute",IF(M15="*****","Non testé","Normal")) -> Normal | M15: 0.6755 | N15: =IFERROR(VALUE(M15),"") -> 0.6755 | O15: Négatif | P15: 0.056 | Q15: 0.1332 | S15: Négatif | T15: =IF(LEFT(U15,1)=">","Censure haute",IF(U15="*****","Echec technique","Normal")) -> Echec technique | U15: ***** | V15: =IFERROR(VALUE(U15),"") | W15: Non testé | X15: 0.905 | Y15: 2.6568 | AA15: Réactif | AB15: =IF(LEFT(AC15,1)=">","Censure haute",IF(AC15="*****","Non testé","Normal")) -> Non testé | AC15: ***** | AE15: =IF(ISBLANK(AF15),"",IF(LEFT(AF15,1)=">","Censure haute",IF(AF15="*****","Non testé","Normal"))) | AG15: =IF(ISBLANK(AF15),"",IFERROR(VALUE(AF15),"")) | AH15: Non testé | AI15: 3.5 | AJ15: 2.3841 | AL15: Réactif | AM15: 210 | AN15: 0 | AO15: =IF(ISBLANK(AM15),"",IF(AM15=92,IF(T15="Censure haute",120,""),IF(AB15="Censure haute",120,"")))
A16: US-124 | B16: Femme | C16: Non | D16: 16.8 | E16: Poids normal | F16: Non vacciné | I16: 15 | J16: S4 | K16: Négatif | L16: =IF(LEFT(M16,1)=">","Censure haute",IF(M16="*****","Non testé","Normal")) -> Normal | M16: 0.3431 | N16: =IFERROR(VALUE(M16),"") -> 0.3431 | O16: Négatif | P16: 0.057 | Q16: 0.3231 | S16: Négatif | T16: =IF(LEFT(U16,1)=">","Censure haute",IF(U16="*****","Echec technique","Normal")) -> Censure haute | U16: >120 | V16: =IFERROR(VALUE(U16),"") | W16: Réactif | X16: 0.041 | Y16: 5.6358 | AA16: Réactif | AB16: =IF(LEFT(AC16,1)=">","Censure haute",IF(AC16="*****","Non testé","Normal")) -> Censure haute | AC16: >120 | AE16: =IF(ISBLANK(AF16),"",IF(LEFT(AF16,1)=">","Censure haute",IF(AF16="*****","Non testé","Normal"))) | AG16: =IF(ISBLANK(AF16),"",IFERROR(VALUE(AF16),"")) | AH16: Réactif | AI16: 0.036 | AJ16: 3.0553 | AL16: Réactif | AM16: 210 | AN16: 0 | AO16: =IF(ISBLANK(AM16),"",IF(AM16=92,IF(T16="Censure haute",120,""),IF(AB16="Censure haute",120,""))) -> 120
A17: US-429 | B17: Femme | D17: 16.6 | E17: Poids normal | F17: Non vacciné | I17: 15 | J17: S4 | K17: Négatif | L17: =IF(LEFT(M17,1)=">","Censure haute",IF(M17="*****","Non testé","Normal")) -> Normal | M17: 1 | N17: =IFERROR(VALUE(M17),"") -> 1 | O17: Négatif | P17: 0.063 | Q17: 0.736 | S17: Négatif | T17: =IF(LEFT(U17,1)=">","Censure haute",IF(U17="*****","Echec technique","Normal")) -> Censure haute | U17: >120 | V17: =IFERROR(VALUE(U17),"") | W17: Réactif | X17: 0.868 | Y17: 0.3661 | AA17: Négatif | AB17: =IF(LEFT(AC17,1)=">","Censure haute",IF(AC17="*****","Non testé","Normal")) -> Censure haute | AC17: >120 | AE17: =IF(ISBLANK(AF17),"",IF(LEFT(AF17,1)=">","Censure haute",IF(AF17="*****","Non testé","Normal"))) | AG17: =IF(ISBLANK(AF17),"",IFERROR(VALUE(AF17),"")) | AH17: Réactif | AI17: 0.389 | AJ17: 3.9966 | AL17: Réactif | AM17: 210 | AN17: 0 | AO17: =IF(ISBLANK(AM17),"",IF(AM17=92,IF(T17="Censure haute",120,""),IF(AB17="Censure haute",120,""))) -> 120
A18: US-150 | B18: Femme | C18: Non | D18: 19.3 | E18: Poids normal | F18: Non vacciné | I18: 12 | J18: S1 | K18: Négatif | L18: =IF(LEFT(M18,1)=">","Censure haute",IF(M18="*****","Non testé","Normal")) -> Normal | M18: 0.4307 | N18: =IFERROR(VALUE(M18),"") -> 0.4307 | O18: Négatif | P18: 0.064 | Q18: 0.4397 | R18: 0.4511 | S18: Négatif | T18: =IF(LEFT(U18,1)=">","Censure haute",IF(U18="*****","Echec technique","Normal")) -> Censure haute | U18: >120 | V18: =IFERROR(VALUE(U18),"") | W18: Réactif | X18: 0.128 | Y18: 0.3466 | AA18: Négatif | AB18: =IF(LEFT(AC18,1)=">","Censure haute",IF(AC18="*****","Non testé","Normal")) -> Censure haute | AC18: >120 | AE18: =IF(ISBLANK(AF18),"",IF(LEFT(AF18,1)=">","Censure haute",IF(AF18="*****","Non testé","Normal"))) | AG18: =IF(ISBLANK(AF18),"",IFERROR(VALUE(AF18),"")) | AH18: Réactif | AI18: 0.146 | AJ18: 4.1619 | AL18: Réactif | AM18: 210 | AN18: 0 | AO18: =IF(ISBLANK(AM18),"",IF(AM18=92,IF(T18="Censure haute",120,""),IF(AB18="Censure haute",120,""))) -> 120
A19: US-493 | B19: Femme | D19: 21.2 | E19: Poids normal | F19: Non vacciné | I19: 12 | J19: S1 | K19: Négatif | L19: =IF(LEFT(M19,1)=">","Censure haute",IF(M19="*****","Non testé","Normal")) -> Normal | M19: 1.0447 | N19: =IFERROR(VALUE(M19),"") -> 1.0447 | O19: Négatif | P19: 0.065 | Q19: 2.6629 | S19: Réactif | T19: =IF(LEFT(U19,1)=">","Censure haute",IF(U19="*****","Echec technique","Normal")) -> Censure haute | U19: >120 | V19: =IFERROR(VALUE(U19),"") | W19: Réactif | X19: 0.26 | Y19: 5.6682 | AA19: Réactif | AB19: =IF(LEFT(AC19,1)=">","Censure haute",IF(AC19="*****","Non testé","Normal")) -> Censure haute | AC19: >120 | AE19: =IF(ISBLANK(AF19),"",IF(LEFT(AF19,1)=">","Censure haute",IF(AF19="*****","Non testé","Normal"))) | AG19: =IF(ISBLANK(AF19),"",IFERROR(VALUE(AF19),"")) | AH19: Réactif | AI19: 0.196 | AJ19: 3.5558 | AL19: Réactif | AM19: 210 | AN19: 0 | AO19: =IF(ISBLANK(AM19),"",IF(AM19=92,IF(T19="Censure haute",120,""),IF(AB19="Censure haute",120,""))) -> 120
A20: US-255 | B20: Homme | D20: 21.9 | E20: Surpoids | F20: Non vacciné | I20: 12 | J20: S1 | K20: Négatif | L20: =IF(LEFT(M20,1)=">","Censure haute",IF(M20="*****","Non testé","Normal")) -> Normal | M20: 0.8702 | N20: =IFERROR(VALUE(M20),"") -> 0.8702 | O20: Négatif | P20: 0.065 | Q20: 0.0699 | S20: Négatif | T20: =IF(LEFT(U20,1)=">","Censure haute",IF(U20="*****","Echec technique","Normal")) -> Normal | U20: 17.0308 | V20: =IFERROR(VALUE(U20),"") -> 17.0308 | W20: Réactif | X20: 0.606 | Y20: 0.9958 | AA20: Négatif | AB20: =IF(LEFT(AC20,1)=">","Censure haute",IF(AC20="*****","Non testé","Normal")) -> Non testé | AC20: ***** | AE20: =IF(ISBLANK(AF20),"",IF(LEFT(AF20,1)=">","Censure haute",IF(AF20="*****","Non testé","Normal"))) | AG20: =IF(ISBLANK(AF20),"",IFERROR(VALUE(AF20),"")) | AH20: Non testé | AI20: 0.506 | AJ20: 0.524 | AL20: Négatif | AM20: 92 | AN20: 1 | AO20: =IF(ISBLANK(AM20),"",IF(AM20=92,IF(T20="Censure haute",120,""),IF(AB20="Censure haute",120,"")))
A21: US-134 | B21: Femme | C21: Non | D21: 25.9 | E21: Surpoids | F21: Non vacciné | I21: 15 | J21: S4 | K21: Réactif | L21: =IF(LEFT(M21,1)=">","Censure haute",IF(M21="*****","Non testé","Normal")) -> Normal | M21: 0.5182 | N21: =IFERROR(VALUE(M21),"") -> 0.5182 | O21: Négatif | P21: 0.065 | Q21: 0.2593 | S21: Négatif | T21: =IF(LEFT(U21,1)=">","Censure haute",IF(U21="*****","Echec technique","Normal")) -> Censure haute | U21: >120 | V21: =IFERROR(VALUE(U21),"") | W21: Réactif | X21: 0.384 | Y21: 0.1082 | AA21: Négatif | AB21: =IF(LEFT(AC21,1)=">","Censure haute",IF(AC21="*****","Non testé","Normal")) -> Non testé | AC21: ***** | AE21: =IF(ISBLANK(AF21),"",IF(LEFT(AF21,1)=">","Censure haute",IF(AF21="*****","Non testé","Normal"))) | AG21: =IF(ISBLANK(AF21),"",IFERROR(VALUE(AF21),"")) | AH21: Non testé | AI21: 1.256 | AJ21: 3.0861 | AL21: Réactif | AM21: 210 | AN21: 0 | AO21: =IF(ISBLANK(AM21),"",IF(AM21=92,IF(T21="Censure haute",120,""),IF(AB21="Censure haute",120,"")))
A22: US-137 | B22: Femme | D22: 17.1 | E22: Poids normal | F22: Non vacciné | I22: 14 | J22: S4 | K22: Négatif | L22: =IF(LEFT(M22,1)=">","Censure haute",IF(M22="*****","Non testé","Normal")) -> Normal | M22: 0.6058 | N22: =IFERROR(VALUE(M22),"") -> 0.6058 | O22: Négatif | P22: 0.067 | Q22: 0.3978 | S22: Négatif | T22: =IF(LEFT(U22,1)=">","Censure haute",IF(U22="*****","Echec technique","Normal")) -> Censure haute | U22: >120 | V22: =IFERROR(VALUE(U22),"") | W22: Réactif | X22: 0.403 | Y22: 0.0861 | AA22: Négatif | AB22: =IF(LEFT(AC22,1)=">","Censure haute",IF(AC22="*****","Non testé","Normal")) -> Non testé | AC22: ***** | AE22: =IF(ISBLANK(AF22),"",IF(LEFT(AF22,1)=">","Censure haute",IF(AF22="*****","Non testé","Normal"))) | AG22: =IF(ISBLANK(AF22),"",IFERROR(VALUE(AF22),"")) | AH22: Non testé | AI22: 0.479 | AJ22: 1.9324 | AL22: Réactif | AM22: 210 | AN22: 0 | AO22: =IF(ISBLANK(AM22),"",IF(AM22=92,IF(T22="Censure haute",120,""),IF(AB22="Censure haute",120,"")))
A23: US-229 | B23: Femme | C23: Non | D23: 34.2 | E23: Obésité | F23: Non vacciné | I23: 11 | J23: S1 | K23: Négatif | L23: =IF(LEFT(M23,1)=">","Censure haute",IF(M23="*****","Non testé","Normal")) -> Normal | M23: 1.0216 | N23: =IFERROR(VALUE(M23),"") -> 1.0216 | O23: Négatif | P23: 0.072 | Q23: 0.1416 | S23: Négatif | T23: =IF(LEFT(U23,1)=">","Censure haute",IF(U23="*****","Echec technique","Normal")) -> Echec technique | U23: ***** | V23: =IFERROR(VALUE(U23),"") | W23: Non testé | X23: 0.745 | Y23: 1.7825 | AA23: Réactif | AB23: =IF(LEFT(AC23,1)=">","Censure haute",IF(AC23="*****","Non testé","Normal")) -> Non testé | AC23: ***** | AE23: =IF(ISBLANK(AF23),"",IF(LEFT(AF23,1)=">","Censure haute",IF(AF23="*****","Non testé","Normal"))) | AG23: =IF(ISBLANK(AF23),"",IFERROR(VALUE(AF23),"")) | AH23: Non testé | AI23: 2.678 | AJ23: 6.219 | AL23: Réactif | AM23: 210 | AN23: 0 | AO23: =IF(ISBLANK(AM23),"",IF(AM23=92,IF(T23="Censure haute",120,""),IF(AB23="Censure haute",120,"")))
A24: US-573 | B24: Femme | C24: Non | D24: 22.3 | E24: Surpoids | F24: Non vacciné | I24: 12 | J24: S1 | K24: Négatif | L24: =IF(LEFT(M24,1)=">","Censure haute",IF(M24="*****","Non testé","Normal")) -> Normal | M24: 0.9089 | N24: =IFERROR(VALUE(M24),"") -> 0.9089 | O24: Négatif | P24: 0.073 | Q24: 1.6025 | S24: Réactif | T24: =IF(LEFT(U24,1)=">","Censure haute",IF(U24="*****","Echec technique","Normal")) -> Censure haute | U24: >120 | V24: =IFERROR(VALUE(U24),"") | W24: Réactif | X24: 0.051 | Y24: 0.6138 | AA24: Négatif | AB24: =IF(LEFT(AC24,1)=">","Censure haute",IF(AC24="*****","Non testé","Normal")) -> Censure haute | AC24: >120 | AE24: =IF(ISBLANK(AF24),"",IF(LEFT(AF24,1)=">","Censure haute",IF(AF24="*****","Non testé","Normal"))) | AG24: =IF(ISBLANK(AF24),"",IFERROR(VALUE(AF24),"")) | AH24: Réactif | AI24: 0.073 | AJ24: 0.25 | AL24: Négatif | AM24: 210 | AN24: 0 | AO24: =IF(ISBLANK(AM24),"",IF(AM24=92,IF(T24="Censure haute",120,""),IF(AB24="Censure haute",120,""))) -> 120
A25: US-048 | B25: Homme | C25: Non | D25: 28.6 | E25: Obésité | F25: Non vacciné | I25: 15 | J25: S4 | K25: Négatif | L25: =IF(LEFT(M25,1)=">","Censure haute",IF(M25="*****","Non testé","Normal")) -> Normal | M25: 1.1533 | N25: =IFERROR(VALUE(M25),"") -> 1.1533 | O25: Négatif | P25: 0.074 | Q25: 0.4571 | S25: Négatif | T25: =IF(LEFT(U25,1)=">","Censure haute",IF(U25="*****","Echec technique","Normal")) -> Echec technique | U25: ***** | V25: =IFERROR(VALUE(U25),"") | W25: Non testé | X25: 0.077 | Y25: 1.479 | AA25: Réactif | AB25: =IF(LEFT(AC25,1)=">","Censure haute",IF(AC25="*****","Non testé","Normal")) -> Non testé | AC25: ***** | AE25: =IF(ISBLANK(AF25),"",IF(LEFT(AF25,1)=">","Censure haute",IF(AF25="*****","Non testé","Normal"))) | AG25: =IF(ISBLANK(AF25),"",IFERROR(VALUE(AF25),"")) | AH25: Non testé | AI25: 1.246 | AJ25: 1.2029 | AL25: Réactif | AM25: 210 | AN25: 0 | AO25: =IF(ISBLANK(AM25),"",IF(AM25=92,IF(T25="Censure haute",120,""),IF(AB25="Censure haute",120,"")))
A26: US-066 | B26: Femme | C26: Non | D26: 17.2 | E26: Poids normal | F26: Non vacciné | I26: 12 | J26: S1 | K26: Négatif | L26: =IF(LEFT(M26,1)=">","Censure haute",IF(M26="*****","Non testé","Normal")) -> Normal | M26: 1.1533 | N26: =IFERROR(VALUE(M26),"") -> 1.1533 | O26: Négatif | P26: 0.089 | Q26: 0.2923 | S26: Négatif | T26: =IF(LEFT(U26,1)=">","Censure haute",IF(U26="*****","Echec technique","Normal")) -> Echec technique | U26: ***** | V26: =IFERROR(VALUE(U26),"") | W26: Non testé | X26: 0.684 | Y26: 3.0044 | AA26: Réactif | AB26: =IF(LEFT(AC26,1)=">","Censure haute",IF(AC26="*****","Non testé","Normal")) -> Non testé | AC26: ***** | AE26: =IF(ISBLANK(AF26),"",IF(LEFT(AF26,1)=">","Censure haute",IF(AF26="*****","Non testé","Normal"))) | AG26: =IF(ISBLANK(AF26),"",IFERROR(VALUE(AF26),"")) | AH26: Non testé | AI26: 0.365 | AJ26: 1.3504 | AL26: Réactif | AM26: 210 | AN26: 0 | AO26: =IF(ISBLANK(AM26),"",IF(AM26=92,IF(T26="Censure haute",120,""),IF(AB26="Censure haute",120,"")))
A27: US-169 | B27: Femme | C27: Non | D27: 27.2 | E27: Surpoids | F27: Non vacciné | I27: 15 | J27: S4 | K27: Réactif | L27: =IF(LEFT(M27,1)=">","Censure haute",IF(M27="*****","Non testé","Normal")) -> Normal | M27: 1.3894 | N27: =IFERROR(VALUE(M27),"") -> 1.3894 | O27: Négatif | P27: 0.089 | Q27: 0.0586 | S27: Négatif | T27: =IF(LEFT(U27,1)=">","Censure haute",IF(U27="*****","Echec technique","Normal")) -> Censure haute | U27: >120 | V27: =IFERROR(VALUE(U27),"") | W27: Réactif | X27: 3.5 | Y27: 5.0045 | AA27: Réactif | AB27: =IF(LEFT(AC27,1)=">","Censure haute",IF(AC27="*****","Non testé","Normal")) -> Normal | AC27: 600531 | AD27: 60.0531 | AE27: =IF(ISBLANK(AF27),"",IF(LEFT(AF27,1)=">","Censure haute",IF(AF27="*****","Non testé","Normal"))) | AG27: =IF(ISBLANK(AF27),"",IFERROR(VALUE(AF27),"")) | AH27: Réactif | AI27: 2.813 | AJ27: 1.8802 | AL27: Réactif | AO27: =IF(ISBLANK(AM27),"",IF(AM27=92,IF(T27="Censure haute",120,""),IF(AB27="Censure haute",120,"")))
A28: US-512 | B28: Homme | D28: 16.4 | E28: Poids normal | F28: Non vacciné | I28: 12 | J28: S1 | K28: Réactif | L28: =IF(LEFT(M28,1)=">","Censure haute",IF(M28="*****","Non testé","Normal")) -> Normal | M28: 1.8263 | N28: =IFERROR(VALUE(M28),"") -> 1.8263 | O28: Négatif | P28: 0.1 | Q28: 3.059 | S28: Réactif | T28: =IF(LEFT(U28,1)=">","Censure haute",IF(U28="*****","Echec technique","Normal")) -> Normal | U28: 45.4201 | V28: =IFERROR(VALUE(U28),"") -> 45.4201 | W28: Réactif | X28: 0.207 | Y28: 1.6463 | AA28: Réactif | AB28: =IF(LEFT(AC28,1)=">","Censure haute",IF(AC28="*****","Non testé","Normal")) -> Normal | AC28: 979592 | AD28: 97.9592 | AE28: =IF(ISBLANK(AF28),"",IF(LEFT(AF28,1)=">","Censure haute",IF(AF28="*****","Non testé","Normal"))) | AG28: =IF(ISBLANK(AF28),"",IFERROR(VALUE(AF28),"")) | AH28: Réactif | AI28: 0.218 | AJ28: 5.7516 | AL28: Réactif | AO28: =IF(ISBLANK(AM28),"",IF(AM28=92,IF(T28="Censure haute",120,""),IF(AB28="Censure haute",120,"")))
A29: US-004 | B29: Homme | C29: Non | D29: 16.8 | E29: Poids normal | F29: Non vacciné | I29: 12 | J29: S1 | K29: Négatif | L29: =IF(LEFT(M29,1)=">","Censure haute",IF(M29="*****","Non testé","Normal")) -> Normal | M29: 1.1752 | N29: =IFERROR(VALUE(M29),"") -> 1.1752 | O29: Négatif | P29: 0.101 | Q29: 0.9143 | S29: Négatif | T29: =IF(LEFT(U29,1)=">","Censure haute",IF(U29="*****","Echec technique","Normal")) -> Echec technique | U29: ***** | V29: =IFERROR(VALUE(U29),"") | W29: Non testé | X29: 1.45 | Y29: 0.5828 | AA29: Négatif | AB29: =IF(LEFT(AC29,1)=">","Censure haute",IF(AC29="*****","Non testé","Normal")) -> Censure haute | AC29: >120 | AE29: =IF(ISBLANK(AF29),"",IF(LEFT(AF29,1)=">","Censure haute",IF(AF29="*****","Non testé","Normal"))) | AG29: =IF(ISBLANK(AF29),"",IFERROR(VALUE(AF29),"")) | AH29: Réactif | AI29: 0.972 | AJ29: 0.416 | AL29: Négatif | AM29: 210 | AN29: 0 | AO29: =IF(ISBLANK(AM29),"",IF(AM29=92,IF(T29="Censure haute",120,""),IF(AB29="Censure haute",120,""))) -> 120
A30: US-042 | B30: Femme | D30: 19.5 | E30: Poids normal | F30: Non vacciné | I30: 15 | J30: S4 | K30: Négatif | L30: =IF(LEFT(M30,1)=">","Censure haute",IF(M30="*****","Non testé","Normal")) -> Normal | M30: 1.5474 | N30: =IFERROR(VALUE(M30),"") -> 1.5474 | O30: Négatif | P30: 0.152 | Q30: 0.3495 | S30: Négatif | T30: =IF(LEFT(U30,1)=">","Censure haute",IF(U30="*****","Echec technique","Normal")) -> Echec technique | U30: ***** | V30: =IFERROR(VALUE(U30),"") | W30: Non testé | X30: 0.114 | Y30: 2.0442 | AA30: Réactif | AB30: =IF(LEFT(AC30,1)=">","Censure haute",IF(AC30="*****","Non testé","Normal")) -> Non testé | AC30: ***** | AE30: =IF(ISBLANK(AF30),"",IF(LEFT(AF30,1)=">","Censure haute",IF(AF30="*****","Non testé","Normal"))) | AG30: =IF(ISBLANK(AF30),"",IFERROR(VALUE(AF30),"")) | AH30: Non testé | AI30: 0.142 | AJ30: 5.2398 | AL30: Réactif | AM30: 210 | AN30: 0 | AO30: =IF(ISBLANK(AM30),"",IF(AM30=92,IF(T30="Censure haute",120,""),IF(AB30="Censure haute",120,"")))
A31: US-100 | B31: Femme | C31: Oui | D31: 37.7 | E31: Obésité | F31: Non vacciné | I31: 15 | J31: S4 | K31: Réactif | L31: =IF(LEFT(M31,1)=">","Censure haute",IF(M31="*****","Non testé","Normal")) -> Normal | M31: 3.6058 | N31: =IFERROR(VALUE(M31),"") -> 3.6058 | O31: Négatif | P31: 0.2 | Q31: 0.4725 | S31: Négatif | T31: =IF(LEFT(U31,1)=">","Censure haute",IF(U31="*****","Echec technique","Normal")) -> Censure haute | U31: >120 | V31: =IFERROR(VALUE(U31),"") | W31: Réactif | X31: 2.5 | Y31: 0.4194 | AA31: Négatif | AB31: =IF(LEFT(AC31,1)=">","Censure haute",IF(AC31="*****","Non testé","Normal")) -> Non testé | AC31: ***** | AE31: =IF(ISBLANK(AF31),"",IF(LEFT(AF31,1)=">","Censure haute",IF(AF31="*****","Non testé","Normal"))) | AG31: =IF(ISBLANK(AF31),"",IFERROR(VALUE(AF31),"")) | AH31: Non testé | AI31: 1.843 | AJ31: 1.2684 | AL31: Réactif | AM31: 210 | AN31: 0 | AO31: =IF(ISBLANK(AM31),"",IF(AM31=92,IF(T31="Censure haute",120,""),IF(AB31="Censure haute",120,"")))
A32: US-484 | B32: Femme | C32: Oui | D32: 20.5 | E32: Poids normal | F32: Non vacciné | I32: 12 | J32: S1 | K32: Négatif | L32: =IF(LEFT(M32,1)=">","Censure haute",IF(M32="*****","Non testé","Normal")) -> Normal | M32: 4.1935 | N32: =IFERROR(VALUE(M32),"") -> 4.1935 | O32: Négatif | P32: 0.206 | Q32: 1.3844 | S32: Réactif | T32: =IF(LEFT(U32,1)=">","Censure haute",IF(U32="*****","Echec technique","Normal")) -> Censure haute | U32: >120 | V32: =IFERROR(VALUE(U32),"") | W32: Réactif | X32: 0.068 | Y32: 1.2466 | AA32: Réactif | AB32: =IF(LEFT(AC32,1)=">","Censure haute",IF(AC32="*****","Non testé","Normal")) -> Censure haute | AC32: >120 | AE32: =IF(ISBLANK(AF32),"",IF(LEFT(AF32,1)=">","Censure haute",IF(AF32="*****","Non testé","Normal"))) | AG32: =IF(ISBLANK(AF32),"",IFERROR(VALUE(AF32),"")) | AH32: Réactif | AI32: 0.067 | AJ32: 5.7789 | AL32: Réactif | AM32: 210 | AN32: 0 | AO32: =IF(ISBLANK(AM32),"",IF(AM32=92,IF(T32="Censure haute",120,""),IF(AB32="Censure haute",120,""))) -> 120
A33: US-453 | B33: Femme | C33: Non | D33: 18.8 | E33: Poids normal | F33: Non vacciné | I33: 14 | J33: S4 | K33: Négatif | L33: =IF(LEFT(M33,1)=">","Censure haute",IF(M33="*****","Non testé","Normal")) -> Normal | M33: 4.7742 | N33: =IFERROR(VALUE(M33),"") -> 4.7742 | O33: Négatif | P33: 0.232 | Q33: 1.8154 | S33: Réactif | T33: =IF(LEFT(U33,1)=">","Censure haute",IF(U33="*****","Echec technique","Normal")) -> Normal | U33: 48.7591 | V33: =IFERROR(VALUE(U33),"") -> 48.7591 | W33: Réactif | X33: 3.421 | Y33: 1.5938 | AA33: Réactif | AB33: =IF(LEFT(AC33,1)=">","Censure haute",IF(AC33="*****","Non testé","Normal")) -> Normal | AC33: 378616 | AD33: 37.8616 | AE33: =IF(ISBLANK(AF33),"",IF(LEFT(AF33,1)=">","Censure haute",IF(AF33="*****","Non testé","Normal"))) | AG33: =IF(ISBLANK(AF33),"",IFERROR(VALUE(AF33),"")) | AH33: Réactif | AI33: 3.397 | AJ33: 0.8293 | AL33: Négatif | AO33: =IF(ISBLANK(AM33),"",IF(AM33=92,IF(T33="Censure haute",120,""),IF(AB33="Censure haute",120,"")))
A34: US-082 | B34: Homme | C34: Non | D34: 18.4 | E34: Poids normal | F34: Non vacciné | I34: 15 | J34: S4 | K34: Négatif | L34: =IF(LEFT(M34,1)=">","Censure haute",IF(M34="*****","Non testé","Normal")) -> Normal | M34: 6.0146 | N34: =IFERROR(VALUE(M34),"") -> 6.0146 | O34: Négatif | P34: 0.292 | Q34: 0.2923 | S34: Négatif | T34: =IF(LEFT(U34,1)=">","Censure haute",IF(U34="*****","Echec technique","Normal")) -> Normal | U34: 22.6736 | V34: =IFERROR(VALUE(U34),"") -> 22.6736 | W34: Réactif | X34: 0.382 | Y34: 2.8168 | AA34: Réactif | AB34: =IF(LEFT(AC34,1)=">","Censure haute",IF(AC34="*****","Non testé","Normal")) -> Normal | AC34: 140227 | AD34: 14.0227 | AE34: =IF(ISBLANK(AF34),"",IF(LEFT(AF34,1)=">","Censure haute",IF(AF34="*****","Non testé","Normal"))) | AG34: =IF(ISBLANK(AF34),"",IFERROR(VALUE(AF34),"")) | AH34: Réactif | AI34: 1.631 | AJ34: 1.1209 | AL34: Réactif | AO34: =IF(ISBLANK(AM34),"",IF(AM34=92,IF(T34="Censure haute",120,""),IF(AB34="Censure haute",120,"")))
A35: US-543 | B35: Femme | C35: Non | D35: 17.2 | E35: Poids normal | F35: Non vacciné | I35: 12 | J35: S1 | K35: Négatif | L35: =IF(LEFT(M35,1)=">","Censure haute",IF(M35="*****","Non testé","Normal")) -> Normal | M35: 7.0608 | N35: =IFERROR(VALUE(M35),"") -> 7.0608 | O35: Négatif | P35: 0.343 | Q35: 3.0045 | S35: Réactif | T35: =IF(LEFT(U35,1)=">","Censure haute",IF(U35="*****","Echec technique","Normal")) -> Echec technique | U35: ***** | V35: =IFERROR(VALUE(U35),"") | W35: Non testé | X35: 0.256 | Y35: 1.8034 | AA35: Réactif | AB35: =IF(LEFT(AC35,1)=">","Censure haute",IF(AC35="*****","Non testé","Normal")) -> Non testé | AC35: ***** | AE35: =IF(ISBLANK(AF35),"",IF(LEFT(AF35,1)=">","Censure haute",IF(AF35="*****","Non testé","Normal"))) | AG35: =IF(ISBLANK(AF35),"",IFERROR(VALUE(AF35),"")) | AH35: Non testé | AI35: 2.683 | AJ35: 6.846 | AL35: Réactif | AM35: 210 | AN35: 0 | AO35: =IF(ISBLANK(AM35),"",IF(AM35=92,IF(T35="Censure haute",120,""),IF(AB35="Censure haute",120,"")))
A36: US-118 | B36: Femme | C36: Oui | D36: 18.1 | E36: Poids normal | F36: Non vacciné | I36: 15 | J36: S4 | K36: Réactif | L36: =IF(LEFT(M36,1)=">","Censure haute",IF(M36="*****","Non testé","Normal")) -> Normal | M36: 7.7226 | N36: =IFERROR(VALUE(M36),"") -> 7.7226 | O36: Négatif | P36: 0.36 | Q36: 0.6769 | S36: Négatif | T36: =IF(LEFT(U36,1)=">","Censure haute",IF(U36="*****","Echec technique","Normal")) -> Normal | U36: 7.5745 | V36: =IFERROR(VALUE(U36),"") -> 7.5745 | W36: Négatif | X36: 0.38 | Y36: 0.4415 | AA36: Négatif | AB36: =IF(LEFT(AC36,1)=">","Censure haute",IF(AC36="*****","Non testé","Normal")) -> Censure haute | AC36: >120 | AE36: =IF(ISBLANK(AF36),"",IF(LEFT(AF36,1)=">","Censure haute",IF(AF36="*****","Non testé","Normal"))) | AG36: =IF(ISBLANK(AF36),"",IFERROR(VALUE(AF36),"")) | AH36: Réactif | AI36: 3.023 | AJ36: 6.5984 | AL36: Réactif | AO36: =IF(ISBLANK(AM36),"",IF(AM36=92,IF(T36="Censure haute",120,""),IF(AB36="Censure haute",120,"")))
A37: US-526 | B37: Homme | D37: 21.7 | E37: Poids normal | F37: Non vacciné | I37: 15 | J37: S4 | K37: Réactif | L37: =IF(LEFT(M37,1)=">","Censure haute",IF(M37="*****","Non testé","Normal")) -> Normal | M37: 8.9727 | N37: =IFERROR(VALUE(M37),"") -> 8.9727 | O37: Incertain | P37: 0.42 | Q37: 1.2052 | S37: Réactif | T37: =IF(LEFT(U37,1)=">","Censure haute",IF(U37="*****","Echec technique","Normal")) -> Censure haute | U37: >120 | V37: =IFERROR(VALUE(U37),"") | W37: Réactif | X37: 2.78 | Y37: 5.0761 | AA37: Réactif | AB37: =IF(LEFT(AC37,1)=">","Censure haute",IF(AC37="*****","Non testé","Normal")) -> Censure haute | AC37: >120 | AE37: =IF(ISBLANK(AF37),"",IF(LEFT(AF37,1)=">","Censure haute",IF(AF37="*****","Non testé","Normal"))) | AG37: =IF(ISBLANK(AF37),"",IFERROR(VALUE(AF37),"")) | AH37: Réactif | AI37: 1.221 | AJ37: 2.4363 | AL37: Réactif | AM37: 210 | AN37: 0 | AO37: =IF(ISBLANK(AM37),"",IF(AM37=92,IF(T37="Censure haute",120,""),IF(AB37="Censure haute",120,""))) -> 120
A38: US-440 | B38: Femme | C38: Non | D38: 18 | E38: Poids normal | F38: Non vacciné | I38: 15 | J38: S4 | K38: Réactif | L38: =IF(LEFT(M38,1)=">","Censure haute",IF(M38="*****","Non testé","Normal")) -> Normal | M38: 9.5533 | N38: =IFERROR(VALUE(M38),"") -> 9.5533 | O38: Incertain | P38: 0.446 | Q38: 0.0909 | S38: Négatif | T38: =IF(LEFT(U38,1)=">","Censure haute",IF(U38="*****","Echec technique","Normal")) -> Censure haute | U38: >120 | V38: =IFERROR(VALUE(U38),"") | W38: Réactif | X38: 0.251 | Y38: 1.308 | AA38: Négatif | AB38: =IF(LEFT(AC38,1)=">","Censure haute",IF(AC38="*****","Non testé","Normal")) -> Normal | AC38: 345493 | AD38: 34.5493 | AE38: =IF(ISBLANK(AF38),"",IF(LEFT(AF38,1)=">","Censure haute",IF(AF38="*****","Non testé","Normal"))) | AG38: =IF(ISBLANK(AF38),"",IFERROR(VALUE(AF38),"")) | AH38: Réactif | AI38: 1.774 | AJ38: 0.7414 | AL38: Négatif | AO38: =IF(ISBLANK(AM38),"",IF(AM38=92,IF(T38="Censure haute",120,""),IF(AB38="Censure haute",120,"")))
A39: US-024 | B39: Homme | C39: Non | D39: 19.8 | E39: Poids normal | F39: Non vacciné | I39: 12 | J39: S1 | K39: Négatif | L39: =IF(LEFT(M39,1)=">","Censure haute",IF(M39="*****","Non testé","Normal")) -> Normal | M39: 9.9124 | N39: =IFERROR(VALUE(M39),"") -> 9.9124 | O39: Incertain | P39: 0.47 | Q39: 0.8635 | R39: 0.7942 | S39: Négatif | T39: =IF(LEFT(U39,1)=">","Censure haute",IF(U39="*****","Echec technique","Normal")) -> Censure haute | U39: >120 | V39: =IFERROR(VALUE(U39),"") | W39: Réactif | X39: 2.322 | Y39: 2.8295 | AA39: Réactif | AB39: =IF(LEFT(AC39,1)=">","Censure haute",IF(AC39="*****","Non testé","Normal")) -> Censure haute | AC39: >120 | AE39: =IF(ISBLANK(AF39),"",IF(LEFT(AF39,1)=">","Censure haute",IF(AF39="*****","Non testé","Normal"))) | AG39: =IF(ISBLANK(AF39),"",IFERROR(VALUE(AF39),"")) | AH39: Réactif | AI39: 1.453 | AJ39: 0.5678 | AL39: Négatif | AM39: 210 | AN39: 0 | AO39: =IF(ISBLANK(AM39),"",IF(AM39=92,IF(T39="Censure haute",120,""),IF(AB39="Censure haute",120,""))) -> 120
A40: US-101 | B40: Homme | C40: Non | D40: 21.5 | E40: Poids normal | F40: Non vacciné | I40: 14 | J40: S4 | K40: Réactif | L40: =IF(LEFT(M40,1)=">","Censure haute",IF(M40="*****","Non testé","Normal")) -> Normal | M40: 9.6496 | N40: =IFERROR(VALUE(M40),"") -> 9.6496 | O40: Incertain | P40: 0.486 | Q40: 0.3275 | S40: Négatif | T40: =IF(LEFT(U40,1)=">","Censure haute",IF(U40="*****","Echec technique","Normal")) -> Censure haute | U40: >120 | V40: =IFERROR(VALUE(U40),"") | W40: Réactif | X40: 3.374 | Y40: 0.1649 | AA40: Négatif | AB40: =IF(LEFT(AC40,1)=">","Censure haute",IF(AC40="*****","Non testé","Normal")) -> Non testé | AC40: ***** | AE40: =IF(ISBLANK(AF40),"",IF(LEFT(AF40,1)=">","Censure haute",IF(AF40="*****","Non testé","Normal"))) | AG40: =IF(ISBLANK(AF40),"",IFERROR(VALUE(AF40),"")) | AH40: Non testé | AI40: 1.898 | AJ40: 1.334 | AL40: Réactif | AM40: 210 | AN40: 0 | AO40: =IF(ISBLANK(AM40),"",IF(AM40=92,IF(T40="Censure haute",120,""),IF(AB40="Censure haute",120,"")))
A41: US-223 | B41: Femme | C41: Non | D41: 20.7 | E41: Poids normal | F41: Non vacciné | I41: 12 | J41: S1 | K41: Négatif | L41: =IF(LEFT(M41,1)=">","Censure haute",IF(M41="*****","Non testé","Normal")) -> Normal | M41: 10.7494 | N41: =IFERROR(VALUE(M41),"") -> 10.7494 | O41: Incertain | P41: 0.516 | Q41: 0.1142 | R41: 0.1797 | S41: Négatif | T41: =IF(LEFT(U41,1)=">","Censure haute",IF(U41="*****","Echec technique","Normal")) -> Censure haute | U41: >120 | V41: =IFERROR(VALUE(U41),"") | W41: Réactif | X41: 2.828 | Y41: 0.1256 | AA41: Négatif | AB41: =IF(LEFT(AC41,1)=">","Censure haute",IF(AC41="*****","Non testé","Normal")) -> Normal | AC41: 1071762 | AD41: 107.1762 | AE41: =IF(ISBLANK(AF41),"",IF(LEFT(AF41,1)=">","Censure haute",IF(AF41="*****","Non testé","Normal"))) | AG41: =IF(ISBLANK(AF41),"",IFERROR(VALUE(AF41),"")) | AH41: Réactif | AI41: 1.705 | AJ41: 0.093 | AL41: Négatif | AM41: 182 | AN41: 1 | AO41: =IF(ISBLANK(AM41),"",IF(AM41=92,IF(T41="Censure haute",120,""),IF(AB41="Censure haute",120,"")))
A42: US-287 | B42: Femme | D42: 22.2 | E42: Surpoids | F42: Non vacciné | I42: 12 | J42: S1 | K42: Négatif | L42: =IF(LEFT(M42,1)=">","Censure haute",IF(M42="*****","Non testé","Normal")) -> Normal | M42: 0.7104 | N42: =IFERROR(VALUE(M42),"") -> 0.7104 | O42: Négatif | P42: 0.55 | Q42: 0.7293 | S42: Négatif | T42: =IF(LEFT(U42,1)=">","Censure haute",IF(U42="*****","Echec technique","Normal")) -> Censure haute | U42: >120 | V42: =IFERROR(VALUE(U42),"") | W42: Réactif | X42: 0.053 | Y42: 0.4442 | AA42: Négatif | AB42: =IF(LEFT(AC42,1)=">","Censure haute",IF(AC42="*****","Non testé","Normal")) -> Censure haute | AC42: >120 | AE42: =IF(ISBLANK(AF42),"",IF(LEFT(AF42,1)=">","Censure haute",IF(AF42="*****","Non testé","Normal"))) | AG42: =IF(ISBLANK(AF42),"",IFERROR(VALUE(AF42),"")) | AH42: Réactif | AI42: 0.044 | AJ42: 0.2276 | AL42: Négatif | AM42: 210 | AN42: 0 | AO42: =IF(ISBLANK(AM42),"",IF(AM42=92,IF(T42="Censure haute",120,""),IF(AB42="Censure haute",120,""))) -> 120
A43: US-019 | B43: Femme | C43: Oui | D43: 18.8 | E43: Poids normal | F43: Non vacciné | I43: 12 | J43: S1 | K43: Négatif | L43: =IF(LEFT(M43,1)=">","Censure haute",IF(M43="*****","Non testé","Normal")) -> Normal | M43: 13.4584 | N43: =IFERROR(VALUE(M43),"") -> 13.4584 | O43: Réactif | P43: 0.576 | Q43: 1.0515 | S43: Négatif | T43: =IF(LEFT(U43,1)=">","Censure haute",IF(U43="*****","Echec technique","Normal")) -> Censure haute | U43: >120 | V43: =IFERROR(VALUE(U43),"") | W43: Réactif | X43: 0.57 | Y43: 6.0571 | AA43: Réactif | AB43: =IF(LEFT(AC43,1)=">","Censure haute",IF(AC43="*****","Non testé","Normal")) -> Censure haute | AC43: >120 | AE43: =IF(ISBLANK(AF43),"",IF(LEFT(AF43,1)=">","Censure haute",IF(AF43="*****","Non testé","Normal"))) | AG43: =IF(ISBLANK(AF43),"",IFERROR(VALUE(AF43),"")) | AH43: Réactif | AI43: 2.605 | AJ43: 3.067 | AL43: Réactif | AM43: 210 | AN43: 0 | AO43: =IF(ISBLANK(AM43),"",IF(AM43=92,IF(T43="Censure haute",120,""),IF(AB43="Censure haute",120,""))) -> 120
A44: US-184 | B44: Homme | C44: Non | D44: 18.2 | E44: Poids normal | F44: Non vacciné | I44: 15 | J44: S4 | K44: Réactif | L44: =IF(LEFT(M44,1)=">","Censure haute",IF(M44="*****","Non testé","Normal")) -> Normal | M44: 15.814 | N44: =IFERROR(VALUE(M44),"") -> 15.814 | O44: Réactif | P44: 0.712 | Q44: 0.4642 | S44: Négatif | T44: =IF(LEFT(U44,1)=">","Censure haute",IF(U44="*****","Echec technique","Normal")) -> Echec technique | U44: ***** | V44: =IFERROR(VALUE(U44),"") | W44: Non testé | X44: 3.462 | Y44: 0.5493 | AA44: Négatif | AB44: =IF(LEFT(AC44,1)=">","Censure haute",IF(AC44="*****","Non testé","Normal")) -> Censure haute | AC44: >120 | AE44: =IF(ISBLANK(AF44),"",IF(LEFT(AF44,1)=">","Censure haute",IF(AF44="*****","Non testé","Normal"))) | AG44: =IF(ISBLANK(AF44),"",IFERROR(VALUE(AF44),"")) | AH44: Réactif | AI44: 2.835 | AJ44: 6.2376 | AL44: Réactif | AM44: 210 | AN44: 0 | AO44: =IF(ISBLANK(AM44),"",IF(AM44=92,IF(T44="Censure haute",120,""),IF(AB44="Censure haute",120,""))) -> 120
A45: US-535 | B45: Homme | C45: Non | D45: 15.9 | E45: Poids normal | F45: Non vacciné | I45: 12 | J45: S1 | K45: Réactif | L45: =IF(LEFT(M45,1)=">","Censure haute",IF(M45="*****","Non testé","Normal")) -> Normal | M45: 16.2814 | N45: =IFERROR(VALUE(M45),"") -> 16.2814 | O45: Réactif | P45: 0.716 | Q45: 4.4161 | S45: Réactif | T45: =IF(LEFT(U45,1)=">","Censure haute",IF(U45="*****","Echec technique","Normal")) -> Censure haute | U45: >120 | V45: =IFERROR(VALUE(U45),"") | W45: Réactif | X45: 2.689 | Y45: 5.9366 | AA45: Réactif | AB45: =IF(LEFT(AC45,1)=">","Censure haute",IF(AC45="*****","Non testé","Normal")) -> Censure haute | AC45: >120 | AE45: =IF(ISBLANK(AF45),"",IF(LEFT(AF45,1)=">","Censure haute",IF(AF45="*****","Non testé","Normal"))) | AG45: =IF(ISBLANK(AF45),"",IFERROR(VALUE(AF45),"")) | AH45: Réactif | AI45: 3.155 | AJ45: 3.7701 | AL45: Réactif | AO45: =IF(ISBLANK(AM45),"",IF(AM45=92,IF(T45="Censure haute",120,""),IF(AB45="Censure haute",120,"")))
A46: US-165 | B46: Homme | D46: 16.5 | E46: Poids normal | F46: Non vacciné | I46: 12 | J46: S1 | K46: Réactif | L46: =IF(LEFT(M46,1)=">","Censure haute",IF(M46="*****","Non testé","Normal")) -> Normal | M46: 17.7519 | N46: =IFERROR(VALUE(M46),"") -> 17.7519 | O46: Réactif | P46: 0.787 | Q46: 0.6091 | S46: Négatif | T46: =IF(LEFT(U46,1)=">","Censure haute",IF(U46="*****","Echec technique","Normal")) -> Censure haute | U46: >120 | V46: =IFERROR(VALUE(U46),"") | W46: Réactif | X46: 3.5 | Y46: 0.3722 | AA46: Négatif | AB46: =IF(LEFT(AC46,1)=">","Censure haute",IF(AC46="*****","Non testé","Normal")) -> Censure haute | AC46: >120 | AE46: =IF(ISBLANK(AF46),"",IF(LEFT(AF46,1)=">","Censure haute",IF(AF46="*****","Non testé","Normal"))) | AG46: =IF(ISBLANK(AF46),"",IFERROR(VALUE(AF46),"")) | AH46: Réactif | AI46: 2.118 | AJ46: 5.7107 | AL46: Négatif | AM46: 210 | AN46: 0 | AO46: =IF(ISBLANK(AM46),"",IF(AM46=92,IF(T46="Censure haute",120,""),IF(AB46="Censure haute",120,""))) -> 120
A47: US-518 | B47: Homme | D47: 21 | E47: Poids normal | F47: Non vacciné | I47: 15 | J47: S4 | K47: Négatif | L47: =IF(LEFT(M47,1)=">","Censure haute",IF(M47="*****","Non testé","Normal")) -> Normal | M47: 18.7186 | N47: =IFERROR(VALUE(M47),"") -> 18.7186 | O47: Réactif | P47: 0.813 | Q47: 4.1943 | S47: Réactif | T47: =IF(LEFT(U47,1)=">","Censure haute",IF(U47="*****","Echec technique","Normal")) -> Censure haute | U47: >120 | V47: =IFERROR(VALUE(U47),"") | W47: Réactif | X47: 2.793 | Y47: 5.7368 | AA47: Réactif | AB47: =IF(LEFT(AC47,1)=">","Censure haute",IF(AC47="*****","Non testé","Normal")) -> Non testé | AC47: ***** | AE47: =IF(ISBLANK(AF47),"",IF(LEFT(AF47,1)=">","Censure haute",IF(AF47="*****","Non testé","Normal"))) | AG47: =IF(ISBLANK(AF47),"",IFERROR(VALUE(AF47),"")) | AH47: Non testé | AI47: 1.61 | AJ47: 2.7349 | AL47: Réactif | AM47: 210 | AN47: 0 | AO47: =IF(ISBLANK(AM47),"",IF(AM47=92,IF(T47="Censure haute",120,""),IF(AB47="Censure haute",120,"")))
A48: US-221 | B48: Homme | C48: Non | D48: 19.2 | E48: Poids normal | F48: Non vacciné | I48: 12 | J48: S1 | K48: Réactif | L48: =IF(LEFT(M48,1)=">","Censure haute",IF(M48="*****","Non testé","Normal")) -> Normal | M48: 20.1524 | N48: =IFERROR(VALUE(M48),"") -> 20.1524 | O48: Réactif | P48: 0.878 | Q48: 0.6107 | S48: Négatif | T48: =IF(LEFT(U48,1)=">","Censure haute",IF(U48="*****","Echec technique","Normal")) -> Censure haute | U48: >120 | V48: =IFERROR(VALUE(U48),"") | W48: Réactif | X48: 0.0738 | Y48: 6.2152 | AA48: Réactif | AB48: =IF(LEFT(AC48,1)=">","Censure haute",IF(AC48="*****","Non testé","Normal")) -> Non testé | AC48: ***** | AE48: =IF(ISBLANK(AF48),"",IF(LEFT(AF48,1)=">","Censure haute",IF(AF48="*****","Non testé","Normal"))) | AG48: =IF(ISBLANK(AF48),"",IFERROR(VALUE(AF48),"")) | AH48: Non testé | AI48: 2.979 | AJ48: 4.9855 | AL48: Réactif | AM48: 210 | AN48: 0 | AO48: =IF(ISBLANK(AM48),"",IF(AM48=92,IF(T48="Censure haute",120,""),IF(AB48="Censure haute",120,"")))
A49: US-035 | B49: Femme | C49: Non | D49: 20.8 | E49: Poids normal | F49: Non vacciné | I49: 15 | J49: S4 | K49: Réactif | L49: =IF(LEFT(M49,1)=">","Censure haute",IF(M49="*****","Non testé","Normal")) -> Normal | M49: 24.3443 | N49: =IFERROR(VALUE(M49),"") -> 24.3443 | O49: Réactif | P49: 0.934 | Q49: 0.2176 | R49: 0.2527 | S49: Négatif | T49: =IF(LEFT(U49,1)=">","Censure haute",IF(U49="*****","Echec technique","Normal")) -> Echec technique | U49: ***** | V49: =IFERROR(VALUE(U49),"") | W49: Non testé | X49: 2.417 | Y49: 4.2185 | AA49: Réactif | AB49: =IF(LEFT(AC49,1)=">","Censure haute",IF(AC49="*****","Non testé","Normal")) -> Censure haute | AC49: >120 | AE49: =IF(ISBLANK(AF49),"",IF(LEFT(AF49,1)=">","Censure haute",IF(AF49="*****","Non testé","Normal"))) | AG49: =IF(ISBLANK(AF49),"",IFERROR(VALUE(AF49),"")) | AH49: Réactif | AI49: 1.218 | AJ49: 1.3463 | AK49: 1.3074 | AL49: Réactif | AM49: 210 | AN49: 0 | AO49: =IF(ISBLANK(AM49),"",IF(AM49=92,IF(T49="Censure haute",120,""),IF(AB49="Censure haute",120,""))) -> 120
A50: US-087 | B50: Homme | C50: Non | D50: 21.6 | E50: Poids normal | F50: Non vacciné | I50: 14 | J50: S4 | K50: Réactif | L50: =IF(LEFT(M50,1)=">","Censure haute",IF(M50="*****","Non testé","Normal")) -> Normal | M50: 26.8306 | N50: =IFERROR(VALUE(M50),"") -> 26.8306 | O50: Réactif | P50: 1.04 | Q50: 0.3538 | S50: Négatif | T50: =IF(LEFT(U50,1)=">","Censure haute",IF(U50="*****","Echec technique","Normal")) -> Normal | U50: 19.3798 | V50: =IFERROR(VALUE(U50),"") -> 19.3798 | W50: Réactif | X50: 2.908 | Y50: 3.7196 | AA50: Réactif | AB50: =IF(LEFT(AC50,1)=">","Censure haute",IF(AC50="*****","Non testé","Normal")) -> Normal | AC50: 114731 | AD50: 11.4731 | AE50: =IF(ISBLANK(AF50),"",IF(LEFT(AF50,1)=">","Censure haute",IF(AF50="*****","Non testé","Normal"))) | AG50: =IF(ISBLANK(AF50),"",IFERROR(VALUE(AF50),"")) | AH50: Réactif | AI50: 2.248 | AJ50: 1.3607 | AL50: Réactif | AO50: =IF(ISBLANK(AM50),"",IF(AM50=92,IF(T50="Censure haute",120,""),IF(AB50="Censure haute",120,"")))
A51: US-253 | B51: Homme | D51: 24.2 | E51: Surpoids | F51: Non vacciné | I51: 12 | J51: S1 | K51: Réactif | L51: =IF(LEFT(M51,1)=">","Censure haute",IF(M51="*****","Non testé","Normal")) -> Normal | M51: 31.6952 | N51: =IFERROR(VALUE(M51),"") -> 31.6952 | O51: Réactif | P51: 1.181 | Q51: 0.0973 | S51: Négatif | T51: =IF(LEFT(U51,1)=">","Censure haute",IF(U51="*****","Echec technique","Normal")) -> Echec technique | U51: ***** | V51: =IFERROR(VALUE(U51),"") | W51: Non testé | X51: 3.361 | Y51: 3.6427 | AA51: Réactif | AB51: =IF(LEFT(AC51,1)=">","Censure haute",IF(AC51="*****","Non testé","Normal")) -> Censure haute | AC51: >120 | AE51: =IF(ISBLANK(AF51),"",IF(LEFT(AF51,1)=">","Censure haute",IF(AF51="*****","Non testé","Normal"))) | AG51: =IF(ISBLANK(AF51),"",IFERROR(VALUE(AF51),"")) | AH51: Réactif | AI51: 2.808 | AJ51: 1.95 | AL51: Réactif | AM51: 210 | AN51: 0 | AO51: =IF(ISBLANK(AM51),"",IF(AM51=92,IF(T51="Censure haute",120,""),IF(AB51="Censure haute",120,""))) -> 120
A52: US-220 | B52: Homme | D52: 15.5 | E52: Poids normal | F52: Non vacciné | I52: 11 | J52: S1 | K52: Réactif | L52: =IF(LEFT(M52,1)=">","Censure haute",IF(M52="*****","Non testé","Normal")) -> Normal | M52: 32.1524 | N52: =IFERROR(VALUE(M52),"") -> 32.1524 | O52: Réactif | P52: 1.193 | Q52: 0.1726 | S52: Négatif | T52: =IF(LEFT(U52,1)=">","Censure haute",IF(U52="*****","Echec technique","Normal")) -> Echec technique | U52: ***** | V52: =IFERROR(VALUE(U52),"") | W52: Non testé | X52: 1.092 | Y52: 3.5628 | AA52: Réactif | AB52: =IF(LEFT(AC52,1)=">","Censure haute",IF(AC52="*****","Non testé","Normal")) -> Non testé | AC52: ***** | AE52: =IF(ISBLANK(AF52),"",IF(LEFT(AF52,1)=">","Censure haute",IF(AF52="*****","Non testé","Normal"))) | AG52: =IF(ISBLANK(AF52),"",IFERROR(VALUE(AF52),"")) | AH52: Non testé | AI52: 3.452 | AJ52: 1.2562 | AL52: Réactif | AM52: 210 | AN52: 0 | AO52: =IF(ISBLANK(AM52),"",IF(AM52=92,IF(T52="Censure haute",120,""),IF(AB52="Censure haute",120,"")))
A53: US-273 | B53: Femme | C53: Non | D53: 15.9 | E53: Poids normal | F53: Non vacciné | I53: 12 | J53: S1 | K53: Réactif | L53: =IF(LEFT(M53,1)=">","Censure haute",IF(M53="*****","Non testé","Normal")) -> Normal | M53: 28.6196 | N53: =IFERROR(VALUE(M53),"") -> 28.6196 | O53: Réactif | P53: 1.196 | Q53: 0.0633 | S53: Négatif | T53: =IF(LEFT(U53,1)=">","Censure haute",IF(U53="*****","Echec technique","Normal")) -> Censure haute | U53: >120 | V53: =IFERROR(VALUE(U53),"") | W53: Réactif | X53: 3.334 | Y53: 1.8589 | AA53: Réactif | AB53: =IF(LEFT(AC53,1)=">","Censure haute",IF(AC53="*****","Non testé","Normal")) -> Censure haute | AC53: >120 | AE53: =IF(ISBLANK(AF53),"",IF(LEFT(AF53,1)=">","Censure haute",IF(AF53="*****","Non testé","Normal"))) | AG53: =IF(ISBLANK(AF53),"",IFERROR(VALUE(AF53),"")) | AH53: Réactif | AI53: 2.075 | AJ53: 0.6472 | AL53: Négatif | AM53: 210 | AN53: 0 | AO53: =IF(ISBLANK(AM53),"",IF(AM53=92,IF(T53="Censure haute",120,""),IF(AB53="Censure haute",120,""))) -> 120
A54: US-191 | B54: Femme | C54: Oui | D54: 18.2 | E54: Poids normal | F54: Non vacciné | I54: 15 | J54: S4 | K54: Réactif | L54: =IF(LEFT(M54,1)=">","Censure haute",IF(M54="*****","Non testé","Normal")) -> Normal | M54: 33.2952 | N54: =IFERROR(VALUE(M54),"") -> 33.2952 | O54: Réactif | P54: 1.223 | Q54: 0.0651 | S54: Négatif | T54: =IF(LEFT(U54,1)=">","Censure haute",IF(U54="*****","Echec technique","Normal")) -> Echec technique | U54: ***** | V54: =IFERROR(VALUE(U54),"") | W54: Non testé | X54: 2.981 | Y54: 0.9686 | AA54: Négatif | AB54: =IF(LEFT(AC54,1)=">","Censure haute",IF(AC54="*****","Non testé","Normal")) -> Non testé | AC54: ***** | AE54: =IF(ISBLANK(AF54),"",IF(LEFT(AF54,1)=">","Censure haute",IF(AF54="*****","Non testé","Normal"))) | AG54: =IF(ISBLANK(AF54),"",IFERROR(VALUE(AF54),"")) | AH54: Non testé | AI54: 2.469 | AJ54: 3.6942 | AL54: Réactif | AM54: 210 | AN54: 0 | AO54: =IF(ISBLANK(AM54),"",IF(AM54=92,IF(T54="Censure haute",120,""),IF(AB54="Censure haute",120,"")))
A55: US-054 | B55: Femme | D55: 17.2 | E55: Poids normal | F55: Non vacciné | I55: 12 | J55: S1 | K55: Négatif | L55: =IF(LEFT(M55,1)=">","Censure haute",IF(M55="*****","Non testé","Normal")) -> Normal | M55: 33.1421 | N55: =IFERROR(VALUE(M55),"") -> 33.1421 | O55: Réactif | P55: 1.283 | Q55: 0.5604 | S55: Négatif | T55: =IF(LEFT(U55,1)=">","Censure haute",IF(U55="*****","Echec technique","Normal")) -> Echec technique | U55: ***** | V55: =IFERROR(VALUE(U55),"") | W55: Non testé | X55: 3.29 | Y55: 6.7726 | AA55: Réactif | AB55: =IF(LEFT(AC55,1)=">","Censure haute",IF(AC55="*****","Non testé","Normal")) -> Censure haute | AC55: >120 | AE55: =IF(ISBLANK(AF55),"",IF(LEFT(AF55,1)=">","Censure haute",IF(AF55="*****","Non testé","Normal"))) | AG55: =IF(ISBLANK(AF55),"",IFERROR(VALUE(AF55),"")) | AH55: Réactif | AI55: 2.581 | AJ55: 3.6414 | AL55: Réactif | AM55: 210 | AN55: 0 | AO55: =IF(ISBLANK(AM55),"",IF(AM55=92,IF(T55="Censure haute",120,""),IF(AB55="Censure haute",120,""))) -> 120
A56: US-532 | B56: Homme | C56: Non | D56: 24.2 | E56: Surpoids | F56: Non vacciné | I56: 12 | J56: S1 | K56: Négatif | L56: =IF(LEFT(M56,1)=">","Censure haute",IF(M56="*****","Non testé","Normal")) -> Normal | M56: 37.97 | N56: =IFERROR(VALUE(M56),"") -> 37.97 | O56: Réactif | P56: 1.404 | Q56: 1.3154 | S56: Réactif | T56: =IF(LEFT(U56,1)=">","Censure haute",IF(U56="*****","Echec technique","Normal")) -> Censure haute | U56: >120 | V56: =IFERROR(VALUE(U56),"") | W56: Réactif | X56: 0.934 | Y56: 5.5284 | AA56: Réactif | AB56: =IF(LEFT(AC56,1)=">","Censure haute",IF(AC56="*****","Non testé","Normal")) -> Censure haute | AC56: >120 | AE56: =IF(ISBLANK(AF56),"",IF(LEFT(AF56,1)=">","Censure haute",IF(AF56="*****","Non testé","Normal"))) | AG56: =IF(ISBLANK(AF56),"",IFERROR(VALUE(AF56),"")) | AH56: Réactif | AI56: 3.379 | AJ56: 1.6347 | AL56: Réactif | AM56: 210 | AN56: 0 | AO56: =IF(ISBLANK(AM56),"",IF(AM56=92,IF(T56="Censure haute",120,""),IF(AB56="Censure haute",120,""))) -> 120
A57: US-005 | B57: Femme | C57: Oui | D57: 16.3 | E57: Poids normal | F57: Non vacciné | I57: 12 | J57: S1 | K57: Négatif | L57: =IF(LEFT(M57,1)=">","Censure haute",IF(M57="*****","Non testé","Normal")) -> Normal | M57: 41.0127 | N57: =IFERROR(VALUE(M57),"") -> 41.0127 | O57: Réactif | P57: 1.466 | Q57: 0.8 | S57: Négatif | T57: =IF(LEFT(U57,1)=">","Censure haute",IF(U57="*****","Echec technique","Normal")) -> Censure haute | U57: >120 | V57: =IFERROR(VALUE(U57),"") | W57: Réactif | X57: 1.63 | Y57: 0.6159 | AA57: Négatif | AB57: =IF(LEFT(AC57,1)=">","Censure haute",IF(AC57="*****","Non testé","Normal")) -> Censure haute | AC57: >120 | AE57: =IF(ISBLANK(AF57),"",IF(LEFT(AF57,1)=">","Censure haute",IF(AF57="*****","Non testé","Normal"))) | AG57: =IF(ISBLANK(AF57),"",IFERROR(VALUE(AF57),"")) | AH57: Réactif | AI57: 1.211 | AJ57: 0.2254 | AL57: Négatif | AM57: 210 | AN57: 0 | AO57: =IF(ISBLANK(AM57),"",IF(AM57=92,IF(T57="Censure haute",120,""),IF(AB57="Censure haute",120,""))) -> 120
A58: US-135 | B58: Homme | C58: Non | D58: 17.4 | E58: Poids normal | F58: Vacciné | G58: 44453 | H58: 44476 | I58: 15 | J58: S4 | K58: Négatif | L58: =IF(LEFT(M58,1)=">","Censure haute",IF(M58="*****","Non testé","Normal")) -> Normal | M58: 39.2077 | N58: =IFERROR(VALUE(M58),"") -> 39.2077 | O58: Réactif | P58: 1.558 | Q58: 0.2462 | S58: Négatif | T58: =IF(LEFT(U58,1)=">","Censure haute",IF(U58="*****","Echec technique","Normal")) -> Normal | U58: 8.0638 | V58: =IFERROR(VALUE(U58),"") -> 8.0638 | W58: Incertain | X58: 3.5 | Y58: 1.0508 | AA58: Négatif | AB58: =IF(LEFT(AC58,1)=">","Censure haute",IF(AC58="*****","Non testé","Normal")) -> Normal | AC58: 109065 | AD58: 10.9065 | AE58: =IF(ISBLANK(AF58),"",IF(LEFT(AF58,1)=">","Censure haute",IF(AF58="*****","Non testé","Normal"))) | AG58: =IF(ISBLANK(AF58),"",IFERROR(VALUE(AF58),"")) | AH58: Incertain | AI58: 2.836 | AJ58: 0.7643 | AL58: Négatif | AO58: =IF(ISBLANK(AM58),"",IF(AM58=92,IF(T58="Censure haute",120,""),IF(AB58="Censure haute",120,"")))
A59: US-457 | B59: Femme | C59: Non | D59: 18 | E59: Poids normal | F59: Non vacciné | I59: 12 | J59: S1 | K59: Négatif | L59: =IF(LEFT(M59,1)=">","Censure haute",IF(M59="*****","Non testé","Normal")) -> Normal | M59: 49.32 | N59: =IFERROR(VALUE(M59),"") -> 49.32 | O59: Réactif | P59: 1.674 | Q59: 1.5604 | S59: Réactif | T59: =IF(LEFT(U59,1)=">","Censure haute",IF(U59="*****","Echec technique","Normal")) -> Echec technique | U59: ***** | V59: =IFERROR(VALUE(U59),"") | W59: Non testé | X59: 0.971 | Y59: 2.0464 | AA59: Réactif | AB59: =IF(LEFT(AC59,1)=">","Censure haute",IF(AC59="*****","Non testé","Normal")) -> Censure haute | AC59: >120 | AE59: =IF(ISBLANK(AF59),"",IF(LEFT(AF59,1)=">","Censure haute",IF(AF59="*****","Non testé","Normal"))) | AG59: =IF(ISBLANK(AF59),"",IFERROR(VALUE(AF59),"")) | AH59: Réactif | AI59: 0.741 | AJ59: 1.6107 | AL59: Réactif | AM59: 210 | AN59: 0 | AO59: =IF(ISBLANK(AM59),"",IF(AM59=92,IF(T59="Censure haute",120,""),IF(AB59="Censure haute",120,""))) -> 120
A60: US-182 | B60: Homme | C60: Non | D60: 17.4 | E60: Poids normal | F60: Non vacciné | I60: 15 | J60: S4 | K60: Négatif | L60: =IF(LEFT(M60,1)=">","Censure haute",IF(M60="*****","Non testé","Normal")) -> Normal | M60: 54.3849 | N60: =IFERROR(VALUE(M60),"") -> 54.3849 | O60: Réactif | P60: 1.741 | Q60: 0.0961 | S60: Négatif | T60: =IF(LEFT(U60,1)=">","Censure haute",IF(U60="*****","Echec technique","Normal")) -> Censure haute | U60: >120 | V60: =IFERROR(VALUE(U60),"") | W60: Réactif | X60: 1.249 | Y60: 0.6233 | AA60: Négatif | AB60: =IF(LEFT(AC60,1)=">","Censure haute",IF(AC60="*****","Non testé","Normal")) -> Censure haute | AC60: >120 | AE60: =IF(ISBLANK(AF60),"",IF(LEFT(AF60,1)=">","Censure haute",IF(AF60="*****","Non testé","Normal"))) | AG60: =IF(ISBLANK(AF60),"",IFERROR(VALUE(AF60),"")) | AH60: Réactif | AI60: 1.093 | AJ60: 0.564 | AL60: Négatif | AM60: 210 | AN60: 0 | AO60: =IF(ISBLANK(AM60),"",IF(AM60=92,IF(T60="Censure haute",120,""),IF(AB60="Censure haute",120,""))) -> 120
A61: US-280 | B61: Femme | C61: Non | D61: 35.5 | E61: Obésité | F61: Non vacciné | I61: 14 | J61: S4 | K61: Négatif | L61: =IF(LEFT(M61,1)=">","Censure haute",IF(M61="*****","Non testé","Normal")) -> Normal | M61: 51.5217 | N61: =IFERROR(VALUE(M61),"") -> 51.5217 | O61: Réactif | P61: 1.779 | Q61: 0.4295 | S61: Négatif | T61: =IF(LEFT(U61,1)=">","Censure haute",IF(U61="*****","Echec technique","Normal")) -> Censure haute | U61: >120 | V61: =IFERROR(VALUE(U61),"") | W61: Réactif | X61: 3.102 | Y61: 0.3642 | AA61: Négatif | AB61: =IF(LEFT(AC61,1)=">","Censure haute",IF(AC61="*****","Non testé","Normal")) -> Non testé | AC61: ***** | AE61: =IF(ISBLANK(AF61),"",IF(LEFT(AF61,1)=">","Censure haute",IF(AF61="*****","Non testé","Normal"))) | AG61: =IF(ISBLANK(AF61),"",IFERROR(VALUE(AF61),"")) | AH61: Non testé | AI61: 2.807 | AJ61: 3.3653 | AL61: Réactif | AM61: 210 | AN61: 0 | AO61: =IF(ISBLANK(AM61),"",IF(AM61=92,IF(T61="Censure haute",120,""),IF(AB61="Censure haute",120,"")))
A62: US-292 | B62: Femme | C62: Non | D62: 25.5 | E62: Surpoids | F62: Non vacciné | I62: 12 | J62: S1 | K62: Réactif | L62: =IF(LEFT(M62,1)=">","Censure haute",IF(M62="*****","Non testé","Normal")) -> Normal | M62: 64.5652 | N62: =IFERROR(VALUE(M62),"") -> 64.5652 | O62: Réactif | P62: 2.019 | Q62: 0.1477 | S62: Négatif | T62: =IF(LEFT(U62,1)=">","Censure haute",IF(U62="*****","Echec technique","Normal")) -> Echec technique | U62: ***** | V62: =IFERROR(VALUE(U62),"") | W62: Non testé | X62: 1.466 | Y62: 0.5032 | AA62: Négatif | AB62: =IF(LEFT(AC62,1)=">","Censure haute",IF(AC62="*****","Non testé","Normal")) -> Censure haute | AC62: >120 | AE62: =IF(ISBLANK(AF62),"",IF(LEFT(AF62,1)=">","Censure haute",IF(AF62="*****","Non testé","Normal"))) | AG62: =IF(ISBLANK(AF62),"",IFERROR(VALUE(AF62),"")) | AH62: Réactif | AI62: 2.407 | AJ62: 0.6263 | AL62: Négatif | AM62: 210 | AN62: 0 | AO62: =IF(ISBLANK(AM62),"",IF(AM62=92,IF(T62="Censure haute",120,""),IF(AB62="Censure haute",120,""))) -> 120
A63: US-257 | B63: Femme | D63: 18.9 | E63: Poids normal | F63: Non vacciné | I63: 12 | J63: S1 | K63: Négatif | L63: =IF(LEFT(M63,1)=">","Censure haute",IF(M63="*****","Non testé","Normal")) -> Normal | M63: 66.1199 | N63: =IFERROR(VALUE(M63),"") -> 66.1199 | O63: Réactif | P63: 2.02 | Q63: 0.2817 | S63: Négatif | T63: =IF(LEFT(U63,1)=">","Censure haute",IF(U63="*****","Echec technique","Normal")) -> Echec technique | U63: ***** | V63: =IFERROR(VALUE(U63),"") | W63: Non testé | X63: 3.5 | Y63: 0.32 | AA63: Négatif | AB63: =IF(LEFT(AC63,1)=">","Censure haute",IF(AC63="*****","Non testé","Normal")) -> Censure haute | AC63: >120 | AE63: =IF(ISBLANK(AF63),"",IF(LEFT(AF63,1)=">","Censure haute",IF(AF63="*****","Non testé","Normal"))) | AG63: =IF(ISBLANK(AF63),"",IFERROR(VALUE(AF63),"")) | AH63: Réactif | AI63: 3.5 | AJ63: 0.2547 | AL63: Négatif | AM63: 210 | AN63: 0 | AO63: =IF(ISBLANK(AM63),"",IF(AM63=92,IF(T63="Censure haute",120,""),IF(AB63="Censure haute",120,""))) -> 120
A64: US-161 | B64: Femme | C64: Oui | D64: 17.8 | E64: Poids normal | F64: Non vacciné | I64: 11 | J64: S1 | K64: Réactif | L64: =IF(LEFT(M64,1)=">","Censure haute",IF(M64="*****","Non testé","Normal")) -> Normal | M64: 68.7697 | N64: =IFERROR(VALUE(M64),"") -> 68.7697 | O64: Réactif | P64: 2.083 | Q64: 0.158 | S64: Négatif | T64: =IF(LEFT(U64,1)=">","Censure haute",IF(U64="*****","Echec technique","Normal")) -> Echec technique | U64: ***** | V64: =IFERROR(VALUE(U64),"") | W64: Non testé | X64: 1.405 | Y64: 1.5673 | AA64: Réactif | AB64: =IF(LEFT(AC64,1)=">","Censure haute",IF(AC64="*****","Non testé","Normal")) -> Normal | AC64: 118004 | AD64: 11.8004 | AE64: =IF(ISBLANK(AF64),"",IF(LEFT(AF64,1)=">","Censure haute",IF(AF64="*****","Non testé","Normal"))) | AG64: =IF(ISBLANK(AF64),"",IFERROR(VALUE(AF64),"")) | AH64: Réactif | AI64: 1.043 | AJ64: 0.8616 | AL64: Négatif | AM64: 182 | AN64: 1 | AO64: =IF(ISBLANK(AM64),"",IF(AM64=92,IF(T64="Censure haute",120,""),IF(AB64="Censure haute",120,"")))
A65: US-178 | B65: Femme | C65: Oui | D65: 20.2 | E65: Poids normal | F65: Non vacciné | I65: 15 | J65: S4 | K65: Réactif | L65: =IF(LEFT(M65,1)=">","Censure haute",IF(M65="*****","Non testé","Normal")) -> Normal | M65: 102.3404 | N65: =IFERROR(VALUE(M65),"") -> 102.3404 | O65: Réactif | P65: 2.455 | Q65: 0.0977 | S65: Négatif | T65: =IF(LEFT(U65,1)=">","Censure haute",IF(U65="*****","Echec technique","Normal")) -> Censure haute | U65: >120 | V65: =IFERROR(VALUE(U65),"") | W65: Réactif | X65: 3.062 | Y65: 3.935 | AA65: Réactif | AB65: =IF(LEFT(AC65,1)=">","Censure haute",IF(AC65="*****","Non testé","Normal")) -> Censure haute | AC65: >120 | AE65: =IF(ISBLANK(AF65),"",IF(LEFT(AF65,1)=">","Censure haute",IF(AF65="*****","Non testé","Normal"))) | AG65: =IF(ISBLANK(AF65),"",IFERROR(VALUE(AF65),"")) | AH65: Réactif | AI65: 3.5 | AJ65: 2.1302 | AL65: Réactif | AM65: 210 | AN65: 0 | AO65: =IF(ISBLANK(AM65),"",IF(AM65=92,IF(T65="Censure haute",120,""),IF(AB65="Censure haute",120,""))) -> 120
A66: US-528 | B66: Femme | C66: Non | D66: 17.9 | E66: Poids normal | F66: Vacciné | G66: 44453 | H66: 44476 | I66: 15 | J66: S4 | K66: Réactif | L66: =IF(LEFT(M66,1)=">","Censure haute",IF(M66="*****","Non testé","Normal")) -> Normal | M66: 95.0324 | N66: =IFERROR(VALUE(M66),"") -> 95.0324 | O66: Réactif | P66: 2.536 | Q66: 1.6353 | R66: 1.6913 | S66: Réactif | T66: =IF(LEFT(U66,1)=">","Censure haute",IF(U66="*****","Echec technique","Normal")) -> Censure haute | U66: >120 | V66: =IFERROR(VALUE(U66),"") | W66: Réactif | X66: 2.899 | Y66: 5.6421 | AA66: Réactif | AB66: =IF(LEFT(AC66,1)=">","Censure haute",IF(AC66="*****","Non testé","Normal")) -> Censure haute | AC66: >120 | AE66: =IF(ISBLANK(AF66),"",IF(LEFT(AF66,1)=">","Censure haute",IF(AF66="*****","Non testé","Normal"))) | AG66: =IF(ISBLANK(AF66),"",IFERROR(VALUE(AF66),"")) | AH66: Réactif | AI66: 2.284 | AJ66: 2.3967 | AL66: Réactif | AM66: 210 | AN66: 0 | AO66: =IF(ISBLANK(AM66),"",IF(AM66=92,IF(T66="Censure haute",120,""),IF(AB66="Censure haute",120,""))) -> 120
A67: US-475 | B67: Homme | C67: Oui | D67: 30.5 | E67: Obésité | F67: Vacciné | G67: 44453 | H67: 44477 | I67: 12 | J67: S1 | K67: Négatif | L67: =IF(LEFT(M67,1)=">","Censure haute",IF(M67="*****","Non testé","Normal")) -> Normal | M67: 101.8575 | N67: =IFERROR(VALUE(M67),"") -> 101.8575 | O67: Réactif | P67: 2.615 | Q67: 2.2622 | S67: Réactif | T67: =IF(LEFT(U67,1)=">","Censure haute",IF(U67="*****","Echec technique","Normal")) -> Normal | U67: 38.1944 | V67: =IFERROR(VALUE(U67),"") -> 38.1944 | W67: Réactif | X67: 3.5 | Y67: 1.5475 | AA67: Réactif | AB67: =IF(LEFT(AC67,1)=">","Censure haute",IF(AC67="*****","Non testé","Normal")) -> Normal | AC67: 282991 | AD67: 28.2991 | AE67: =IF(ISBLANK(AF67),"",IF(LEFT(AF67,1)=">","Censure haute",IF(AF67="*****","Non testé","Normal"))) | AG67: =IF(ISBLANK(AF67),"",IFERROR(VALUE(AF67),"")) | AH67: Réactif | AI67: 3.417 | AJ67: 0.9112 | AK67: 0.8884 | AL67: Négatif | AO67: =IF(ISBLANK(AM67),"",IF(AM67=92,IF(T67="Censure haute",120,""),IF(AB67="Censure haute",120,"")))
A68: US-216 | B68: Femme | D68: 16.2 | E68: Poids normal | F68: Non vacciné | I68: 12 | J68: S1 | K68: Négatif | L68: =IF(LEFT(M68,1)=">","Censure haute",IF(M68="*****","Non testé","Normal")) -> Censure haute | M68: >120 | N68: =IFERROR(VALUE(M68),"") | O68: Réactif | P68: 2.69 | Q68: 0.0635 | S68: Négatif | T68: =IF(LEFT(U68,1)=">","Censure haute",IF(U68="*****","Echec technique","Normal")) -> Echec technique | U68: ***** | V68: =IFERROR(VALUE(U68),"") | W68: Non testé | X68: 3.378 | Y68: 1.8251 | AA68: Réactif | AB68: =IF(LEFT(AC68,1)=">","Censure haute",IF(AC68="*****","Non testé","Normal")) -> Censure haute | AC68: >120 | AE68: =IF(ISBLANK(AF68),"",IF(LEFT(AF68,1)=">","Censure haute",IF(AF68="*****","Non testé","Normal"))) | AG68: =IF(ISBLANK(AF68),"",IFERROR(VALUE(AF68),"")) | AH68: Réactif | AI68: 3.017 | AJ68: 0.626 | AL68: Négatif | AM68: 210 | AN68: 0 | AO68: =IF(ISBLANK(AM68),"",IF(AM68=92,IF(T68="Censure haute",120,""),IF(AB68="Censure haute",120,""))) -> 120
A69: US-416 | B69: Femme | D69: 22.9 | E69: Poids normal | F69: Vacciné | G69: 44454 | H69: 44476 | I69: 15 | J69: S4 | K69: Négatif | L69: =IF(LEFT(M69,1)=">","Censure haute",IF(M69="*****","Non testé","Normal")) -> Non testé | M69: ***** | N69: =IFERROR(VALUE(M69),"") | O69: Non testé | P69: 2.779 | Q69: 0.1857 | S69: Négatif | T69: =IF(LEFT(U69,1)=">","Censure haute",IF(U69="*****","Echec technique","Normal")) -> Censure haute | U69: >120 | V69: =IFERROR(VALUE(U69),"") | W69: Réactif | X69: 3.493 | Y69: 1.6384 | AA69: Réactif | AB69: =IF(LEFT(AC69,1)=">","Censure haute",IF(AC69="*****","Non testé","Normal")) -> Censure haute | AC69: >120 | AE69: =IF(ISBLANK(AF69),"",IF(LEFT(AF69,1)=">","Censure haute",IF(AF69="*****","Non testé","Normal"))) | AG69: =IF(ISBLANK(AF69),"",IFERROR(VALUE(AF69),"")) | AH69: Réactif | AI69: 3.046 | AJ69: 0.9586 | AL69: Négatif | AM69: 210 | AN69: 0 | AO69: =IF(ISBLANK(AM69),"",IF(AM69=92,IF(T69="Censure haute",120,""),IF(AB69="Censure haute",120,""))) -> 120
A70: US-545 | B70: Femme | D70: 26.3 | E70: Obésité | F70: Vacciné | G70: 44453 | H70: 44476 | I70: 12 | J70: S1 | K70: Négatif | L70: =IF(LEFT(M70,1)=">","Censure haute",IF(M70="*****","Non testé","Normal")) -> Censure haute | M70: >120 | N70: =IFERROR(VALUE(M70),"") | O70: Réactif | P70: 2.939 | Q70: 1.4672 | S70: Réactif | T70: =IF(LEFT(U70,1)=">","Censure haute",IF(U70="*****","Echec technique","Normal")) -> Censure haute | U70: >120 | V70: =IFERROR(VALUE(U70),"") | W70: Réactif | X70: 2.971 | Y70: 6.7209 | AA70: Réactif | AB70: =IF(LEFT(AC70,1)=">","Censure haute",IF(AC70="*****","Non testé","Normal")) -> Censure haute | AC70: >120 | AE70: =IF(ISBLANK(AF70),"",IF(LEFT(AF70,1)=">","Censure haute",IF(AF70="*****","Non testé","Normal"))) | AG70: =IF(ISBLANK(AF70),"",IFERROR(VALUE(AF70),"")) | AH70: Réactif | AI70: 3.5 | AJ70: 3.904 | AL70: Réactif | AM70: 210 | AN70: 0 | AO70: =IF(ISBLANK(AM70),"",IF(AM70=92,IF(T70="Censure haute",120,""),IF(AB70="Censure haute",120,""))) -> 120
A71: US-211 | B71: Homme | C71: Non | D71: 23.7 | E71: Surpoids | F71: Vacciné | G71: 44453 | H71: 44477 | I71: 12 | J71: S1 | K71: Réactif | L71: =IF(LEFT(M71,1)=">","Censure haute",IF(M71="*****","Non testé","Normal")) -> Censure haute | M71: >120 | N71: =IFERROR(VALUE(M71),"") | O71: Réactif | P71: 2.96 | Q71: 0.114 | S71: Négatif | T71: =IF(LEFT(U71,1)=">","Censure haute",IF(U71="*****","Echec technique","Normal")) -> Echec technique | U71: ***** | V71: =IFERROR(VALUE(U71),"") | W71: Non testé | X71: 3.5 | Y71: 2.2197 | AA71: Réactif | AB71: =IF(LEFT(AC71,1)=">","Censure haute",IF(AC71="*****","Non testé","Normal")) -> Censure haute | AC71: >120 | AE71: =IF(ISBLANK(AF71),"",IF(LEFT(AF71,1)=">","Censure haute",IF(AF71="*****","Non testé","Normal"))) | AG71: =IF(ISBLANK(AF71),"",IFERROR(VALUE(AF71),"")) | AH71: Réactif | AI71: 3.5 | AJ71: 0.7872 | AL71: Négatif | AM71: 210 | AN71: 0 | AO71: =IF(ISBLANK(AM71),"",IF(AM71=92,IF(T71="Censure haute",120,""),IF(AB71="Censure haute",120,""))) -> 120
A72: US-212 | B72: Homme | C72: Oui | D72: 16.2 | E72: Poids normal | F72: Vacciné | G72: 44453 | H72: 44480 | I72: 12 | J72: S1 | K72: Négatif | L72: =IF(LEFT(M72,1)=">","Censure haute",IF(M72="*****","Non testé","Normal")) -> Censure haute | M72: >120 | N72: =IFERROR(VALUE(M72),"") | O72: Réactif | P72: 3.056 | Q72: 0.0863 | S72: Négatif | T72: =IF(LEFT(U72,1)=">","Censure haute",IF(U72="*****","Echec technique","Normal")) -> Censure haute | U72: >120 | V72: =IFERROR(VALUE(U72),"") | W72: Réactif | X72: 3.5 | Y72: 0.1457 | AA72: Négatif | AB72: =IF(LEFT(AC72,1)=">","Censure haute",IF(AC72="*****","Non testé","Normal")) -> Non testé | AC72: ***** | AE72: =IF(ISBLANK(AF72),"",IF(LEFT(AF72,1)=">","Censure haute",IF(AF72="*****","Non testé","Normal"))) | AG72: =IF(ISBLANK(AF72),"",IFERROR(VALUE(AF72),"")) | AH72: Non testé | AI72: 2.971 | AJ72: 1.4897 | AL72: Réactif | AM72: 210 | AN72: 0 | AO72: =IF(ISBLANK(AM72),"",IF(AM72=92,IF(T72="Censure haute",120,""),IF(AB72="Censure haute",120,"")))
A73: US-386 | B73: Femme | C73: Non | D73: 42.2 | E73: Obésité | F73: Non vacciné | I73: 15 | J73: S4 | K73: Négatif | L73: =IF(LEFT(M73,1)=">","Censure haute",IF(M73="*****","Non testé","Normal")) -> Normal | M73: 3.7178 | N73: =IFERROR(VALUE(M73),"") -> 3.7178 | O73: Négatif | P73: 3.059 | Q73: 0.7673 | S73: Négatif | T73: =IF(LEFT(U73,1)=">","Censure haute",IF(U73="*****","Echec technique","Normal")) -> Censure haute | U73: >120 | V73: =IFERROR(VALUE(U73),"") | W73: Réactif | X73: 2.352 | Y73: 0.3552 | AA73: Négatif | AB73: =IF(LEFT(AC73,1)=">","Censure haute",IF(AC73="*****","Non testé","Normal")) -> Censure haute | AC73: >120 | AE73: =IF(ISBLANK(AF73),"",IF(LEFT(AF73,1)=">","Censure haute",IF(AF73="*****","Non testé","Normal"))) | AG73: =IF(ISBLANK(AF73),"",IFERROR(VALUE(AF73),"")) | AH73: Réactif | AI73: 3.157 | AJ73: 5.8482 | AL73: Réactif | AM73: 210 | AN73: 0 | AO73: =IF(ISBLANK(AM73),"",IF(AM73=92,IF(T73="Censure haute",120,""),IF(AB73="Censure haute",120,""))) -> 120
A74: US-317 | B74: Femme | D74: 21.8 | E74: Poids normal | F74: Vacciné | G74: 44453 | H74: 44476 | I74: 14 | J74: S4 | K74: Négatif | L74: =IF(LEFT(M74,1)=">","Censure haute",IF(M74="*****","Non testé","Normal")) -> Censure haute | M74: >120 | N74: =IFERROR(VALUE(M74),"") | O74: Réactif | P74: 3.059 | Q74: 0.2886 | S74: Négatif | T74: =IF(LEFT(U74,1)=">","Censure haute",IF(U74="*****","Echec technique","Normal")) -> Censure haute | U74: >120 | V74: =IFERROR(VALUE(U74),"") | W74: Réactif | X74: 3.5 | Y74: 3.7188 | AA74: Réactif | AB74: =IF(LEFT(AC74,1)=">","Censure haute",IF(AC74="*****","Non testé","Normal")) -> Censure haute | AC74: >120 | AE74: =IF(ISBLANK(AF74),"",IF(LEFT(AF74,1)=">","Censure haute",IF(AF74="*****","Non testé","Normal"))) | AG74: =IF(ISBLANK(AF74),"",IFERROR(VALUE(AF74),"")) | AH74: Réactif | AI74: 3.411 | AJ74: 5.7098 | AL74: Réactif | AO74: =IF(ISBLANK(AM74),"",IF(AM74=92,IF(T74="Censure haute",120,""),IF(AB74="Censure haute",120,"")))
A75: US-187 | B75: Homme | D75: 19.2 | E75: Poids normal | F75: Vacciné | G75: 44453 | H75: 44482 | I75: 15 | J75: S4 | K75: Négatif | L75: =IF(LEFT(M75,1)=">","Censure haute",IF(M75="*****","Non testé","Normal")) -> Censure haute | M75: >120 | N75: =IFERROR(VALUE(M75),"") | O75: Réactif | P75: 3.059 | Q75: 0.0603 | S75: Négatif | T75: =IF(LEFT(U75,1)=">","Censure haute",IF(U75="*****","Echec technique","Normal")) -> Echec technique | U75: ***** | V75: =IFERROR(VALUE(U75),"") | W75: Non testé | X75: 3.5 | Y75: 1.4978 | AA75: Réactif | AB75: =IF(LEFT(AC75,1)=">","Censure haute",IF(AC75="*****","Non testé","Normal")) -> Non testé | AC75: ***** | AE75: =IF(ISBLANK(AF75),"",IF(LEFT(AF75,1)=">","Censure haute",IF(AF75="*****","Non testé","Normal"))) | AG75: =IF(ISBLANK(AF75),"",IFERROR(VALUE(AF75),"")) | AH75: Non testé | AI75: 3.5 | AJ75: 0.8864 | AL75: Négatif | AM75: 210 | AN75: 0 | AO75: =IF(ISBLANK(AM75),"",IF(AM75=92,IF(T75="Censure haute",120,""),IF(AB75="Censure haute",120,"")))
A76: US-248 | B76: Femme | D76: 24.8 | E76: Surpoids | F76: Vacciné | G76: 44453 | H76: 44477 | I76: 12 | J76: S1 | K76: Négatif | L76: =IF(LEFT(M76,1)=">","Censure haute",IF(M76="*****","Non testé","Normal")) -> Censure haute | M76: >120 | N76: =IFERROR(VALUE(M76),"") | O76: Réactif | P76: 3.087 | Q76: 0.0764 | S76: Négatif | T76: =IF(LEFT(U76,1)=">","Censure haute",IF(U76="*****","Echec technique","Normal")) -> Censure haute | U76: >120 | V76: =IFERROR(VALUE(U76),"") | W76: Réactif | X76: 3.253 | Y76: 0.0821 | AA76: Négatif | AB76: =IF(LEFT(AC76,1)=">","Censure haute",IF(AC76="*****","Non testé","Normal")) -> Censure haute | AC76: >120 | AE76: =IF(ISBLANK(AF76),"",IF(LEFT(AF76,1)=">","Censure haute",IF(AF76="*****","Non testé","Normal"))) | AG76: =IF(ISBLANK(AF76),"",IFERROR(VALUE(AF76),"")) | AH76: Réactif | AI76: 3.5 | AJ76: 1.4175 | AL76: Réactif | AM76: 210 | AN76: 0 | AO76: =IF(ISBLANK(AM76),"",IF(AM76=92,IF(T76="Censure haute",120,""),IF(AB76="Censure haute",120,""))) -> 120
A77: US-148 | B77: Homme | D77: 22 | E77: Surpoids | F77: Vacciné | G77: 44453 | H77: 44482 | I77: 12 | J77: S1 | K77: Négatif | L77: =IF(LEFT(M77,1)=">","Censure haute",IF(M77="*****","Non testé","Normal")) -> Censure haute | M77: >120 | N77: =IFERROR(VALUE(M77),"") | O77: Réactif | P77: 3.089 | Q77: 0.2606 | R77: 0.2541 | S77: Négatif | T77: =IF(LEFT(U77,1)=">","Censure haute",IF(U77="*****","Echec technique","Normal")) -> Censure haute | U77: >120 | V77: =IFERROR(VALUE(U77),"") | W77: Réactif | X77: 3.164 | Y77: 2.1325 | AA77: Réactif | AB77: =IF(LEFT(AC77,1)=">","Censure haute",IF(AC77="*****","Non testé","Normal")) -> Censure haute | AC77: >120 | AE77: =IF(ISBLANK(AF77),"",IF(LEFT(AF77,1)=">","Censure haute",IF(AF77="*****","Non testé","Normal"))) | AG77: =IF(ISBLANK(AF77),"",IFERROR(VALUE(AF77),"")) | AH77: Réactif | AI77: 2.677 | AJ77: 0.8422 | AL77: Négatif | AM77: 210 | AN77: 0 | AO77: =IF(ISBLANK(AM77),"",IF(AM77=92,IF(T77="Censure haute",120,""),IF(AB77="Censure haute",120,""))) -> 120
A78: US-449 | B78: Homme | C78: Non | D78: 23.6 | E78: Poids normal | F78: Vacciné | G78: 44454 | H78: 44476 | I78: 15 | J78: S4 | K78: Négatif | L78: =IF(LEFT(M78,1)=">","Censure haute",IF(M78="*****","Non testé","Normal")) -> Censure haute | M78: >120 | N78: =IFERROR(VALUE(M78),"") | O78: Réactif | P78: 3.089 | Q78: 0.093 | S78: Négatif | T78: =IF(LEFT(U78,1)=">","Censure haute",IF(U78="*****","Echec technique","Normal")) -> Censure haute | U78: >120 | V78: =IFERROR(VALUE(U78),"") | W78: Réactif | X78: 3.5 | Y78: 1.7388 | AA78: Réactif | AB78: =IF(LEFT(AC78,1)=">","Censure haute",IF(AC78="*****","Non testé","Normal")) -> Censure haute | AC78: >120 | AE78: =IF(ISBLANK(AF78),"",IF(LEFT(AF78,1)=">","Censure haute",IF(AF78="*****","Non testé","Normal"))) | AG78: =IF(ISBLANK(AF78),"",IFERROR(VALUE(AF78),"")) | AH78: Réactif | AI78: 3.322 | AJ78: 0.969 | AL78: Négatif | AM78: 210 | AN78: 0 | AO78: =IF(ISBLANK(AM78),"",IF(AM78=92,IF(T78="Censure haute",120,""),IF(AB78="Censure haute",120,""))) -> 120
A79: US-426 | B79: Femme | D79: 19.7 | E79: Poids normal | F79: Vacciné | G79: 44453 | H79: 44476 | I79: 14 | J79: S4 | K79: Négatif | L79: =IF(LEFT(M79,1)=">","Censure haute",IF(M79="*****","Non testé","Normal")) -> Censure haute | M79: >120 | N79: =IFERROR(VALUE(M79),"") | O79: Réactif | P79: 3.113 | Q79: 0.4832 | S79: Négatif | T79: =IF(LEFT(U79,1)=">","Censure haute",IF(U79="*****","Echec technique","Normal")) -> Censure haute | U79: >120 | V79: =IFERROR(VALUE(U79),"") | W79: Réactif | X79: 3.5 | Y79: 0.3147 | AA79: Négatif | AB79: =IF(LEFT(AC79,1)=">","Censure haute",IF(AC79="*****","Non testé","Normal")) -> Censure haute | AC79: >120 | AE79: =IF(ISBLANK(AF79),"",IF(LEFT(AF79,1)=">","Censure haute",IF(AF79="*****","Non testé","Normal"))) | AG79: =IF(ISBLANK(AF79),"",IFERROR(VALUE(AF79),"")) | AH79: Réactif | AI79: 3.006 | AJ79: 5.7569 | AL79: Réactif | AM79: 210 | AN79: 0 | AO79: =IF(ISBLANK(AM79),"",IF(AM79=92,IF(T79="Censure haute",120,""),IF(AB79="Censure haute",120,""))) -> 120
A80: US-470 | B80: Femme | C80: Non | D80: 13 | E80: Insuffisance pondérale | F80: Vacciné | G80: 44453 | H80: 44477 | I80: 11 | J80: S1 | K80: Réactif | L80: =IF(LEFT(M80,1)=">","Censure haute",IF(M80="*****","Non testé","Normal")) -> Censure haute | M80: >120 | N80: =IFERROR(VALUE(M80),"") | O80: Réactif | P80: 3.114 | Q80: 1.6923 | S80: Réactif | T80: =IF(LEFT(U80,1)=">","Censure haute",IF(U80="*****","Echec technique","Normal")) -> Censure haute | U80: >120 | V80: =IFERROR(VALUE(U80),"") | W80: Réactif | X80: 3.255 | Y80: 1.1943 | AA80: Réactif | AB80: =IF(LEFT(AC80,1)=">","Censure haute",IF(AC80="*****","Non testé","Normal")) -> Censure haute | AC80: >120 | AE80: =IF(ISBLANK(AF80),"",IF(LEFT(AF80,1)=">","Censure haute",IF(AF80="*****","Non testé","Normal"))) | AG80: =IF(ISBLANK(AF80),"",IFERROR(VALUE(AF80),"")) | AH80: Réactif | AI80: 3.238 | AJ80: 0.8053 | AL80: Négatif | AM80: 210 | AN80: 0 | AO80: =IF(ISBLANK(AM80),"",IF(AM80=92,IF(T80="Censure haute",120,""),IF(AB80="Censure haute",120,""))) -> 120
A81: US-404 | B81: Homme | C81: Oui | D81: 21.2 | E81: Poids normal | F81: Vacciné | G81: 44454 | H81: 44476 | I81: 15 | J81: S4 | K81: Négatif | L81: =IF(LEFT(M81,1)=">","Censure haute",IF(M81="*****","Non testé","Normal")) -> Censure haute | M81: >120 | N81: =IFERROR(VALUE(M81),"") | O81: Réactif | P81: 3.127 | Q81: 0.7047 | S81: Négatif | T81: =IF(LEFT(U81,1)=">","Censure haute",IF(U81="*****","Echec technique","Normal")) -> Censure haute | U81: >120 | V81: =IFERROR(VALUE(U81),"") | W81: Réactif | X81: 3.063 | Y81: 1.7098 | AA81: Réactif | AB81: =IF(LEFT(AC81,1)=">","Censure haute",IF(AC81="*****","Non testé","Normal")) -> Censure haute | AC81: >120 | AE81: =IF(ISBLANK(AF81),"",IF(LEFT(AF81,1)=">","Censure haute",IF(AF81="*****","Non testé","Normal"))) -> Censure haute | AF81: >120 | AG81: =IF(ISBLANK(AF81),"",IFERROR(VALUE(AF81),"")) | AH81: Réactif | AI81: 2.387 | AJ81: 1.0086 | AL81: Négatif | AM81: 210 | AN81: 0 | AO81: =IF(ISBLANK(AM81),"",IF(AM81=92,IF(T81="Censure haute",120,""),IF(AB81="Censure haute",120,""))) -> 120
A82: US-238 | B82: Femme | C82: Non | D82: 28.4 | E82: Obésité | F82: Vacciné | G82: 44453 | H82: 44477 | I82: 14 | J82: S4 | K82: Négatif | L82: =IF(LEFT(M82,1)=">","Censure haute",IF(M82="*****","Non testé","Normal")) -> Censure haute | M82: >120 | N82: =IFERROR(VALUE(M82),"") | O82: Réactif | P82: 3.14 | Q82: 0.1878 | S82: Négatif | T82: =IF(LEFT(U82,1)=">","Censure haute",IF(U82="*****","Echec technique","Normal")) -> Censure haute | U82: >120 | V82: =IFERROR(VALUE(U82),"") | W82: Réactif | X82: 3.242 | Y82: 0.1749 | AA82: Négatif | AB82: =IF(LEFT(AC82,1)=">","Censure haute",IF(AC82="*****","Non testé","Normal")) -> Non testé | AC82: ***** | AE82: =IF(ISBLANK(AF82),"",IF(LEFT(AF82,1)=">","Censure haute",IF(AF82="*****","Non testé","Normal"))) | AG82: =IF(ISBLANK(AF82),"",IFERROR(VALUE(AF82),"")) | AH82: Non testé | AI82: 3.099 | AJ82: 0.952 | AL82: Négatif | AM82: 210 | AN82: 0 | AO82: =IF(ISBLANK(AM82),"",IF(AM82=92,IF(T82="Censure haute",120,""),IF(AB82="Censure haute",120,"")))
A83: US-158 | B83: Homme | C83: Non | D83: 18.4 | E83: Poids normal | F83: Vacciné | G83: 44453 | H83: 44477 | I83: 12 | J83: S1 | K83: Réactif | L83: =IF(LEFT(M83,1)=">","Censure haute",IF(M83="*****","Non testé","Normal")) -> Censure haute | M83: >120 | N83: =IFERROR(VALUE(M83),"") | O83: Réactif | P83: 3.141 | Q83: 0.1759 | S83: Négatif | T83: =IF(LEFT(U83,1)=">","Censure haute",IF(U83="*****","Echec technique","Normal")) -> Echec technique | U83: ***** | V83: =IFERROR(VALUE(U83),"") | W83: Non testé | X83: 3.5 | Y83: 1.936 | AA83: Réactif | AB83: =IF(LEFT(AC83,1)=">","Censure haute",IF(AC83="*****","Non testé","Normal")) -> Censure haute | AC83: >120 | AE83: =IF(ISBLANK(AF83),"",IF(LEFT(AF83,1)=">","Censure haute",IF(AF83="*****","Non testé","Normal"))) | AG83: =IF(ISBLANK(AF83),"",IFERROR(VALUE(AF83),"")) | AH83: Réactif | AI83: 3.409 | AJ83: 1.1157 | AL83: Réactif | AO83: =IF(ISBLANK(AM83),"",IF(AM83=92,IF(T83="Censure haute",120,""),IF(AB83="Censure haute",120,"")))
A84: US-267 | B84: Femme | D84: 15.5 | E84: Poids normal | F84: Vacciné | G84: 44453 | H84: 44477 | I84: 12 | J84: S1 | K84: Négatif | L84: =IF(LEFT(M84,1)=">","Censure haute",IF(M84="*****","Non testé","Normal")) -> Non testé | M84: ***** | N84: =IFERROR(VALUE(M84),"") | O84: Non testé | P84: 3.146 | Q84: 0.2555 | S84: Négatif | T84: =IF(LEFT(U84,1)=">","Censure haute",IF(U84="*****","Echec technique","Normal")) -> Echec technique | U84: ***** | V84: =IFERROR(VALUE(U84),"") | W84: Non testé | X84: 3.5 | Y84: 5.4358 | AA84: Réactif | AB84: =IF(LEFT(AC84,1)=">","Censure haute",IF(AC84="*****","Non testé","Normal")) -> Censure haute | AC84: >120 | AE84: =IF(ISBLANK(AF84),"",IF(LEFT(AF84,1)=">","Censure haute",IF(AF84="*****","Non testé","Normal"))) | AG84: =IF(ISBLANK(AF84),"",IFERROR(VALUE(AF84),"")) | AH84: Réactif | AI84: 3.5 | AJ84: 1.904 | AL84: Réactif | AM84: 210 | AN84: 0 | AO84: =IF(ISBLANK(AM84),"",IF(AM84=92,IF(T84="Censure haute",120,""),IF(AB84="Censure haute",120,""))) -> 120
A85: US-481 | B85: Femme | C85: Non | D85: 15.7 | E85: Poids normal | F85: Vacciné | G85: 44453 | H85: 44477 | I85: 11 | J85: S1 | K85: Négatif | L85: =IF(LEFT(M85,1)=">","Censure haute",IF(M85="*****","Non testé","Normal")) -> Censure haute | M85: >120 | N85: =IFERROR(VALUE(M85),"") | O85: Réactif | P85: 3.157 | Q85: 2.759 | S85: Réactif | T85: =IF(LEFT(U85,1)=">","Censure haute",IF(U85="*****","Echec technique","Normal")) -> Censure haute | U85: >120 | V85: =IFERROR(VALUE(U85),"") | W85: Réactif | X85: 3.307 | Y85: 2.6413 | Z85: 2.5695 | AA85: Réactif | AB85: =IF(LEFT(AC85,1)=">","Censure haute",IF(AC85="*****","Non testé","Normal")) -> Non testé | AC85: ***** | AE85: =IF(ISBLANK(AF85),"",IF(LEFT(AF85,1)=">","Censure haute",IF(AF85="*****","Non testé","Normal"))) | AG85: =IF(ISBLANK(AF85),"",IFERROR(VALUE(AF85),"")) | AH85: Non testé | AI85: 3.09 | AJ85: 5.8595 | AL85: Réactif | AO85: =IF(ISBLANK(AM85),"",IF(AM85=92,IF(T85="Censure haute",120,""),IF(AB85="Censure haute",120,"")))
A86: US-205 | B86: Femme | D86: 31.4 | E86: Obésité | F86: Vacciné | G86: 44453 | H86: 44477 | I86: 12 | J86: S1 | K86: Réactif | L86: =IF(LEFT(M86,1)=">","Censure haute",IF(M86="*****","Non testé","Normal")) -> Censure haute | M86: >120 | N86: =IFERROR(VALUE(M86),"") | O86: Réactif | P86: 3.165 | Q86: 0.0456 | S86: Négatif | T86: =IF(LEFT(U86,1)=">","Censure haute",IF(U86="*****","Echec technique","Normal")) -> Censure haute | U86: >120 | V86: =IFERROR(VALUE(U86),"") | W86: Réactif | X86: 3.5 | Y86: 0.074 | AA86: Négatif | AB86: =IF(LEFT(AC86,1)=">","Censure haute",IF(AC86="*****","Non testé","Normal")) -> Censure haute | AC86: >120 | AE86: =IF(ISBLANK(AF86),"",IF(LEFT(AF86,1)=">","Censure haute",IF(AF86="*****","Non testé","Normal"))) | AG86: =IF(ISBLANK(AF86),"",IFERROR(VALUE(AF86),"")) | AH86: Réactif | AI86: 3.351 | AJ86: 0.2169 | AL86: Négatif | AM86: 210 | AN86: 0 | AO86: =IF(ISBLANK(AM86),"",IF(AM86=92,IF(T86="Censure haute",120,""),IF(AB86="Censure haute",120,""))) -> 120
A87: US-504 | B87: Femme | C87: Non | D87: 21.7 | E87: Poids normal | F87: Vacciné | G87: 44453 | H87: 44477 | I87: 12 | J87: S1 | K87: Réactif | L87: =IF(LEFT(M87,1)=">","Censure haute",IF(M87="*****","Non testé","Normal")) -> Censure haute | M87: >120 | N87: =IFERROR(VALUE(M87),"") | O87: Réactif | P87: 3.183 | Q87: 1.5546 | S87: Réactif | T87: =IF(LEFT(U87,1)=">","Censure haute",IF(U87="*****","Echec technique","Normal")) -> Censure haute | U87: >120 | V87: =IFERROR(VALUE(U87),"") | W87: Réactif | X87: 3.196 | Y87: 0.6457 | AA87: Négatif | AB87: =IF(LEFT(AC87,1)=">","Censure haute",IF(AC87="*****","Non testé","Normal")) -> Non testé | AC87: ***** | AE87: =IF(ISBLANK(AF87),"",IF(LEFT(AF87,1)=">","Censure haute",IF(AF87="*****","Non testé","Normal"))) | AG87: =IF(ISBLANK(AF87),"",IFERROR(VALUE(AF87),"")) | AH87: Non testé | AI87: 2.599 | AJ87: 4.7829 | AL87: Réactif | AM87: 210 | AN87: 0 | AO87: =IF(ISBLANK(AM87),"",IF(AM87=92,IF(T87="Censure haute",120,""),IF(AB87="Censure haute",120,"")))
A88: US-097 | B88: Femme | D88: 20.3 | E88: Poids normal | F88: Vacciné | G88: 44453 | H88: 44476 | I88: 15 | J88: S4 | K88: Réactif | L88: =IF(LEFT(M88,1)=">","Censure haute",IF(M88="*****","Non testé","Normal")) -> Censure haute | M88: >120 | N88: =IFERROR(VALUE(M88),"") | O88: Réactif | P88: 3.195 | Q88: 0.4637 | S88: Négatif | T88: =IF(LEFT(U88,1)=">","Censure haute",IF(U88="*****","Echec technique","Normal")) -> Normal | U88: 14.9096 | V88: =IFERROR(VALUE(U88),"") -> 14.9096 | W88: Réactif | X88: 3.5 | Y88: 2.5342 | AA88: Réactif | AB88: =IF(LEFT(AC88,1)=">","Censure haute",IF(AC88="*****","Non testé","Normal")) -> Normal | AC88: 80372 | AD88: 8.0372 | AE88: =IF(ISBLANK(AF88),"",IF(LEFT(AF88,1)=">","Censure haute",IF(AF88="*****","Non testé","Normal"))) | AG88: =IF(ISBLANK(AF88),"",IFERROR(VALUE(AF88),"")) | AH88: Incertain | AI88: 2.994 | AJ88: 0.918 | AL88: Négatif | AO88: =IF(ISBLANK(AM88),"",IF(AM88=92,IF(T88="Censure haute",120,""),IF(AB88="Censure haute",120,"")))
A89: US-459 | B89: Femme | C89: Non | D89: 15.1 | E89: Poids normal | F89: Vacciné | G89: 44453 | H89: 44477 | I89: 12 | J89: S1 | K89: Négatif | L89: =IF(LEFT(M89,1)=">","Censure haute",IF(M89="*****","Non testé","Normal")) -> Censure haute | M89: >120 | N89: =IFERROR(VALUE(M89),"") | O89: Réactif | P89: 3.205 | Q89: 1.1582 | S89: Réactif | T89: =IF(LEFT(U89,1)=">","Censure haute",IF(U89="*****","Echec technique","Normal")) -> Normal | U89: 84.8451 | V89: =IFERROR(VALUE(U89),"") -> 84.8451 | W89: Réactif | X89: 3.5 | Y89: 5.1192 | AA89: Réactif | AB89: =IF(LEFT(AC89,1)=">","Censure haute",IF(AC89="*****","Non testé","Normal")) -> Normal | AC89: 48724 | AD89: 4.8724 | AE89: =IF(ISBLANK(AF89),"",IF(LEFT(AF89,1)=">","Censure haute",IF(AF89="*****","Non testé","Normal"))) | AG89: =IF(ISBLANK(AF89),"",IFERROR(VALUE(AF89),"")) | AH89: Réactif | AI89: 3.031 | AJ89: 2.1414 | AL89: Réactif | AO89: =IF(ISBLANK(AM89),"",IF(AM89=92,IF(T89="Censure haute",120,""),IF(AB89="Censure haute",120,"")))
A90: US-127 | B90: Homme | C90: Non | D90: 20.5 | E90: Poids normal | F90: Vacciné | G90: 44453 | H90: 44476 | I90: 14 | J90: S4 | K90: Négatif | L90: =IF(LEFT(M90,1)=">","Censure haute",IF(M90="*****","Non testé","Normal")) -> Censure haute | M90: >120 | N90: =IFERROR(VALUE(M90),"") | O90: Réactif | P90: 3.217 | Q90: 0.6066 | S90: Négatif | T90: =IF(LEFT(U90,1)=">","Censure haute",IF(U90="*****","Echec technique","Normal")) -> Censure haute | U90: >120 | V90: =IFERROR(VALUE(U90),"") | W90: Réactif | X90: 3.128 | Y90: 0.3642 | AA90: Négatif | AB90: =IF(LEFT(AC90,1)=">","Censure haute",IF(AC90="*****","Non testé","Normal")) -> Censure haute | AC90: >120 | AE90: =IF(ISBLANK(AF90),"",IF(LEFT(AF90,1)=">","Censure haute",IF(AF90="*****","Non testé","Normal"))) | AG90: =IF(ISBLANK(AF90),"",IFERROR(VALUE(AF90),"")) | AH90: Réactif | AI90: 3.376 | AJ90: 4.709 | AL90: Réactif | AM90: 210 | AN90: 0 | AO90: =IF(ISBLANK(AM90),"",IF(AM90=92,IF(T90="Censure haute",120,""),IF(AB90="Censure haute",120,""))) -> 120
A91: US-075 | B91: Homme | D91: 25.6 | E91: Obésité | F91: Vacciné | G91: 44453 | H91: 44477 | I91: 12 | J91: S1 | K91: Négatif | L91: =IF(LEFT(M91,1)=">","Censure haute",IF(M91="*****","Non testé","Normal")) -> Censure haute | M91: >120 | N91: =IFERROR(VALUE(M91),"") | O91: Réactif | P91: 3.223 | Q91: 0.5407 | S91: Négatif | T91: =IF(LEFT(U91,1)=">","Censure haute",IF(U91="*****","Echec technique","Normal")) -> Normal | U91: 1.1277 | V91: =IFERROR(VALUE(U91),"") -> 1.1277 | W91: Négatif | X91: 3.118 | Y91: 0.1965 | AA91: Négatif | AB91: =IF(LEFT(AC91,1)=">","Censure haute",IF(AC91="*****","Non testé","Normal")) -> Normal | AC91: 376285 | AD91: 37.6285 | AE91: =IF(ISBLANK(AF91),"",IF(LEFT(AF91,1)=">","Censure haute",IF(AF91="*****","Non testé","Normal"))) | AG91: =IF(ISBLANK(AF91),"",IFERROR(VALUE(AF91),"")) | AH91: Réactif | AI91: 3.023 | AJ91: 3.3176 | AL91: Réactif | AO91: =IF(ISBLANK(AM91),"",IF(AM91=92,IF(T91="Censure haute",120,""),IF(AB91="Censure haute",120,"")))
A92: US-006 | B92: Femme | D92: 14.7 | E92: Insuffisance pondérale | F92: Vacciné | G92: 44466 | H92: 44487 | I92: 11 | J92: S1 | K92: Négatif | L92: =IF(LEFT(M92,1)=">","Censure haute",IF(M92="*****","Non testé","Normal")) -> Censure haute | M92: >120 | N92: =IFERROR(VALUE(M92),"") | O92: Réactif | P92: 3.265 | Q92: 1.033 | S92: Négatif | T92: =IF(LEFT(U92,1)=">","Censure haute",IF(U92="*****","Echec technique","Normal")) -> Censure haute | U92: >120 | V92: =IFERROR(VALUE(U92),"") | W92: Réactif | X92: 3.064 | Y92: 5.7061 | AA92: Réactif | AB92: =IF(LEFT(AC92,1)=">","Censure haute",IF(AC92="*****","Non testé","Normal")) -> Normal | AC92: 713687 | AD92: 71.3687 | AE92: =IF(ISBLANK(AF92),"",IF(LEFT(AF92,1)=">","Censure haute",IF(AF92="*****","Non testé","Normal"))) | AG92: =IF(ISBLANK(AF92),"",IFERROR(VALUE(AF92),"")) | AH92: Réactif | AI92: 3.5 | AJ92: 1.3155 | AL92: Réactif | AO92: =IF(ISBLANK(AM92),"",IF(AM92=92,IF(T92="Censure haute",120,""),IF(AB92="Censure haute",120,"")))
A93: US-575 | B93: Homme | D93: 23.7 | E93: Poids normal | F93: Vacciné | G93: 44454 | H93: 44476 | I93: 15 | J93: S4 | K93: Négatif | L93: =IF(LEFT(M93,1)=">","Censure haute",IF(M93="*****","Non testé","Normal")) -> Censure haute | M93: >120 | N93: =IFERROR(VALUE(M93),"") | O93: Réactif | P93: 3.31 | Q93: 1.5856 | S93: Réactif | T93: =IF(LEFT(U93,1)=">","Censure haute",IF(U93="*****","Echec technique","Normal")) -> Echec technique | U93: ***** | V93: =IFERROR(VALUE(U93),"") | W93: Non testé | X93: 3.335 | Y93: 5.6496 | AA93: Réactif | AB93: =IF(LEFT(AC93,1)=">","Censure haute",IF(AC93="*****","Non testé","Normal")) -> Censure haute | AC93: >120 | AE93: =IF(ISBLANK(AF93),"",IF(LEFT(AF93,1)=">","Censure haute",IF(AF93="*****","Non testé","Normal"))) | AG93: =IF(ISBLANK(AF93),"",IFERROR(VALUE(AF93),"")) | AH93: Réactif | AI93: 3.5 | AJ93: 1.4552 | AL93: Réactif | AM93: 210 | AN93: 0 | AO93: =IF(ISBLANK(AM93),"",IF(AM93=92,IF(T93="Censure haute",120,""),IF(AB93="Censure haute",120,""))) -> 120
A94: US-549 | B94: Homme | C94: Non | D94: 14.6 | E94: Insuffisance pondérale | F94: Vacciné | G94: 44453 | H94: 44476 | I94: 12 | J94: S1 | K94: Négatif | L94: =IF(LEFT(M94,1)=">","Censure haute",IF(M94="*****","Non testé","Normal")) -> Censure haute | M94: >120 | N94: =IFERROR(VALUE(M94),"") | O94: Réactif | P94: 3.355 | Q94: 1.302 | S94: Réactif | T94: =IF(LEFT(U94,1)=">","Censure haute",IF(U94="*****","Echec technique","Normal")) -> Censure haute | U94: >120 | V94: =IFERROR(VALUE(U94),"") | W94: Réactif | X94: 3.5 | Y94: 0.5714 | Z94: 0.558 | AA94: Négatif | AB94: =IF(LEFT(AC94,1)=">","Censure haute",IF(AC94="*****","Non testé","Normal")) -> Censure haute | AC94: >120 | AE94: =IF(ISBLANK(AF94),"",IF(LEFT(AF94,1)=">","Censure haute",IF(AF94="*****","Non testé","Normal"))) | AG94: =IF(ISBLANK(AF94),"",IFERROR(VALUE(AF94),"")) | AH94: Réactif | AI94: 3.026 | AJ94: 0.4241 | AL94: Négatif | AM94: 210 | AN94: 0 | AO94: =IF(ISBLANK(AM94),"",IF(AM94=92,IF(T94="Censure haute",120,""),IF(AB94="Censure haute",120,""))) -> 120
A95: US-215 | B95: Homme | C95: Oui | D95: 16.6 | E95: Poids normal | F95: Vacciné | G95: 44453 | H95: 44477 | I95: 12 | J95: S1 | K95: Réactif | L95: =IF(LEFT(M95,1)=">","Censure haute",IF(M95="*****","Non testé","Normal")) -> Censure haute | M95: >120 | N95: =IFERROR(VALUE(M95),"") | O95: Réactif | P95: 3.376 | Q95: 0.0831 | S95: Négatif | T95: =IF(LEFT(U95,1)=">","Censure haute",IF(U95="*****","Echec technique","Normal")) -> Normal | U95: 14.121 | V95: =IFERROR(VALUE(U95),"") -> 14.121 | W95: Réactif | X95: 3.154 | Y95: 3.1323 | AA95: Réactif | AB95: =IF(LEFT(AC95,1)=">","Censure haute",IF(AC95="*****","Non testé","Normal")) -> Normal | AC95: 113462 | AD95: 11.3462 | AE95: =IF(ISBLANK(AF95),"",IF(LEFT(AF95,1)=">","Censure haute",IF(AF95="*****","Non testé","Normal"))) | AG95: =IF(ISBLANK(AF95),"",IFERROR(VALUE(AF95),"")) | AH95: Réactif | AI95: 2.941 | AJ95: 1.0847 | AL95: Négatif | AO95: =IF(ISBLANK(AM95),"",IF(AM95=92,IF(T95="Censure haute",120,""),IF(AB95="Censure haute",120,"")))
A96: US-189 | B96: Homme | C96: Oui | D96: 20.3 | E96: Poids normal | F96: Vacciné | G96: 44453 | H96: 44476 | I96: 14 | J96: S4 | K96: Négatif | L96: =IF(LEFT(M96,1)=">","Censure haute",IF(M96="*****","Non testé","Normal")) -> Censure haute | M96: >120 | N96: =IFERROR(VALUE(M96),"") | O96: Réactif | P96: 3.398 | Q96: 0.1059 | S96: Négatif | T96: =IF(LEFT(U96,1)=">","Censure haute",IF(U96="*****","Echec technique","Normal")) -> Echec technique | U96: ***** | V96: =IFERROR(VALUE(U96),"") | W96: Non testé | X96: 3.081 | Y96: 2.9462 | AA96: Réactif | AB96: =IF(LEFT(AC96,1)=">","Censure haute",IF(AC96="*****","Non testé","Normal")) -> Censure haute | AC96: >120 | AE96: =IF(ISBLANK(AF96),"",IF(LEFT(AF96,1)=">","Censure haute",IF(AF96="*****","Non testé","Normal"))) | AG96: =IF(ISBLANK(AF96),"",IFERROR(VALUE(AF96),"")) | AH96: Réactif | AI96: 3.5 | AJ96: 0.8967 | AL96: Négatif | AM96: 210 | AN96: 0 | AO96: =IF(ISBLANK(AM96),"",IF(AM96=92,IF(T96="Censure haute",120,""),IF(AB96="Censure haute",120,""))) -> 120
A97: US-260 | B97: Femme | D97: 19.6 | E97: Poids normal | F97: Vacciné | G97: 44453 | H97: 44477 | I97: 12 | J97: S1 | K97: Négatif | L97: =IF(LEFT(M97,1)=">","Censure haute",IF(M97="*****","Non testé","Normal")) -> Censure haute | M97: >120 | N97: =IFERROR(VALUE(M97),"") | O97: Réactif | P97: 3.405 | Q97: 0.0808 | S97: Négatif | T97: =IF(LEFT(U97,1)=">","Censure haute",IF(U97="*****","Echec technique","Normal")) -> Censure haute | U97: >120 | V97: =IFERROR(VALUE(U97),"") | W97: Réactif | X97: 3.5 | Y97: 0.0884 | AA97: Négatif | AB97: =IF(LEFT(AC97,1)=">","Censure haute",IF(AC97="*****","Non testé","Normal")) -> Censure haute | AC97: >120 | AE97: =IF(ISBLANK(AF97),"",IF(LEFT(AF97,1)=">","Censure haute",IF(AF97="*****","Non testé","Normal"))) | AG97: =IF(ISBLANK(AF97),"",IFERROR(VALUE(AF97),"")) | AH97: Réactif | AI97: 3.5 | AJ97: 0.0731 | AL97: Négatif | AM97: 210 | AN97: 0 | AO97: =IF(ISBLANK(AM97),"",IF(AM97=92,IF(T97="Censure haute",120,""),IF(AB97="Censure haute",120,""))) -> 120
A98: US-285 | B98: Femme | D98: 29.1 | E98: Obésité | F98: Vacciné | G98: 44453 | H98: 44477 | I98: 15 | J98: S4 | K98: Négatif | L98: =IF(LEFT(M98,1)=">","Censure haute",IF(M98="*****","Non testé","Normal")) -> Censure haute | M98: >120 | N98: =IFERROR(VALUE(M98),"") | O98: Réactif | P98: 3.416 | Q98: 0.5839 | S98: Négatif | T98: =IF(LEFT(U98,1)=">","Censure haute",IF(U98="*****","Echec technique","Normal")) -> Censure haute | U98: >120 | V98: =IFERROR(VALUE(U98),"") | W98: Réactif | X98: 3.5 | Y98: 2.0737 | AA98: Réactif | AB98: =IF(LEFT(AC98,1)=">","Censure haute",IF(AC98="*****","Non testé","Normal")) -> Censure haute | AC98: >120 | AE98: =IF(ISBLANK(AF98),"",IF(LEFT(AF98,1)=">","Censure haute",IF(AF98="*****","Non testé","Normal"))) | AG98: =IF(ISBLANK(AF98),"",IFERROR(VALUE(AF98),"")) | AH98: Réactif | AI98: 3.5 | AJ98: 1.2923 | AL98: Réactif | AM98: 210 | AN98: 0 | AO98: =IF(ISBLANK(AM98),"",IF(AM98=92,IF(T98="Censure haute",120,""),IF(AB98="Censure haute",120,""))) -> 120
A99: US-138 | B99: Homme | C99: Oui | D99: 23.7 | E99: Surpoids | F99: Vacciné | G99: 44453 | H99: 44476 | I99: 15 | J99: S4 | K99: Négatif | L99: =IF(LEFT(M99,1)=">","Censure haute",IF(M99="*****","Non testé","Normal")) -> Censure haute | M99: >120 | N99: =IFERROR(VALUE(M99),"") | O99: Réactif | P99: 3.428 | Q99: 0.5495 | S99: Négatif | T99: =IF(LEFT(U99,1)=">","Censure haute",IF(U99="*****","Echec technique","Normal")) -> Censure haute | U99: >120 | V99: =IFERROR(VALUE(U99),"") | W99: Réactif | X99: 2.979 | Y99: 0.2384 | AA99: Négatif | AB99: =IF(LEFT(AC99,1)=">","Censure haute",IF(AC99="*****","Non testé","Normal")) -> Censure haute | AC99: >120 | AE99: =IF(ISBLANK(AF99),"",IF(LEFT(AF99,1)=">","Censure haute",IF(AF99="*****","Non testé","Normal"))) | AG99: =IF(ISBLANK(AF99),"",IFERROR(VALUE(AF99),"")) | AH99: Réactif | AI99: 3.5 | AJ99: 1.4795 | AL99: Réactif | AM99: 210 | AN99: 0 | AO99: =IF(ISBLANK(AM99),"",IF(AM99=92,IF(T99="Censure haute",120,""),IF(AB99="Censure haute",120,""))) -> 120
A100: US-195 | B100: Homme | C100: Oui | D100: 17.8 | E100: Poids normal | F100: Vacciné | G100: 44453 | H100: 44477 | I100: 12 | J100: S1 | K100: Négatif | L100: =IF(LEFT(M100,1)=">","Censure haute",IF(M100="*****","Non testé","Normal")) -> Censure haute | M100: >120 | N100: =IFERROR(VALUE(M100),"") | O100: Réactif | P100: 3.43 | Q100: 0.202 | S100: Négatif | T100: =IF(LEFT(U100,1)=">","Censure haute",IF(U100="*****","Echec technique","Normal")) -> Normal | U100: 18.1268 | V100: =IFERROR(VALUE(U100),"") -> 18.1268 | W100: Réactif | X100: 3.171 | Y100: 2.148 | AA100: Réactif | AB100: =IF(LEFT(AC100,1)=">","Censure haute",IF(AC100="*****","Non testé","Normal")) -> Censure haute | AC100: >120 | AE100: =IF(ISBLANK(AF100),"",IF(LEFT(AF100,1)=">","Censure haute",IF(AF100="*****","Non testé","Normal"))) | AG100: =IF(ISBLANK(AF100),"",IFERROR(VALUE(AF100),"")) | AH100: Réactif | AI100: 2.924 | AJ100: 5.9628 | AL100: Réactif | AO100: =IF(ISBLANK(AM100),"",IF(AM100=92,IF(T100="Censure haute",120,""),IF(AB100="Censure haute",120,"")))
...

Sheet Cleaned_data (Eng)
A1: Subject_ID | B1: Sex | C1: Birth_comorbidity | D1: BMI_value | E1: BMI_class | F1: Vaccination_status | G1: Dose_Date1 | H1: Dose_Date2 | I1: Age | J1: School_grade | K1: Prior_infection | L1: Antibody_titer_28d_status | M1: Antibody_titer_28d | N1: Antibody_titer_28d_value | O1: Qual_result_28d | P1: Optical_density_28d | Q1: Neutralization_capacity_28d_m1 | R1: Neutralization_capacity_28d_m2 | S1: Neutralization_result_28d | T1: Antibody_titer_3m_status | U1: Antibody_titer_3m | V1: Antibody_titer_3m_value | W1: Qual_result_3m | X1: Optical_density_3m | Y1: Neutralization_capacity_3m_m1 | Z1: Neutralization_capacity_3m_m2 | AA1: Neutralization_result_3m | AB1: Antibody_titer_7m_m1_status | AC1: Antibody_titer_7m_m1 | AD1: Antibody_titer_7m_m1_value | AE1: Antibody_titer_7m_m2_status | AF1: Antibody_titer_7m_m2 | AG1: Antibody_titer_7m_m2_value | AH1: Qual_result_7m | AI1: Optical_density_7m | AJ1: Neutralization_capacity_7m_m1 | AK1: Neutralization_capacity_7m_m2 | AL1: Neutralization_result_7m | AM1: Followup_time_days | AN1: Event_status | AO1: Truncated_titer_derived
A2: US-050 | B2: Female | D2: 22.8 | E2: Overweight | F2: Unvaccinated | I2: 12 | J2: S1 | K2: Negative | L2: =IF(LEFT(M2,1)=">","Upper censored",IF(M2="*****","Not tested","Normal")) -> Normal | M2: 0.1679 | N2: =IFERROR(VALUE(M2),"") -> 0.1679 | O2: Negative | P2: 0.031 | Q2: 0.7099 | S2: Negative | T2: =IF(LEFT(U2,1)=">","Upper censored",IF(U2="*****","Technical failure","Normal")) -> Upper censored | U2: >120 | V2: =IFERROR(VALUE(U2),"") | W2: Reactive | X2: 0.958 | Y2: 6.4746 | AA2: Reactive | AB2: =IF(LEFT(AC2,1)=">","Upper censored",IF(AC2="*****","Not tested","Normal")) -> Upper censored | AC2: >120 | AG2: =IF(ISBLANK(AF2),"",IFERROR(VALUE(AF2),"")) | AH2: Reactive | AI2: 0.589 | AJ2: 3.3545 | AL2: Reactive | AM2: 210 | AN2: 0 | AO2: =IF(ISBLANK(AM2),"",IF(AM2=92,IF(T2="Upper censored",120,""),IF(AB2="Upper censored",120,""))) -> 120
A3: US-509 | B3: Male | C3: No | D3: 17 | E3: Normal Weight | F3: Unvaccinated | I3: 12 | J3: S1 | K3: Negative | L3: =IF(LEFT(M3,1)=">","Upper censored",IF(M3="*****","Not tested","Normal")) -> Normal | M3: 0.3747 | N3: =IFERROR(VALUE(M3),"") -> 0.3747 | O3: Negative | P3: 0.035 | Q3: 1.6594 | S3: Reactive | T3: =IF(LEFT(U3,1)=">","Upper censored",IF(U3="*****","Technical failure","Normal")) -> Upper censored | U3: >120 | V3: =IFERROR(VALUE(U3),"") | W3: Reactive | X3: 0.482 | Y3: 6.2601 | AA3: Reactive | AB3: =IF(LEFT(AC3,1)=">","Upper censored",IF(AC3="*****","Not tested","Normal")) -> Upper censored | AC3: >120 | AE3: =IF(ISBLANK(AF3),"",IF(LEFT(AF3,1)=">","Upper censored",IF(AF3="*****","Not tested","Normal"))) | AG3: =IF(ISBLANK(AF3),"",IFERROR(VALUE(AF3),"")) | AH3: Reactive | AI3: 2.847 | AJ3: 2.3946 | AL3: Reactive | AM3: 210 | AN3: 0 | AO3: =IF(ISBLANK(AM3),"",IF(AM3=92,IF(T3="Upper censored",120,""),IF(AB3="Upper censored",120,""))) -> 120
A4: US-063 | B4: Female | C4: No | D4: 14.4 | E4: Underweight | F4: Unvaccinated | I4: 12 | J4: S1 | K4: Negative | L4: =IF(LEFT(M4,1)=">","Upper censored",IF(M4="*****","Not tested","Normal")) -> Normal | M4: 0.1022 | N4: =IFERROR(VALUE(M4),"") -> 0.1022 | O4: Negative | P4: 0.037 | Q4: 0.5253 | S4: Negative | T4: =IF(LEFT(U4,1)=">","Upper censored",IF(U4="*****","Technical failure","Normal")) -> Upper censored | U4: >120 | V4: =IFERROR(VALUE(U4),"") | W4: Reactive | X4: 0.857 | Y4: 0.2737 | AA4: Negative | AB4: =IF(LEFT(AC4,1)=">","Upper censored",IF(AC4="*****","Not tested","Normal")) -> Upper censored | AC4: >120 | AE4: =IF(ISBLANK(AF4),"",IF(LEFT(AF4,1)=">","Upper censored",IF(AF4="*****","Not tested","Normal"))) | AG4: =IF(ISBLANK(AF4),"",IFERROR(VALUE(AF4),"")) | AH4: Reactive | AI4: 0.499 | AJ4: 0.1885 | AL4: Negative | AM4: 210 | AN4: 0 | AO4: =IF(ISBLANK(AM4),"",IF(AM4=92,IF(T4="Upper censored",120,""),IF(AB4="Upper censored",120,""))) -> 120
A5: US-188 | B5: Male | D5: 21.4 | E5: Normal Weight | F5: Unvaccinated | I5: 15 | J5: S4 | K5: Negative | L5: =IF(LEFT(M5,1)=">","Upper censored",IF(M5="*****","Not tested","Normal")) -> Normal | M5: 0.2861 | N5: =IFERROR(VALUE(M5),"") -> 0.2861 | O5: Negative | P5: 0.038 | Q5: 0.298 | S5: Negative | T5: =IF(LEFT(U5,1)=">","Upper censored",IF(U5="*****","Technical failure","Normal")) -> Technical failure | U5: ***** | V5: =IFERROR(VALUE(U5),"") | W5: Not tested | X5: 0.737 | Y5: 2.0179 | AA5: Reactive | AB5: =IF(LEFT(AC5,1)=">","Upper censored",IF(AC5="*****","Not tested","Normal")) -> Upper censored | AC5: >120 | AE5: =IF(ISBLANK(AF5),"",IF(LEFT(AF5,1)=">","Upper censored",IF(AF5="*****","Not tested","Normal"))) | AG5: =IF(ISBLANK(AF5),"",IFERROR(VALUE(AF5),"")) | AH5: Reactive | AI5: 0.43 | AJ5: 0.6488 | AL5: Negative | AM5: 210 | AN5: 0 | AO5: =IF(ISBLANK(AM5),"",IF(AM5=92,IF(T5="Upper censored",120,""),IF(AB5="Upper censored",120,""))) -> 120
A6: US-286 | B6: Male | D6: 33.2 | E6: Obese | F6: Unvaccinated | I6: 15 | J6: S4 | K6: Negative | L6: =IF(LEFT(M6,1)=">","Upper censored",IF(M6="*****","Not tested","Normal")) -> Normal | M6: 0.3317 | N6: =IFERROR(VALUE(M6),"") -> 0.3317 | O6: Negative | P6: 0.038 | Q6: 0.528 | S6: Negative | T6: =IF(LEFT(U6,1)=">","Upper censored",IF(U6="*****","Technical failure","Normal")) -> Upper censored | U6: >120 | V6: =IFERROR(VALUE(U6),"") | W6: Reactive | X6: 3.392 | Y6: 0.3179 | AA6: Negative | AB6: =IF(LEFT(AC6,1)=">","Upper censored",IF(AC6="*****","Not tested","Normal")) -> Upper censored | AC6: >120 | AE6: =IF(ISBLANK(AF6),"",IF(LEFT(AF6,1)=">","Upper censored",IF(AF6="*****","Not tested","Normal"))) | AG6: =IF(ISBLANK(AF6),"",IFERROR(VALUE(AF6),"")) | AH6: Reactive | AI6: 3.2 | AJ6: 0.1482 | AL6: Negative | AM6: 210 | AN6: 0 | AO6: =IF(ISBLANK(AM6),"",IF(AM6=92,IF(T6="Upper censored",120,""),IF(AB6="Upper censored",120,""))) -> 120
A7: US-116 | B7: Female | C7: Yes | D7: 25.5 | E7: Overweight | F7: Unvaccinated | I7: 14 | J7: S4 | K7: Negative | L7: =IF(LEFT(M7,1)=">","Upper censored",IF(M7="*****","Not tested","Normal")) -> Normal | M7: 0.2117 | N7: =IFERROR(VALUE(M7),"") -> 0.2117 | O7: Negative | P7: 0.04 | Q7: 0.1868 | S7: Negative | T7: =IF(LEFT(U7,1)=">","Upper censored",IF(U7="*****","Technical failure","Normal")) -> Normal | U7: 0.2649 | V7: =IFERROR(VALUE(U7),"") -> 0.2649 | W7: Negative | X7: 0.05 | Y7: 0.083 | AA7: Negative | AB7: =IF(LEFT(AC7,1)=">","Upper censored",IF(AC7="*****","Not tested","Normal")) -> Normal | AC7: 0.0426 | AD7: 0.0426 | AE7: =IF(ISBLANK(AF7),"",IF(LEFT(AF7,1)=">","Upper censored",IF(AF7="*****","Not tested","Normal"))) | AG7: =IF(ISBLANK(AF7),"",IFERROR(VALUE(AF7),"")) | AH7: Negative | AI7: 0.031 | AJ7: 0.1496 | AL7: Negative | AO7: =IF(ISBLANK(AM7),"",IF(AM7=92,IF(T7="Upper censored",120,""),IF(AB7="Upper censored",120,"")))
A8: US-544 | B8: Female | C8: No | D8: 17.6 | E8: Normal Weight | F8: Unvaccinated | I8: 12 | J8: S1 | K8: Negative | L8: =IF(LEFT(M8,1)=">","Upper censored",IF(M8="*****","Not tested","Normal")) -> Normal | M8: 0.1797 | N8: =IFERROR(VALUE(M8),"") -> 0.1797 | O8: Negative | P8: 0.041 | Q8: 1.2327 | S8: Reactive | T8: =IF(LEFT(U8,1)=">","Upper censored",IF(U8="*****","Technical failure","Normal")) -> Upper censored | U8: >120 | V8: =IFERROR(VALUE(U8),"") | W8: Reactive | X8: 1.84 | Y8: 0.5941 | AA8: Negative | AB8: =IF(LEFT(AC8,1)=">","Upper censored",IF(AC8="*****","Not tested","Normal")) -> Upper censored | AC8: >120 | AE8: =IF(ISBLANK(AF8),"",IF(LEFT(AF8,1)=">","Upper censored",IF(AF8="*****","Not tested","Normal"))) | AG8: =IF(ISBLANK(AF8),"",IFERROR(VALUE(AF8),"")) | AH8: Reactive | AI8: 1.691 | AJ8: 6.0625 | AL8: Reactive | AM8: 210 | AN8: 0 | AO8: =IF(ISBLANK(AM8),"",IF(AM8=92,IF(T8="Upper censored",120,""),IF(AB8="Upper censored",120,""))) -> 120
A9: US-551 | B9: Male | D9: 22.1 | E9: Overweight | F9: Unvaccinated | I9: 12 | J9: S1 | K9: Negative | L9: =IF(LEFT(M9,1)=">","Upper censored",IF(M9="*****","Not tested","Normal")) -> Normal | M9: 0.2709 | N9: =IFERROR(VALUE(M9),"") -> 0.2709 | O9: Negative | P9: 0.045 | Q9: 1.1834 | S9: Reactive | T9: =IF(LEFT(U9,1)=">","Upper censored",IF(U9="*****","Technical failure","Normal")) -> Upper censored | U9: >120 | V9: =IFERROR(VALUE(U9),"") | W9: Reactive | X9: 0.321 | Y9: 6.1808 | AA9: Reactive | AB9: =IF(LEFT(AC9,1)=">","Upper censored",IF(AC9="*****","Not tested","Normal")) -> Not tested | AC9: ***** | AE9: =IF(ISBLANK(AF9),"",IF(LEFT(AF9,1)=">","Upper censored",IF(AF9="*****","Not tested","Normal"))) | AG9: =IF(ISBLANK(AF9),"",IFERROR(VALUE(AF9),"")) | AH9: Not tested | AI9: 2.068 | AJ9: 1.9138 | AK9: 1.8862 | AL9: Reactive | AM9: 210 | AN9: 0 | AO9: =IF(ISBLANK(AM9),"",IF(AM9=92,IF(T9="Upper censored",120,""),IF(AB9="Upper censored",120,"")))
A10: US-231 | B10: Male | C10: Yes | D10: 26.3 | E10: Overweight | F10: Vaccinated | G10: 44453 | H10: 44476 | I10: 15 | J10: S4 | K10: Reactive | L10: =IF(LEFT(M10,1)=">","Upper censored",IF(M10="*****","Not tested","Normal")) -> Normal | M10: 4.4375 | N10: =IFERROR(VALUE(M10),"") -> 4.4375 | O10: Negative | P10: 0.045 | Q10: 1.1459 | S10: Negative | T10: =IF(LEFT(U10,1)=">","Upper censored",IF(U10="*****","Technical failure","Normal")) -> Upper censored | U10: >120 | V10: =IFERROR(VALUE(U10),"") | W10: Reactive | X10: 3.329 | Y10: 4.2489 | AA10: Reactive | AB10: =IF(LEFT(AC10,1)=">","Upper censored",IF(AC10="*****","Not tested","Normal")) -> Not tested | AC10: ***** | AE10: =IF(ISBLANK(AF10),"",IF(LEFT(AF10,1)=">","Upper censored",IF(AF10="*****","Not tested","Normal"))) | AG10: =IF(ISBLANK(AF10),"",IFERROR(VALUE(AF10),"")) | AH10: Not tested | AI10: 2.835 | AJ10: 1.7662 | AK10: 1.643 | AL10: Reactive | AM10: 210 | AN10: 0 | AO10: =IF(ISBLANK(AM10),"",IF(AM10=92,IF(T10="Upper censored",120,""),IF(AB10="Upper censored",120,"")))
A11: US-547 | B11: Male | D11: 21.4 | E11: Overweight | F11: Unvaccinated | I11: 12 | J11: S1 | K11: Negative | L11: =IF(LEFT(M11,1)=">","Upper censored",IF(M11="*****","Not tested","Normal")) -> Normal | M11: 0.2937 | N11: =IFERROR(VALUE(M11),"") -> 0.2937 | O11: Negative | P11: 0.046 | Q11: 1.9888 | S11: Reactive | T11: =IF(LEFT(U11,1)=">","Upper censored",IF(U11="*****","Technical failure","Normal")) -> Technical failure | U11: ***** | V11: =IFERROR(VALUE(U11),"") | W11: Not tested | X11: 2.559 | Y11: 7.1226 | AA11: Reactive | AB11: =IF(LEFT(AC11,1)=">","Upper censored",IF(AC11="*****","Not tested","Normal")) -> Upper censored | AC11: >120 | AE11: =IF(ISBLANK(AF11),"",IF(LEFT(AF11,1)=">","Upper censored",IF(AF11="*****","Not tested","Normal"))) | AG11: =IF(ISBLANK(AF11),"",IFERROR(VALUE(AF11),"")) | AH11: Reactive | AI11: 1.132 | AJ11: 4.0134 | AL11: Reactive | AM11: 210 | AN11: 0 | AO11: =IF(ISBLANK(AM11),"",IF(AM11=92,IF(T11="Upper censored",120,""),IF(AB11="Upper censored",120,""))) -> 120
A12: US-530 | B12: Male | C12: No | D12: 20.1 | E12: Normal Weight | F12: Unvaccinated | I12: 15 | J12: S4 | K12: Negative | L12: =IF(LEFT(M12,1)=">","Upper censored",IF(M12="*****","Not tested","Normal")) -> Normal | M12: 0.665 | N12: =IFERROR(VALUE(M12),"") -> 0.665 | O12: Negative | P12: 0.048 | Q12: 1.1387 | S12: Reactive | T12: =IF(LEFT(U12,1)=">","Upper censored",IF(U12="*****","Technical failure","Normal")) -> Technical failure | U12: ***** | V12: =IFERROR(VALUE(U12),"") | W12: Not tested | X12: 0.033 | Y12: 0.9011 | AA12: Negative | AB12: =IF(LEFT(AC12,1)=">","Upper censored",IF(AC12="*****","Not tested","Normal")) -> Upper censored | AC12: >120 | AE12: =IF(ISBLANK(AF12),"",IF(LEFT(AF12,1)=">","Upper censored",IF(AF12="*****","Not tested","Normal"))) | AG12: =IF(ISBLANK(AF12),"",IFERROR(VALUE(AF12),"")) | AH12: Reactive | AI12: 1.945 | AJ12: 0.6033 | AL12: Negative | AM12: 210 | AN12: 0 | AO12: =IF(ISBLANK(AM12),"",IF(AM12=92,IF(T12="Upper censored",120,""),IF(AB12="Upper censored",120,""))) -> 120
A13: US-149 | B13: Male | C13: No | D13: 18.6 | E13: Normal Weight | F13: Unvaccinated | I13: 12 | J13: S1 | K13: Negative | L13: =IF(LEFT(M13,1)=">","Upper censored",IF(M13="*****","Not tested","Normal")) -> Normal | M13: 0.365 | N13: =IFERROR(VALUE(M13),"") -> 0.365 | O13: Negative | P13: 0.052 | Q13: 0.0831 | R13: 0.0814 | S13: Negative | T13: =IF(LEFT(U13,1)=">","Upper censored",IF(U13="*****","Technical failure","Normal")) -> Upper censored | U13: >120 | V13: =IFERROR(VALUE(U13),"") | W13: Reactive | X13: 3.376 | Y13: 0.1192 | AA13: Negative | AB13: =IF(LEFT(AC13,1)=">","Upper censored",IF(AC13="*****","Not tested","Normal")) -> Upper censored | AC13: >120 | AE13: =IF(ISBLANK(AF13),"",IF(LEFT(AF13,1)=">","Upper censored",IF(AF13="*****","Not tested","Normal"))) | AG13: =IF(ISBLANK(AF13),"",IFERROR(VALUE(AF13),"")) | AH13: Reactive | AI13: 2.346 | AJ13: 2.2869 | AL13: Reactive | AM13: 210 | AN13: 0 | AO13: =IF(ISBLANK(AM13),"",IF(AM13=92,IF(T13="Upper censored",120,""),IF(AB13="Upper censored",120,""))) -> 120
A14: US-433 | B14: Female | C14: Yes | D14: 30.8 | E14: Obese | F14: Unvaccinated | I14: 15 | J14: S4 | K14: Negative | L14: =IF(LEFT(M14,1)=">","Upper censored",IF(M14="*****","Not tested","Normal")) -> Normal | M14: 0.7767 | N14: =IFERROR(VALUE(M14),"") -> 0.7767 | O14: Negative | P14: 0.053 | Q14: 0.537 | S14: Negative | T14: =IF(LEFT(U14,1)=">","Upper censored",IF(U14="*****","Technical failure","Normal")) -> Upper censored | U14: >120 | V14: =IFERROR(VALUE(U14),"") | W14: Reactive | X14: 1.131 | Y14: 7.0446 | AA14: Negative | AB14: =IF(LEFT(AC14,1)=">","Upper censored",IF(AC14="*****","Not tested","Normal")) -> Upper censored | AC14: >120 | AE14: =IF(ISBLANK(AF14),"",IF(LEFT(AF14,1)=">","Upper censored",IF(AF14="*****","Not tested","Normal"))) | AG14: =IF(ISBLANK(AF14),"",IFERROR(VALUE(AF14),"")) | AH14: Reactive | AI14: 0.732 | AJ14: 1.6983 | AL14: Reactive | AM14: 210 | AN14: 0 | AO14: =IF(ISBLANK(AM14),"",IF(AM14=92,IF(T14="Upper censored",120,""),IF(AB14="Upper censored",120,""))) -> 120
A15: US-258 | B15: Male | C15: No | D15: 17.8 | E15: Normal Weight | F15: Unvaccinated | I15: 12 | J15: S1 | K15: Negative | L15: =IF(LEFT(M15,1)=">","Upper censored",IF(M15="*****","Not tested","Normal")) -> Normal | M15: 0.6755 | N15: =IFERROR(VALUE(M15),"") -> 0.6755 | O15: Negative | P15: 0.056 | Q15: 0.1332 | S15: Negative | T15: =IF(LEFT(U15,1)=">","Upper censored",IF(U15="*****","Technical failure","Normal")) -> Technical failure | U15: ***** | V15: =IFERROR(VALUE(U15),"") | W15: Not tested | X15: 0.905 | Y15: 2.6568 | AA15: Reactive | AB15: =IF(LEFT(AC15,1)=">","Upper censored",IF(AC15="*****","Not tested","Normal")) -> Not tested | AC15: ***** | AE15: =IF(ISBLANK(AF15),"",IF(LEFT(AF15,1)=">","Upper censored",IF(AF15="*****","Not tested","Normal"))) | AG15: =IF(ISBLANK(AF15),"",IFERROR(VALUE(AF15),"")) | AH15: Not tested | AI15: 3.5 | AJ15: 2.3841 | AL15: Reactive | AM15: 210 | AN15: 0 | AO15: =IF(ISBLANK(AM15),"",IF(AM15=92,IF(T15="Upper censored",120,""),IF(AB15="Upper censored",120,"")))
A16: US-124 | B16: Female | C16: No | D16: 16.8 | E16: Normal Weight | F16: Unvaccinated | I16: 15 | J16: S4 | K16: Negative | L16: =IF(LEFT(M16,1)=">","Upper censored",IF(M16="*****","Not tested","Normal")) -> Normal | M16: 0.3431 | N16: =IFERROR(VALUE(M16),"") -> 0.3431 | O16: Negative | P16: 0.057 | Q16: 0.3231 | S16: Negative | T16: =IF(LEFT(U16,1)=">","Upper censored",IF(U16="*****","Technical failure","Normal")) -> Upper censored | U16: >120 | V16: =IFERROR(VALUE(U16),"") | W16: Reactive | X16: 0.041 | Y16: 5.6358 | AA16: Reactive | AB16: =IF(LEFT(AC16,1)=">","Upper censored",IF(AC16="*****","Not tested","Normal")) -> Upper censored | AC16: >120 | AE16: =IF(ISBLANK(AF16),"",IF(LEFT(AF16,1)=">","Upper censored",IF(AF16="*****","Not tested","Normal"))) | AG16: =IF(ISBLANK(AF16),"",IFERROR(VALUE(AF16),"")) | AH16: Reactive | AI16: 0.036 | AJ16: 3.0553 | AL16: Reactive | AM16: 210 | AN16: 0 | AO16: =IF(ISBLANK(AM16),"",IF(AM16=92,IF(T16="Upper censored",120,""),IF(AB16="Upper censored",120,""))) -> 120
A17: US-429 | B17: Female | D17: 16.6 | E17: Normal Weight | F17: Unvaccinated | I17: 15 | J17: S4 | K17: Negative | L17: =IF(LEFT(M17,1)=">","Upper censored",IF(M17="*****","Not tested","Normal")) -> Normal | M17: 1 | N17: =IFERROR(VALUE(M17),"") -> 1 | O17: Negative | P17: 0.063 | Q17: 0.736 | S17: Negative | T17: =IF(LEFT(U17,1)=">","Upper censored",IF(U17="*****","Technical failure","Normal")) -> Upper censored | U17: >120 | V17: =IFERROR(VALUE(U17),"") | W17: Reactive | X17: 0.868 | Y17: 0.3661 | AA17: Negative | AB17: =IF(LEFT(AC17,1)=">","Upper censored",IF(AC17="*****","Not tested","Normal")) -> Upper censored | AC17: >120 | AE17: =IF(ISBLANK(AF17),"",IF(LEFT(AF17,1)=">","Upper censored",IF(AF17="*****","Not tested","Normal"))) | AG17: =IF(ISBLANK(AF17),"",IFERROR(VALUE(AF17),"")) | AH17: Reactive | AI17: 0.389 | AJ17: 3.9966 | AL17: Reactive | AM17: 210 | AN17: 0 | AO17: =IF(ISBLANK(AM17),"",IF(AM17=92,IF(T17="Upper censored",120,""),IF(AB17="Upper censored",120,""))) -> 120
A18: US-150 | B18: Female | C18: No | D18: 19.3 | E18: Normal Weight | F18: Unvaccinated | I18: 12 | J18: S1 | K18: Negative | L18: =IF(LEFT(M18,1)=">","Upper censored",IF(M18="*****","Not tested","Normal")) -> Normal | M18: 0.4307 | N18: =IFERROR(VALUE(M18),"") -> 0.4307 | O18: Negative | P18: 0.064 | Q18: 0.4397 | R18: 0.4511 | S18: Negative | T18: =IF(LEFT(U18,1)=">","Upper censored",IF(U18="*****","Technical failure","Normal")) -> Upper censored | U18: >120 | V18: =IFERROR(VALUE(U18),"") | W18: Reactive | X18: 0.128 | Y18: 0.3466 | AA18: Negative | AB18: =IF(LEFT(AC18,1)=">","Upper censored",IF(AC18="*****","Not tested","Normal")) -> Upper censored | AC18: >120 | AE18: =IF(ISBLANK(AF18),"",IF(LEFT(AF18,1)=">","Upper censored",IF(AF18="*****","Not tested","Normal"))) | AG18: =IF(ISBLANK(AF18),"",IFERROR(VALUE(AF18),"")) | AH18: Reactive | AI18: 0.146 | AJ18: 4.1619 | AL18: Reactive | AM18: 210 | AN18: 0 | AO18: =IF(ISBLANK(AM18),"",IF(AM18=92,IF(T18="Upper censored",120,""),IF(AB18="Upper censored",120,""))) -> 120
A19: US-493 | B19: Female | D19: 21.2 | E19: Normal Weight | F19: Unvaccinated | I19: 12 | J19: S1 | K19: Negative | L19: =IF(LEFT(M19,1)=">","Upper censored",IF(M19="*****","Not tested","Normal")) -> Normal | M19: 1.0447 | N19: =IFERROR(VALUE(M19),"") -> 1.0447 | O19: Negative | P19: 0.065 | Q19: 2.6629 | S19: Reactive | T19: =IF(LEFT(U19,1)=">","Upper censored",IF(U19="*****","Technical failure","Normal")) -> Upper censored | U19: >120 | V19: =IFERROR(VALUE(U19),"") | W19: Reactive | X19: 0.26 | Y19: 5.6682 | AA19: Reactive | AB19: =IF(LEFT(AC19,1)=">","Upper censored",IF(AC19="*****","Not tested","Normal")) -> Upper censored | AC19: >120 | AE19: =IF(ISBLANK(AF19),"",IF(LEFT(AF19,1)=">","Upper censored",IF(AF19="*****","Not tested","Normal"))) | AG19: =IF(ISBLANK(AF19),"",IFERROR(VALUE(AF19),"")) | AH19: Reactive | AI19: 0.196 | AJ19: 3.5558 | AL19: Reactive | AM19: 210 | AN19: 0 | AO19: =IF(ISBLANK(AM19),"",IF(AM19=92,IF(T19="Upper censored",120,""),IF(AB19="Upper censored",120,""))) -> 120
A20: US-255 | B20: Male | D20: 21.9 | E20: Overweight | F20: Unvaccinated | I20: 12 | J20: S1 | K20: Negative | L20: =IF(LEFT(M20,1)=">","Upper censored",IF(M20="*****","Not tested","Normal")) -> Normal | M20: 0.8702 | N20: =IFERROR(VALUE(M20),"") -> 0.8702 | O20: Negative | P20: 0.065 | Q20: 0.0699 | S20: Negative | T20: =IF(LEFT(U20,1)=">","Upper censored",IF(U20="*****","Technical failure","Normal")) -> Normal | U20: 17.0308 | V20: =IFERROR(VALUE(U20),"") -> 17.0308 | W20: Reactive | X20: 0.606 | Y20: 0.9958 | AA20: Negative | AB20: =IF(LEFT(AC20,1)=">","Upper censored",IF(AC20="*****","Not tested","Normal")) -> Not tested | AC20: ***** | AE20: =IF(ISBLANK(AF20),"",IF(LEFT(AF20,1)=">","Upper censored",IF(AF20="*****","Not tested","Normal"))) | AG20: =IF(ISBLANK(AF20),"",IFERROR(VALUE(AF20),"")) | AH20: Not tested | AI20: 0.506 | AJ20: 0.524 | AL20: Negative | AM20: 92 | AN20: 1 | AO20: =IF(ISBLANK(AM20),"",IF(AM20=92,IF(T20="Upper censored",120,""),IF(AB20="Upper censored",120,"")))
A21: US-134 | B21: Female | C21: No | D21: 25.9 | E21: Overweight | F21: Unvaccinated | I21: 15 | J21: S4 | K21: Reactive | L21: =IF(LEFT(M21,1)=">","Upper censored",IF(M21="*****","Not tested","Normal")) -> Normal | M21: 0.5182 | N21: =IFERROR(VALUE(M21),"") -> 0.5182 | O21: Negative | P21: 0.065 | Q21: 0.2593 | S21: Negative | T21: =IF(LEFT(U21,1)=">","Upper censored",IF(U21="*****","Technical failure","Normal")) -> Upper censored | U21: >120 | V21: =IFERROR(VALUE(U21),"") | W21: Reactive | X21: 0.384 | Y21: 0.1082 | AA21: Negative | AB21: =IF(LEFT(AC21,1)=">","Upper censored",IF(AC21="*****","Not tested","Normal")) -> Not tested | AC21: ***** | AE21: =IF(ISBLANK(AF21),"",IF(LEFT(AF21,1)=">","Upper censored",IF(AF21="*****","Not tested","Normal"))) | AG21: =IF(ISBLANK(AF21),"",IFERROR(VALUE(AF21),"")) | AH21: Not tested | AI21: 1.256 | AJ21: 3.0861 | AL21: Reactive | AM21: 210 | AN21: 0 | AO21: =IF(ISBLANK(AM21),"",IF(AM21=92,IF(T21="Upper censored",120,""),IF(AB21="Upper censored",120,"")))
A22: US-137 | B22: Female | D22: 17.1 | E22: Normal Weight | F22: Unvaccinated | I22: 14 | J22: S4 | K22: Negative | L22: =IF(LEFT(M22,1)=">","Upper censored",IF(M22="*****","Not tested","Normal")) -> Normal | M22: 0.6058 | N22: =IFERROR(VALUE(M22),"") -> 0.6058 | O22: Negative | P22: 0.067 | Q22: 0.3978 | S22: Negative | T22: =IF(LEFT(U22,1)=">","Upper censored",IF(U22="*****","Technical failure","Normal")) -> Upper censored | U22: >120 | V22: =IFERROR(VALUE(U22),"") | W22: Reactive | X22: 0.403 | Y22: 0.0861 | AA22: Negative | AB22: =IF(LEFT(AC22,1)=">","Upper censored",IF(AC22="*****","Not tested","Normal")) -> Not tested | AC22: ***** | AE22: =IF(ISBLANK(AF22),"",IF(LEFT(AF22,1)=">","Upper censored",IF(AF22="*****","Not tested","Normal"))) | AG22: =IF(ISBLANK(AF22),"",IFERROR(VALUE(AF22),"")) | AH22: Not tested | AI22: 0.479 | AJ22: 1.9324 | AL22: Reactive | AM22: 210 | AN22: 0 | AO22: =IF(ISBLANK(AM22),"",IF(AM22=92,IF(T22="Upper censored",120,""),IF(AB22="Upper censored",120,"")))
A23: US-229 | B23: Female | C23: No | D23: 34.2 | E23: Obese | F23: Unvaccinated | I23: 11 | J23: S1 | K23: Negative | L23: =IF(LEFT(M23,1)=">","Upper censored",IF(M23="*****","Not tested","Normal")) -> Normal | M23: 1.0216 | N23: =IFERROR(VALUE(M23),"") -> 1.0216 | O23: Negative | P23: 0.072 | Q23: 0.1416 | S23: Negative | T23: =IF(LEFT(U23,1)=">","Upper censored",IF(U23="*****","Technical failure","Normal")) -> Technical failure | U23: ***** | V23: =IFERROR(VALUE(U23),"") | W23: Not tested | X23: 0.745 | Y23: 1.7825 | AA23: Reactive | AB23: =IF(LEFT(AC23,1)=">","Upper censored",IF(AC23="*****","Not tested","Normal")) -> Not tested | AC23: ***** | AE23: =IF(ISBLANK(AF23),"",IF(LEFT(AF23,1)=">","Upper censored",IF(AF23="*****","Not tested","Normal"))) | AG23: =IF(ISBLANK(AF23),"",IFERROR(VALUE(AF23),"")) | AH23: Not tested | AI23: 2.678 | AJ23: 6.219 | AL23: Reactive | AM23: 210 | AN23: 0 | AO23: =IF(ISBLANK(AM23),"",IF(AM23=92,IF(T23="Upper censored",120,""),IF(AB23="Upper censored",120,"")))
A24: US-573 | B24: Female | C24: No | D24: 22.3 | E24: Overweight | F24: Unvaccinated | I24: 12 | J24: S1 | K24: Negative | L24: =IF(LEFT(M24,1)=">","Upper censored",IF(M24="*****","Not tested","Normal")) -> Normal | M24: 0.9089 | N24: =IFERROR(VALUE(M24),"") -> 0.9089 | O24: Negative | P24: 0.073 | Q24: 1.6025 | S24: Reactive | T24: =IF(LEFT(U24,1)=">","Upper censored",IF(U24="*****","Technical failure","Normal")) -> Upper censored | U24: >120 | V24: =IFERROR(VALUE(U24),"") | W24: Reactive | X24: 0.051 | Y24: 0.6138 | AA24: Negative | AB24: =IF(LEFT(AC24,1)=">","Upper censored",IF(AC24="*****","Not tested","Normal")) -> Upper censored | AC24: >120 | AE24: =IF(ISBLANK(AF24),"",IF(LEFT(AF24,1)=">","Upper censored",IF(AF24="*****","Not tested","Normal"))) | AG24: =IF(ISBLANK(AF24),"",IFERROR(VALUE(AF24),"")) | AH24: Reactive | AI24: 0.073 | AJ24: 0.25 | AL24: Negative | AM24: 210 | AN24: 0 | AO24: =IF(ISBLANK(AM24),"",IF(AM24=92,IF(T24="Upper censored",120,""),IF(AB24="Upper censored",120,""))) -> 120
A25: US-048 | B25: Male | C25: No | D25: 28.6 | E25: Obese | F25: Unvaccinated | I25: 15 | J25: S4 | K25: Negative | L25: =IF(LEFT(M25,1)=">","Upper censored",IF(M25="*****","Not tested","Normal")) -> Normal | M25: 1.1533 | N25: =IFERROR(VALUE(M25),"") -> 1.1533 | O25: Negative | P25: 0.074 | Q25: 0.4571 | S25: Negative | T25: =IF(LEFT(U25,1)=">","Upper censored",IF(U25="*****","Technical failure","Normal")) -> Technical failure | U25: ***** | V25: =IFERROR(VALUE(U25),"") | W25: Not tested | X25: 0.077 | Y25: 1.479 | AA25: Reactive | AB25: =IF(LEFT(AC25,1)=">","Upper censored",IF(AC25="*****","Not tested","Normal")) -> Not tested | AC25: ***** | AE25: =IF(ISBLANK(AF25),"",IF(LEFT(AF25,1)=">","Upper censored",IF(AF25="*****","Not tested","Normal"))) | AG25: =IF(ISBLANK(AF25),"",IFERROR(VALUE(AF25),"")) | AH25: Not tested | AI25: 1.246 | AJ25: 1.2029 | AL25: Reactive | AM25: 210 | AN25: 0 | AO25: =IF(ISBLANK(AM25),"",IF(AM25=92,IF(T25="Upper censored",120,""),IF(AB25="Upper censored",120,"")))
A26: US-066 | B26: Female | C26: No | D26: 17.2 | E26: Normal Weight | F26: Unvaccinated | I26: 12 | J26: S1 | K26: Negative | L26: =IF(LEFT(M26,1)=">","Upper censored",IF(M26="*****","Not tested","Normal")) -> Normal | M26: 1.1533 | N26: =IFERROR(VALUE(M26),"") -> 1.1533 | O26: Negative | P26: 0.089 | Q26: 0.2923 | S26: Negative | T26: =IF(LEFT(U26,1)=">","Upper censored",IF(U26="*****","Technical failure","Normal")) -> Technical failure | U26: ***** | V26: =IFERROR(VALUE(U26),"") | W26: Not tested | X26: 0.684 | Y26: 3.0044 | AA26: Reactive | AB26: =IF(LEFT(AC26,1)=">","Upper censored",IF(AC26="*****","Not tested","Normal")) -> Not tested | AC26: ***** | AE26: =IF(ISBLANK(AF26),"",IF(LEFT(AF26,1)=">","Upper censored",IF(AF26="*****","Not tested","Normal"))) | AG26: =IF(ISBLANK(AF26),"",IFERROR(VALUE(AF26),"")) | AH26: Not tested | AI26: 0.365 | AJ26: 1.3504 | AL26: Reactive | AM26: 210 | AN26: 0 | AO26: =IF(ISBLANK(AM26),"",IF(AM26=92,IF(T26="Upper censored",120,""),IF(AB26="Upper censored",120,"")))
A27: US-169 | B27: Female | C27: No | D27: 27.2 | E27: Overweight | F27: Unvaccinated | I27: 15 | J27: S4 | K27: Reactive | L27: =IF(LEFT(M27,1)=">","Upper censored",IF(M27="*****","Not tested","Normal")) -> Normal | M27: 1.3894 | N27: =IFERROR(VALUE(M27),"") -> 1.3894 | O27: Negative | P27: 0.089 | Q27: 0.0586 | S27: Negative | T27: =IF(LEFT(U27,1)=">","Upper censored",IF(U27="*****","Technical failure","Normal")) -> Upper censored | U27: >120 | V27: =IFERROR(VALUE(U27),"") | W27: Reactive | X27: 3.5 | Y27: 5.0045 | AA27: Reactive | AB27: =IF(LEFT(AC27,1)=">","Upper censored",IF(AC27="*****","Not tested","Normal")) -> Normal | AC27: 600531 | AD27: 60.0531 | AE27: =IF(ISBLANK(AF27),"",IF(LEFT(AF27,1)=">","Upper censored",IF(AF27="*****","Not tested","Normal"))) | AG27: =IF(ISBLANK(AF27),"",IFERROR(VALUE(AF27),"")) | AH27: Reactive | AI27: 2.813 | AJ27: 1.8802 | AL27: Reactive | AO27: =IF(ISBLANK(AM27),"",IF(AM27=92,IF(T27="Upper censored",120,""),IF(AB27="Upper censored",120,"")))
A28: US-512 | B28: Male | D28: 16.4 | E28: Normal Weight | F28: Unvaccinated | I28: 12 | J28: S1 | K28: Reactive | L28: =IF(LEFT(M28,1)=">","Upper censored",IF(M28="*****","Not tested","Normal")) -> Normal | M28: 1.8263 | N28: =IFERROR(VALUE(M28),"") -> 1.8263 | O28: Negative | P28: 0.1 | Q28: 3.059 | S28: Reactive | T28: =IF(LEFT(U28,1)=">","Upper censored",IF(U28="*****","Technical failure","Normal")) -> Normal | U28: 45.4201 | V28: =IFERROR(VALUE(U28),"") -> 45.4201 | W28: Reactive | X28: 0.207 | Y28: 1.6463 | AA28: Reactive | AB28: =IF(LEFT(AC28,1)=">","Upper censored",IF(AC28="*****","Not tested","Normal")) -> Normal | AC28: 979592 | AD28: 97.9592 | AE28: =IF(ISBLANK(AF28),"",IF(LEFT(AF28,1)=">","Upper censored",IF(AF28="*****","Not tested","Normal"))) | AG28: =IF(ISBLANK(AF28),"",IFERROR(VALUE(AF28),"")) | AH28: Reactive | AI28: 0.218 | AJ28: 5.7516 | AL28: Reactive | AO28: =IF(ISBLANK(AM28),"",IF(AM28=92,IF(T28="Upper censored",120,""),IF(AB28="Upper censored",120,"")))
A29: US-004 | B29: Male | C29: No | D29: 16.8 | E29: Normal Weight | F29: Unvaccinated | I29: 12 | J29: S1 | K29: Negative | L29: =IF(LEFT(M29,1)=">","Upper censored",IF(M29="*****","Not tested","Normal")) -> Normal | M29: 1.1752 | N29: =IFERROR(VALUE(M29),"") -> 1.1752 | O29: Negative | P29: 0.101 | Q29: 0.9143 | S29: Negative | T29: =IF(LEFT(U29,1)=">","Upper censored",IF(U29="*****","Technical failure","Normal")) -> Technical failure | U29: ***** | V29: =IFERROR(VALUE(U29),"") | W29: Not tested | X29: 1.45 | Y29: 0.5828 | AA29: Negative | AB29: =IF(LEFT(AC29,1)=">","Upper censored",IF(AC29="*****","Not tested","Normal")) -> Upper censored | AC29: >120 | AE29: =IF(ISBLANK(AF29),"",IF(LEFT(AF29,1)=">","Upper censored",IF(AF29="*****","Not tested","Normal"))) | AG29: =IF(ISBLANK(AF29),"",IFERROR(VALUE(AF29),"")) | AH29: Reactive | AI29: 0.972 | AJ29: 0.416 | AL29: Negative | AM29: 210 | AN29: 0 | AO29: =IF(ISBLANK(AM29),"",IF(AM29=92,IF(T29="Upper censored",120,""),IF(AB29="Upper censored",120,""))) -> 120
A30: US-042 | B30: Female | D30: 19.5 | E30: Normal Weight | F30: Unvaccinated | I30: 15 | J30: S4 | K30: Negative | L30: =IF(LEFT(M30,1)=">","Upper censored",IF(M30="*****","Not tested","Normal")) -> Normal | M30: 1.5474 | N30: =IFERROR(VALUE(M30),"") -> 1.5474 | O30: Negative | P30: 0.152 | Q30: 0.3495 | S30: Negative | T30: =IF(LEFT(U30,1)=">","Upper censored",IF(U30="*****","Technical failure","Normal")) -> Technical failure | U30: ***** | V30: =IFERROR(VALUE(U30),"") | W30: Not tested | X30: 0.114 | Y30: 2.0442 | AA30: Reactive | AB30: =IF(LEFT(AC30,1)=">","Upper censored",IF(AC30="*****","Not tested","Normal")) -> Not tested | AC30: ***** | AE30: =IF(ISBLANK(AF30),"",IF(LEFT(AF30,1)=">","Upper censored",IF(AF30="*****","Not tested","Normal"))) | AG30: =IF(ISBLANK(AF30),"",IFERROR(VALUE(AF30),"")) | AH30: Not tested | AI30: 0.142 | AJ30: 5.2398 | AL30: Reactive | AM30: 210 | AN30: 0 | AO30: =IF(ISBLANK(AM30),"",IF(AM30=92,IF(T30="Upper censored",120,""),IF(AB30="Upper censored",120,"")))
A31: US-100 | B31: Female | C31: Yes | D31: 37.7 | E31: Obese | F31: Unvaccinated | I31: 15 | J31: S4 | K31: Reactive | L31: =IF(LEFT(M31,1)=">","Upper censored",IF(M31="*****","Not tested","Normal")) -> Normal | M31: 3.6058 | N31: =IFERROR(VALUE(M31),"") -> 3.6058 | O31: Negative | P31: 0.2 | Q31: 0.4725 | S31: Negative | T31: =IF(LEFT(U31,1)=">","Upper censored",IF(U31="*****","Technical failure","Normal")) -> Upper censored | U31: >120 | V31: =IFERROR(VALUE(U31),"") | W31: Reactive | X31: 2.5 | Y31: 0.4194 | AA31: Negative | AB31: =IF(LEFT(AC31,1)=">","Upper censored",IF(AC31="*****","Not tested","Normal")) -> Not tested | AC31: ***** | AE31: =IF(ISBLANK(AF31),"",IF(LEFT(AF31,1)=">","Upper censored",IF(AF31="*****","Not tested","Normal"))) | AG31: =IF(ISBLANK(AF31),"",IFERROR(VALUE(AF31),"")) | AH31: Not tested | AI31: 1.843 | AJ31: 1.2684 | AL31: Reactive | AM31: 210 | AN31: 0 | AO31: =IF(ISBLANK(AM31),"",IF(AM31=92,IF(T31="Upper censored",120,""),IF(AB31="Upper censored",120,"")))
A32: US-484 | B32: Female | C32: Yes | D32: 20.5 | E32: Normal Weight | F32: Unvaccinated | I32: 12 | J32: S1 | K32: Negative | L32: =IF(LEFT(M32,1)=">","Upper censored",IF(M32="*****","Not tested","Normal")) -> Normal | M32: 4.1935 | N32: =IFERROR(VALUE(M32),"") -> 4.1935 | O32: Negative | P32: 0.206 | Q32: 1.3844 | S32: Reactive | T32: =IF(LEFT(U32,1)=">","Upper censored",IF(U32="*****","Technical failure","Normal")) -> Upper censored | U32: >120 | V32: =IFERROR(VALUE(U32),"") | W32: Reactive | X32: 0.068 | Y32: 1.2466 | AA32: Reactive | AB32: =IF(LEFT(AC32,1)=">","Upper censored",IF(AC32="*****","Not tested","Normal")) -> Upper censored | AC32: >120 | AE32: =IF(ISBLANK(AF32),"",IF(LEFT(AF32,1)=">","Upper censored",IF(AF32="*****","Not tested","Normal"))) | AG32: =IF(ISBLANK(AF32),"",IFERROR(VALUE(AF32),"")) | AH32: Reactive | AI32: 0.067 | AJ32: 5.7789 | AL32: Reactive | AM32: 210 | AN32: 0 | AO32: =IF(ISBLANK(AM32),"",IF(AM32=92,IF(T32="Upper censored",120,""),IF(AB32="Upper censored",120,""))) -> 120
A33: US-453 | B33: Female | C33: No | D33: 18.8 | E33: Normal Weight | F33: Unvaccinated | I33: 14 | J33: S4 | K33: Negative | L33: =IF(LEFT(M33,1)=">","Upper censored",IF(M33="*****","Not tested","Normal")) -> Normal | M33: 4.7742 | N33: =IFERROR(VALUE(M33),"") -> 4.7742 | O33: Negative | P33: 0.232 | Q33: 1.8154 | S33: Reactive | T33: =IF(LEFT(U33,1)=">","Upper censored",IF(U33="*****","Technical failure","Normal")) -> Normal | U33: 48.7591 | V33: =IFERROR(VALUE(U33),"") -> 48.7591 | W33: Reactive | X33: 3.421 | Y33: 1.5938 | AA33: Reactive | AB33: =IF(LEFT(AC33,1)=">","Upper censored",IF(AC33="*****","Not tested","Normal")) -> Normal | AC33: 378616 | AD33: 37.8616 | AE33: =IF(ISBLANK(AF33),"",IF(LEFT(AF33,1)=">","Upper censored",IF(AF33="*****","Not tested","Normal"))) | AG33: =IF(ISBLANK(AF33),"",IFERROR(VALUE(AF33),"")) | AH33: Reactive | AI33: 3.397 | AJ33: 0.8293 | AL33: Negative | AO33: =IF(ISBLANK(AM33),"",IF(AM33=92,IF(T33="Upper censored",120,""),IF(AB33="Upper censored",120,"")))
A34: US-082 | B34: Male | C34: No | D34: 18.4 | E34: Normal Weight | F34: Unvaccinated | I34: 15 | J34: S4 | K34: Negative | L34: =IF(LEFT(M34,1)=">","Upper censored",IF(M34="*****","Not tested","Normal")) -> Normal | M34: 6.0146 | N34: =IFERROR(VALUE(M34),"") -> 6.0146 | O34: Negative | P34: 0.292 | Q34: 0.2923 | S34: Negative | T34: =IF(LEFT(U34,1)=">","Upper censored",IF(U34="*****","Technical failure","Normal")) -> Normal | U34: 22.6736 | V34: =IFERROR(VALUE(U34),"") -> 22.6736 | W34: Reactive | X34: 0.382 | Y34: 2.8168 | AA34: Reactive | AB34: =IF(LEFT(AC34,1)=">","Upper censored",IF(AC34="*****","Not tested","Normal")) -> Normal | AC34: 140227 | AD34: 14.0227 | AE34: =IF(ISBLANK(AF34),"",IF(LEFT(AF34,1)=">","Upper censored",IF(AF34="*****","Not tested","Normal"))) | AG34: =IF(ISBLANK(AF34),"",IFERROR(VALUE(AF34),"")) | AH34: Reactive | AI34: 1.631 | AJ34: 1.1209 | AL34: Reactive | AO34: =IF(ISBLANK(AM34),"",IF(AM34=92,IF(T34="Upper censored",120,""),IF(AB34="Upper censored",120,"")))
A35: US-543 | B35: Female | C35: No | D35: 17.2 | E35: Normal Weight | F35: Unvaccinated | I35: 12 | J35: S1 | K35: Negative | L35: =IF(LEFT(M35,1)=">","Upper censored",IF(M35="*****","Not tested","Normal")) -> Normal | M35: 7.0608 | N35: =IFERROR(VALUE(M35),"") -> 7.0608 | O35: Negative | P35: 0.343 | Q35: 3.0045 | S35: Reactive | T35: =IF(LEFT(U35,1)=">","Upper censored",IF(U35="*****","Technical failure","Normal")) -> Technical failure | U35: ***** | V35: =IFERROR(VALUE(U35),"") | W35: Not tested | X35: 0.256 | Y35: 1.8034 | AA35: Reactive | AB35: =IF(LEFT(AC35,1)=">","Upper censored",IF(AC35="*****","Not tested","Normal")) -> Not tested | AC35: ***** | AE35: =IF(ISBLANK(AF35),"",IF(LEFT(AF35,1)=">","Upper censored",IF(AF35="*****","Not tested","Normal"))) | AG35: =IF(ISBLANK(AF35),"",IFERROR(VALUE(AF35),"")) | AH35: Not tested | AI35: 2.683 | AJ35: 6.846 | AL35: Reactive | AM35: 210 | AN35: 0 | AO35: =IF(ISBLANK(AM35),"",IF(AM35=92,IF(T35="Upper censored",120,""),IF(AB35="Upper censored",120,"")))
A36: US-118 | B36: Female | C36: Yes | D36: 18.1 | E36: Normal Weight | F36: Unvaccinated | I36: 15 | J36: S4 | K36: Reactive | L36: =IF(LEFT(M36,1)=">","Upper censored",IF(M36="*****","Not tested","Normal")) -> Normal | M36: 7.7226 | N36: =IFERROR(VALUE(M36),"") -> 7.7226 | O36: Negative | P36: 0.36 | Q36: 0.6769 | S36: Negative | T36: =IF(LEFT(U36,1)=">","Upper censored",IF(U36="*****","Technical failure","Normal")) -> Normal | U36: 7.5745 | V36: =IFERROR(VALUE(U36),"") -> 7.5745 | W36: Negative | X36: 0.38 | Y36: 0.4415 | AA36: Negative | AB36: =IF(LEFT(AC36,1)=">","Upper censored",IF(AC36="*****","Not tested","Normal")) -> Upper censored | AC36: >120 | AE36: =IF(ISBLANK(AF36),"",IF(LEFT(AF36,1)=">","Upper censored",IF(AF36="*****","Not tested","Normal"))) | AG36: =IF(ISBLANK(AF36),"",IFERROR(VALUE(AF36),"")) | AH36: Reactive | AI36: 3.023 | AJ36: 6.5984 | AL36: Reactive | AO36: =IF(ISBLANK(AM36),"",IF(AM36=92,IF(T36="Upper censored",120,""),IF(AB36="Upper censored",120,"")))
A37: US-526 | B37: Male | D37: 21.7 | E37: Normal Weight | F37: Unvaccinated | I37: 15 | J37: S4 | K37: Reactive | L37: =IF(LEFT(M37,1)=">","Upper censored",IF(M37="*****","Not tested","Normal")) -> Normal | M37: 8.9727 | N37: =IFERROR(VALUE(M37),"") -> 8.9727 | O37: Uncertain | P37: 0.42 | Q37: 1.2052 | S37: Reactive | T37: =IF(LEFT(U37,1)=">","Upper censored",IF(U37="*****","Technical failure","Normal")) -> Upper censored | U37: >120 | V37: =IFERROR(VALUE(U37),"") | W37: Reactive | X37: 2.78 | Y37: 5.0761 | AA37: Reactive | AB37: =IF(LEFT(AC37,1)=">","Upper censored",IF(AC37="*****","Not tested","Normal")) -> Upper censored | AC37: >120 | AE37: =IF(ISBLANK(AF37),"",IF(LEFT(AF37,1)=">","Upper censored",IF(AF37="*****","Not tested","Normal"))) | AG37: =IF(ISBLANK(AF37),"",IFERROR(VALUE(AF37),"")) | AH37: Reactive | AI37: 1.221 | AJ37: 2.4363 | AL37: Reactive | AM37: 210 | AN37: 0 | AO37: =IF(ISBLANK(AM37),"",IF(AM37=92,IF(T37="Upper censored",120,""),IF(AB37="Upper censored",120,""))) -> 120
A38: US-440 | B38: Female | C38: No | D38: 18 | E38: Normal Weight | F38: Unvaccinated | I38: 15 | J38: S4 | K38: Reactive | L38: =IF(LEFT(M38,1)=">","Upper censored",IF(M38="*****","Not tested","Normal")) -> Normal | M38: 9.5533 | N38: =IFERROR(VALUE(M38),"") -> 9.5533 | O38: Uncertain | P38: 0.446 | Q38: 0.0909 | S38: Negative | T38: =IF(LEFT(U38,1)=">","Upper censored",IF(U38="*****","Technical failure","Normal")) -> Upper censored | U38: >120 | V38: =IFERROR(VALUE(U38),"") | W38: Reactive | X38: 0.251 | Y38: 1.308 | AA38: Negative | AB38: =IF(LEFT(AC38,1)=">","Upper censored",IF(AC38="*****","Not tested","Normal")) -> Normal | AC38: 345493 | AD38: 34.5493 | AE38: =IF(ISBLANK(AF38),"",IF(LEFT(AF38,1)=">","Upper censored",IF(AF38="*****","Not tested","Normal"))) | AG38: =IF(ISBLANK(AF38),"",IFERROR(VALUE(AF38),"")) | AH38: Reactive | AI38: 1.774 | AJ38: 0.7414 | AL38: Negative | AO38: =IF(ISBLANK(AM38),"",IF(AM38=92,IF(T38="Upper censored",120,""),IF(AB38="Upper censored",120,"")))
A39: US-024 | B39: Male | C39: No | D39: 19.8 | E39: Normal Weight | F39: Unvaccinated | I39: 12 | J39: S1 | K39: Negative | L39: =IF(LEFT(M39,1)=">","Upper censored",IF(M39="*****","Not tested","Normal")) -> Normal | M39: 9.9124 | N39: =IFERROR(VALUE(M39),"") -> 9.9124 | O39: Uncertain | P39: 0.47 | Q39: 0.8635 | R39: 0.7942 | S39: Negative | T39: =IF(LEFT(U39,1)=">","Upper censored",IF(U39="*****","Technical failure","Normal")) -> Upper censored | U39: >120 | V39: =IFERROR(VALUE(U39),"") | W39: Reactive | X39: 2.322 | Y39: 2.8295 | AA39: Reactive | AB39: =IF(LEFT(AC39,1)=">","Upper censored",IF(AC39="*****","Not tested","Normal")) -> Upper censored | AC39: >120 | AE39: =IF(ISBLANK(AF39),"",IF(LEFT(AF39,1)=">","Upper censored",IF(AF39="*****","Not tested","Normal"))) | AG39: =IF(ISBLANK(AF39),"",IFERROR(VALUE(AF39),"")) | AH39: Reactive | AI39: 1.453 | AJ39: 0.5678 | AL39: Negative | AM39: 210 | AN39: 0 | AO39: =IF(ISBLANK(AM39),"",IF(AM39=92,IF(T39="Upper censored",120,""),IF(AB39="Upper censored",120,""))) -> 120
A40: US-101 | B40: Male | C40: No | D40: 21.5 | E40: Normal Weight | F40: Unvaccinated | I40: 14 | J40: S4 | K40: Reactive | L40: =IF(LEFT(M40,1)=">","Upper censored",IF(M40="*****","Not tested","Normal")) -> Normal | M40: 9.6496 | N40: =IFERROR(VALUE(M40),"") -> 9.6496 | O40: Uncertain | P40: 0.486 | Q40: 0.3275 | S40: Negative | T40: =IF(LEFT(U40,1)=">","Upper censored",IF(U40="*****","Technical failure","Normal")) -> Upper censored | U40: >120 | V40: =IFERROR(VALUE(U40),"") | W40: Reactive | X40: 3.374 | Y40: 0.1649 | AA40: Negative | AB40: =IF(LEFT(AC40,1)=">","Upper censored",IF(AC40="*****","Not tested","Normal")) -> Not tested | AC40: ***** | AE40: =IF(ISBLANK(AF40),"",IF(LEFT(AF40,1)=">","Upper censored",IF(AF40="*****","Not tested","Normal"))) | AG40: =IF(ISBLANK(AF40),"",IFERROR(VALUE(AF40),"")) | AH40: Not tested | AI40: 1.898 | AJ40: 1.334 | AL40: Reactive | AM40: 210 | AN40: 0 | AO40: =IF(ISBLANK(AM40),"",IF(AM40=92,IF(T40="Upper censored",120,""),IF(AB40="Upper censored",120,"")))
A41: US-223 | B41: Female | C41: No | D41: 20.7 | E41: Normal Weight | F41: Unvaccinated | I41: 12 | J41: S1 | K41: Negative | L41: =IF(LEFT(M41,1)=">","Upper censored",IF(M41="*****","Not tested","Normal")) -> Normal | M41: 10.7494 | N41: =IFERROR(VALUE(M41),"") -> 10.7494 | O41: Uncertain | P41: 0.516 | Q41: 0.1142 | R41: 0.1797 | S41: Negative | T41: =IF(LEFT(U41,1)=">","Upper censored",IF(U41="*****","Technical failure","Normal")) -> Upper censored | U41: >120 | V41: =IFERROR(VALUE(U41),"") | W41: Reactive | X41: 2.828 | Y41: 0.1256 | AA41: Negative | AB41: =IF(LEFT(AC41,1)=">","Upper censored",IF(AC41="*****","Not tested","Normal")) -> Normal | AC41: 1071762 | AD41: 107.1762 | AE41: =IF(ISBLANK(AF41),"",IF(LEFT(AF41,1)=">","Upper censored",IF(AF41="*****","Not tested","Normal"))) | AG41: =IF(ISBLANK(AF41),"",IFERROR(VALUE(AF41),"")) | AH41: Reactive | AI41: 1.705 | AJ41: 0.093 | AL41: Negative | AM41: 182 | AN41: 1 | AO41: =IF(ISBLANK(AM41),"",IF(AM41=92,IF(T41="Upper censored",120,""),IF(AB41="Upper censored",120,"")))
A42: US-287 | B42: Female | D42: 22.2 | E42: Overweight | F42: Unvaccinated | I42: 12 | J42: S1 | K42: Negative | L42: =IF(LEFT(M42,1)=">","Upper censored",IF(M42="*****","Not tested","Normal")) -> Normal | M42: 0.7104 | N42: =IFERROR(VALUE(M42),"") -> 0.7104 | O42: Negative | P42: 0.55 | Q42: 0.7293 | S42: Negative | T42: =IF(LEFT(U42,1)=">","Upper censored",IF(U42="*****","Technical failure","Normal")) -> Upper censored | U42: >120 | V42: =IFERROR(VALUE(U42),"") | W42: Reactive | X42: 0.053 | Y42: 0.4442 | AA42: Negative | AB42: =IF(LEFT(AC42,1)=">","Upper censored",IF(AC42="*****","Not tested","Normal")) -> Upper censored | AC42: >120 | AE42: =IF(ISBLANK(AF42),"",IF(LEFT(AF42,1)=">","Upper censored",IF(AF42="*****","Not tested","Normal"))) | AG42: =IF(ISBLANK(AF42),"",IFERROR(VALUE(AF42),"")) | AH42: Reactive | AI42: 0.044 | AJ42: 0.2276 | AL42: Negative | AM42: 210 | AN42: 0 | AO42: =IF(ISBLANK(AM42),"",IF(AM42=92,IF(T42="Upper censored",120,""),IF(AB42="Upper censored",120,""))) -> 120
A43: US-019 | B43: Female | C43: Yes | D43: 18.8 | E43: Normal Weight | F43: Unvaccinated | I43: 12 | J43: S1 | K43: Negative | L43: =IF(LEFT(M43,1)=">","Upper censored",IF(M43="*****","Not tested","Normal")) -> Normal | M43: 13.4584 | N43: =IFERROR(VALUE(M43),"") -> 13.4584 | O43: Reactive | P43: 0.576 | Q43: 1.0515 | S43: Negative | T43: =IF(LEFT(U43,1)=">","Upper censored",IF(U43="*****","Technical failure","Normal")) -> Upper censored | U43: >120 | V43: =IFERROR(VALUE(U43),"") | W43: Reactive | X43: 0.57 | Y43: 6.0571 | AA43: Reactive | AB43: =IF(LEFT(AC43,1)=">","Upper censored",IF(AC43="*****","Not tested","Normal")) -> Upper censored | AC43: >120 | AE43: =IF(ISBLANK(AF43),"",IF(LEFT(AF43,1)=">","Upper censored",IF(AF43="*****","Not tested","Normal"))) | AG43: =IF(ISBLANK(AF43),"",IFERROR(VALUE(AF43),"")) | AH43: Reactive | AI43: 2.605 | AJ43: 3.067 | AL43: Reactive | AM43: 210 | AN43: 0 | AO43: =IF(ISBLANK(AM43),"",IF(AM43=92,IF(T43="Upper censored",120,""),IF(AB43="Upper censored",120,""))) -> 120
A44: US-184 | B44: Male | C44: No | D44: 18.2 | E44: Normal Weight | F44: Unvaccinated | I44: 15 | J44: S4 | K44: Reactive | L44: =IF(LEFT(M44,1)=">","Upper censored",IF(M44="*****","Not tested","Normal")) -> Normal | M44: 15.814 | N44: =IFERROR(VALUE(M44),"") -> 15.814 | O44: Reactive | P44: 0.712 | Q44: 0.4642 | S44: Negative | T44: =IF(LEFT(U44,1)=">","Upper censored",IF(U44="*****","Technical failure","Normal")) -> Technical failure | U44: ***** | V44: =IFERROR(VALUE(U44),"") | W44: Not tested | X44: 3.462 | Y44: 0.5493 | AA44: Negative | AB44: =IF(LEFT(AC44,1)=">","Upper censored",IF(AC44="*****","Not tested","Normal")) -> Upper censored | AC44: >120 | AE44: =IF(ISBLANK(AF44),"",IF(LEFT(AF44,1)=">","Upper censored",IF(AF44="*****","Not tested","Normal"))) | AG44: =IF(ISBLANK(AF44),"",IFERROR(VALUE(AF44),"")) | AH44: Reactive | AI44: 2.835 | AJ44: 6.2376 | AL44: Reactive | AM44: 210 | AN44: 0 | AO44: =IF(ISBLANK(AM44),"",IF(AM44=92,IF(T44="Upper censored",120,""),IF(AB44="Upper censored",120,""))) -> 120
A45: US-535 | B45: Male | C45: No | D45: 15.9 | E45: Normal Weight | F45: Unvaccinated | I45: 12 | J45: S1 | K45: Reactive | L45: =IF(LEFT(M45,1)=">","Upper censored",IF(M45="*****","Not tested","Normal")) -> Normal | M45: 16.2814 | N45: =IFERROR(VALUE(M45),"") -> 16.2814 | O45: Reactive | P45: 0.716 | Q45: 4.4161 | S45: Reactive | T45: =IF(LEFT(U45,1)=">","Upper censored",IF(U45="*****","Technical failure","Normal")) -> Upper censored | U45: >120 | V45: =IFERROR(VALUE(U45),"") | W45: Reactive | X45: 2.689 | Y45: 5.9366 | AA45: Reactive | AB45: =IF(LEFT(AC45,1)=">","Upper censored",IF(AC45="*****","Not tested","Normal")) -> Upper censored | AC45: >120 | AE45: =IF(ISBLANK(AF45),"",IF(LEFT(AF45,1)=">","Upper censored",IF(AF45="*****","Not tested","Normal"))) | AG45: =IF(ISBLANK(AF45),"",IFERROR(VALUE(AF45),"")) | AH45: Reactive | AI45: 3.155 | AJ45: 3.7701 | AL45: Reactive | AO45: =IF(ISBLANK(AM45),"",IF(AM45=92,IF(T45="Upper censored",120,""),IF(AB45="Upper censored",120,"")))
A46: US-165 | B46: Male | D46: 16.5 | E46: Normal Weight | F46: Unvaccinated | I46: 12 | J46: S1 | K46: Reactive | L46: =IF(LEFT(M46,1)=">","Upper censored",IF(M46="*****","Not tested","Normal")) -> Normal | M46: 17.7519 | N46: =IFERROR(VALUE(M46),"") -> 17.7519 | O46: Reactive | P46: 0.787 | Q46: 0.6091 | S46: Negative | T46: =IF(LEFT(U46,1)=">","Upper censored",IF(U46="*****","Technical failure","Normal")) -> Upper censored | U46: >120 | V46: =IFERROR(VALUE(U46),"") | W46: Reactive | X46: 3.5 | Y46: 0.3722 | AA46: Negative | AB46: =IF(LEFT(AC46,1)=">","Upper censored",IF(AC46="*****","Not tested","Normal")) -> Upper censored | AC46: >120 | AE46: =IF(ISBLANK(AF46),"",IF(LEFT(AF46,1)=">","Upper censored",IF(AF46="*****","Not tested","Normal"))) | AG46: =IF(ISBLANK(AF46),"",IFERROR(VALUE(AF46),"")) | AH46: Reactive | AI46: 2.118 | AJ46: 5.7107 | AL46: Negative | AM46: 210 | AN46: 0 | AO46: =IF(ISBLANK(AM46),"",IF(AM46=92,IF(T46="Upper censored",120,""),IF(AB46="Upper censored",120,""))) -> 120
A47: US-518 | B47: Male | D47: 21 | E47: Normal Weight | F47: Unvaccinated | I47: 15 | J47: S4 | K47: Negative | L47: =IF(LEFT(M47,1)=">","Upper censored",IF(M47="*****","Not tested","Normal")) -> Normal | M47: 18.7186 | N47: =IFERROR(VALUE(M47),"") -> 18.7186 | O47: Reactive | P47: 0.813 | Q47: 4.1943 | S47: Reactive | T47: =IF(LEFT(U47,1)=">","Upper censored",IF(U47="*****","Technical failure","Normal")) -> Upper censored | U47: >120 | V47: =IFERROR(VALUE(U47),"") | W47: Reactive | X47: 2.793 | Y47: 5.7368 | AA47: Reactive | AB47: =IF(LEFT(AC47,1)=">","Upper censored",IF(AC47="*****","Not tested","Normal")) -> Not tested | AC47: ***** | AE47: =IF(ISBLANK(AF47),"",IF(LEFT(AF47,1)=">","Upper censored",IF(AF47="*****","Not tested","Normal"))) | AG47: =IF(ISBLANK(AF47),"",IFERROR(VALUE(AF47),"")) | AH47: Not tested | AI47: 1.61 | AJ47: 2.7349 | AL47: Reactive | AM47: 210 | AN47: 0 | AO47: =IF(ISBLANK(AM47),"",IF(AM47=92,IF(T47="Upper censored",120,""),IF(AB47="Upper censored",120,"")))
